Workbook
Name ___xlnm._FilterDatabase_1: #REF!
Name ___xlnm._FilterDatabase_1: #REF!
Name ___xlnm._FilterDatabase_1: #REF!
Name ___xlnm._FilterDatabase_1: #REF!
Name ___xlnm._FilterDatabase_1: #REF!
Name ___xlnm._FilterDatabase_1: #REF!
Name __xlnm._FilterDatabase_1: #REF!
Name __xlnm._FilterDatabase_1: #REF!
Name __xlnm._FilterDatabase_1: #REF!
Name __xlnm._FilterDatabase_1: #REF!
Name __xlnm._FilterDatabase_1: #REF!
Name __xlnm._FilterDatabase_1: #REF!
Name Capex: #REF!

Sheet ИНФ
B1: Заполнить
B2: Договор № | C2: ТО-ЭСТ-РО-2025 | D2: 46111
B3: Договор от | C3: 45901
B4: Период | C4: ОРЕХ 2612-2613
B5: Доп название
B6: Начало | C6: 16.03.2026г
B7: Конец | C7: 29.03.2026г.
B8: Автозаполнение | C8: ООО "ЮСТК-Энергострой", 350000, г. Краснодар, ул. Сливовая, 33
B9: Автозаполнение | C9: Азаренко Р. Г.
A10: ИСПОЛНИТЕЛЬ | B10: Организация исполнителя | C10: ООО "ЭСТ", 350005, Краснодарский край, г. Краснодар, ул. им. Александра Покрышкина д. 25/А, корп.2, помещ. 21,22,23
B11: Представитель исполнителя | C11: Нестеренко Е.В.
B12: Должность исполнителя | C12: Директор ООО "ЭСТ"
B13: ОКПО Исполнителя | C13: 91130665
A14: ЗАКАЗЧИК | B14: Представитель заказчика | C14: Мотлях К.Г.
B15: Должность заказчика | C15: Директор макрорегионального филиала "Юг" ОOO "Т2 Мобайл"
B16: Организация заказчика | C16: ООО "Т2 Мобайл", 108811, г. Москва, Киевское шоссе 22-й километр, домовладение 6, строение 1, этаж 5, комната 33
B17: ОКПО Заказчика | C17: 17872715

Sheet Работы
A1: № п/п | B1: Наименование работ* | C1: Ед. Изм. | D1: Цена за единицу в рублях без НДС
A2: 1. Антенно - фидерное устройство Объекта
A3: .1.1. | B3: Диагностика, измерение потерь оптической линии между аппаратной и оборудованием на АМС рефлектометром (длина линии, расстояние до повреждения, затухание) | C3: шт. | D3: 503
A4: 1.2. | B4: Диагностика и устранение дефектов АФУ сектора БС (локализация неисправности или перепуток Net Monitor'ом, проверка/ремонт разъёмов, соединительных джемперов, проверка КСВ) | C4: Объект | D4: 4180
A5: 1.3. | B5: Замена RF кабеля БС 1/2, RF кабеля РРЛ (с установкой креплений, заземлением, включая крепёжные элементы) | C5: м.п. | D5: 205
A6: 1.4. | B6: Замена RF кабеля БС 7/8 (с установкой креплений, заземлением, включая крепёжные элементы) | C6: м.п. | D6: 270
A7: 1.5. | B7: Замена RF кабеля GPS антенны | C7: м.п. | D7: 158
A8: 1.6. | B8: Диагностика, замена или ремонт RF разъёмов БС и RF разъёмов РРЛ N-type на АМС | C8: шт. | D8: 2365
A9: 1.7. | B9: Диагностика, замена или ремонт RF разъёмов БС и RF разъёмов РРЛ N-type в аппаратной | C9: шт. | D9: 773
A10: 1.8. | B10: Диагностика и замена outdoor джамперов 1/2" | C10: шт. | D10: 2728
A11: 1.9. | B11: Диагностика и замена indoor джамперов 1/2" | C11: шт. | D11: 1489
A12: 1.10. | B12: Диагностика и замена кабеля управления RET | C12: шт. | D12: 2104
A13: 1.11. | B13: Диагностика и замена устройств регулировки угла наклона (RET) | C13: шт. | D13: 2160
A14: 1.12. | B14: Замена, подключение и юстировка антенн базовых станций (вкл. джамперы, заземления, грозоразрядники) | C14: шт. | D14: 6935
... A25: 1.23. | B25: Измерение мощности оптического сигнала | C25: волокно | D25: 140
A26: 2. Оборудование Объекта
A27: 2.1. | B27: Диагностика и замена модуля передатчиков БС в аппаратной, включая монтаж всех крепёжных элементов и кабелей, переключение джемперов и созданием логических объектов на стороне БС | C27: шт. | D27: 1052
A28: 2.2. | B28: Диагностика и замена модуля передатчиков БС на АМС, включая монтаж всех крепёжных элементов и кабелей, переключение джамперов и созданием логических объектов на стороне БС | C28: шт. | D28: 2830
A29: 2.3. | B29: Диагностика и замена системного модуля БС в аппаратной или ниже 10м на Объекте (включая монтаж всех крепёжных элементов и кабелей и создание логических объектов на стороне БС) | C29: шт. | D29: 1117
A30: 2.4. | B30: Диагностика и замена системного модуля БС на АМС (включая монтаж всех крепёжных элементов и кабелей, переключение джамперов и созданием логических объектов на стороне БС) | C30: шт. | D30: 2830
A31: 2.5. | B31: Диагностика и замена модуля в корзине БС (TCU, FIQB, FTIF, FIQA, или аналогичного) или платы расширения системы (FBBA и аналогичного) в аппаратной или ниже 10 метров на Объекте, включая монтаж всех крепёжных элементов и кабелей. Создание логических объектов на стороне БС | C31: шт. | D31: 624
A32: 2.6. | B32: Диагностика и замена модуля в корзине БС (TCU, FIQB, FTIF, FIQA, или аналогичного) или платы расширения системы (FBBA и аналогичного) на АМС, выше 10 метров, включая монтаж всех крепёжных элементов и кабелей. Создание логических объектов на стороне БС | C32: шт. | D32: 1359
A33: 2.7. | B33: Диагностика и замена корзины питания модулей DUW/DUS/TCU или аналогичных | C33: шт. | D33: 1117
A34: 2.8. | B34: Диагностика и замена оптического модуля SFP в оборудование, смонтированное в аппаратной или ниже 10 метров | C34: шт. | D34: 130
A35: 2.9. | B35: Диагностика и замена оптического модуля SFP в оборудование, смонтированное на АМС, выше 10 метров | C35: шт. | D35: 987
A36: 2.10. | B36: Замена и подключение кабелей питания DC 48В между системой питания и оборудованием БС или трансмиссии в аппаратной | C36: м.п. | D36: 400
A37: 2.11. | B37: Диагностика, замена FAN-модуля (вентиляторов в EXDA, FXEA, FXEB или аналогичных модулях) | C37: шт. | D37: 307
A38: 2.12. | B38: Диагностика, замена соединительных кабелей на АМС (Power, заземление) | C38: м.п. | D38: 484
... A53: 2.27. | B53: Чистка от загрязнения вентиляторов выпрямителей, внутренних модулей БС, трансмиссии | C53: модуль | D53: 493
A54: 3. Работы в отношении антенно - фидерного устройства радиорелейной линии (РРЛ)
A55: 3.1. | B55: Замена антенны РРЛ 0,3 м (в комплекте с радиомодулем), заземление | C55: шт. | D55: 3807
A56: 3.2. | B56: Замена антенны РРЛ 0,6 (0,9) м (в комплекте с радиомодулем), заземление | C56: шт. | D56: 5520
A57: 3.3. | B57: Замена антенны РРЛ 1,2 – 1,8 м (в комплекте с радиомодулем), заземление | C57: шт. | D57: 7727
A58: 3.4. | B58: Юстировка РРЛ пролёта (диам. от 0,3 до 0,9м) | C58: пролёт | D58: 3686
A59: 3.5. | B59: Юстировка РРЛ пролёта (диам. от 1м до 1,8) | C59: пролёт | D59: 5148
A60: 3.6. | B60: Юстировка РРЛ полупролета (диам. от 0,3 до 0,9м) | C60: полупролёт | D60: 1843
A61: 3.7. | B61: Юстировка РРЛ полупролета (диам. от 1м до 1,8) | C61: полупролёт | D61: 2579
A62: 3.8. | B62: Диагностика, замена, ремонт заземления РРЛ-фидера (Комплект на один фидер) | C62: комплект | D62: 484
A63: 3.9. | B63: Восстановление крепления кабелей РРЛ, оптических кабелей, цифровых кабелей (1xAlarm, 1xLMP, 4xE1, 2xEthernet), кабелей питания DC (СИП 4*35, 4*50, ВБбШв2*25) по кабельному мосту, АМС включая зажимы, стяжки | C63: м.п. | D63: 158
A64: 3.10. | B64: Герметизация соединения оптического кабеля (между системным блоком и радиоблоком) включая материал лента VM, лента 88Т | C64: шт. | D64: 214
A65: 3.11. | B65: Диагностика АФУ РРЛ (проверка/ремонт разъёмов, осмотр Ground Kit`ов, соединительных джамперов, КСВ фидерной трассы, поиск неисправности средствами диагностики РРЛ) | C65: линия | D65: 1545
A66: 3.12. | B66: Замена радио-блока (ODU) РРЛ с настройкой параметров магазина и внутренних блоков РРС одного полукомплекта РРС включая герметизацию RF разъёма | C66: шт. | D66: 2709
A67: 4. Работы в отношении оборудования радиорелейной линии, трансмиссионного оборудования
A68: 4.1. | B68: Диагностика, замена, настройка и интеграция трансмиссионного оборудования (полукомлект РРЛ, MUX, модем, MBH, CWDM, оптический медиаконвертер (преобразователь FOL-ETH)) | C68: шт. | D68: 1238
A69: 4.2. | B69: Замена корзины РРЛ, внутренних блоков РРЛ, узла доступа, узла агрегации, включая перенос блоков, монтаж всех крепежных элементов, кабелей и интеграцию | C69: шт. | D69: 1238
A70: 4.3. | B70: Настройка параметров трансмиссионного оборудования (полукомлект РРЛ, MUX, модем, MBH) | C70: шт. | D70: 745
A71: 4.4. | B71: Замена indoor плат на трансмиссионном оборудовании (включая интеграцию) | C71: шт. | D71: 624
A72: 4.5. | B72: Замена оптического или медного патч-корда | C72: шт. | D72: 261
A73: 4.6. | B73: Кроссировка, маршрутизация и проверка потоков (независимо от кол-ва потоков) | C73: Объект | D73: 735
A74: 5. Работы в отношении энергопринимающего устройства
A75: 5.1. | B75: Диагностика и замена управляющего блока стойки питания (включая подключение и конфигурацию) | C75: шт. | D75: 735
A76: 5.2. | B76: Диагностика и замена выпрямительного модуля (включая подключение и конфигурацию) | C76: шт. | D76: 493
A77: 5.3. | B77: Осмотр и тестирование аккумуляторов источников бесперебойного питания (ИБП) по упрощенной методике (разряд на штатную нагрузку ИБП до 2 (двух) часов с измерением их параметров) | C77: ИБП | D77: 1778
A78: 5.4. | B78: Замена одной аккумуляторной батареи в группе | C78: шт. | D78: 1843
A79: 5.5. | B79: Замена группы аккумуляторных батарей | C79: шт. | D79: 7345
A80: 5.6. | B80: Замена, ремонт кабеля соединения с заземляющим устройством ГЗШ | C80: м.п. | D80: 326
A81: 5.7. | B81: Замена, ремонт вводного кабеля, кабелей электропитания оборудования | C81: м.п. | D81: 382
A82: 5.8. | B82: Замена, ремонт распределительного щита (outdoor, indoor) | C82: шт. | D82: 3081
A83: 5.9. | B83: Диагностика и замена контактора/пускателя в щите автоматического включения резерва (АВР) (без учета стоимости контактора/пускателя) | C83: шт. | D83: 1722
A84: 5.10. | B84: Диагностика и замена АСКУЭ | C84: шт. | D84: 745
A85: 5.11. | B85: Замена электросчетчика | C85: шт. | D85: 987
A86: 5.12. | B86: Замена автоматического выключателя (АВВ или аналог) или элемента устройства защиты от импульсных перенапряжений (УЗИП) или плавкой вставки или устройства защитного отключения (УЗО) или перемещение фазы подключения (без учета стоимости материалов) | C86: шт. | D86: 493
... A93: 5.19. | B93: Замена магазина автоматических выключателей 48VDC (DCDU, PDU) | C93: шт. | D93: 2020
A94: 6. Общестроительные работы
A95: 6.1. | B95: Замена розетки, выключателя (с учётом стоимости материалов) | C95: шт. | D95: 438
A96: 6.2. | B96: Ремонт, замена, внутреннего кабель-роста (демонтаж-монтаж кабель-роста и перекладка существующего кабеля) | C96: м.п. | D96: 1061
A97: 6.3. | B97: Ремонт, перемещение и замена наружного кабель-роста (демонтаж-монтаж кабель-роста и перекладка существующего кабеля) | C97: м.п. | D97: 1592
A98: 6.4. | B98: Устранение протечек (изготовление/восстановление кровли контейнера, с учетом стоимости материалов) | C98: м.кв. | D98: 2150
A99: 6.5. | B99: Изготовление ключа (с учетом стоимости материалов) | C99: шт. | D99: 745
A100: 6.6. | B100: Устранение нарушений конструкций обеспечивающих безопасность объектов (антивандальные ограждение и т.п., без учета стоимости материалов) | C100: м.кв. | D100: 2122
A101: 6.7. | B101: Ремонт и замена несущих антенных конструкций, трубостойки | C101: шт. | D101: 4040
A102: 6.8. | B102: Изготовление несущих антенных конструкций, трубостойки | C102: шт. | D102: 13247
A103: 6.9. | B103: Ремонт и замена двери (демонтаж-монтаж с расходным материалом без стоимости двери) | C103: шт. | D103: 5827
A104: 6.10. | B104: Ремонт стен, потолка, пола, включая покраску | C104: м.кв. | D104: 1061
A105: 6.11. | B105: Покраска металлоконструкций | C105: м.кв. | D105: 568
A106: 6.12. | B106: Ремонт антистатического линолеума | C106: м.кв. | D106: 1685
... A117: 6.23. | B117: Замена основания под размещение КШ АКБ на готовое основание | C117: тонна | D117: 44358
A118: 7. Помещения Объекта
A119: 7.1. | B119: Замена перегоревших ламп и неисправных светильников в помещениях базовых станций | C119: шт. | D119: 261
A120: 8. Работы в отношении охранно-пожарной сигнализации
A121: 8.1. | B121: Диагностика и замена ОПС (комплект, включая извещатели, кодовые панели, укладку кабелей, пуско-наладку и проверку прохождения сигналов в NOC) (без учета стоимости материалов) | C121: комплект | D121: 1974
A122: 8.2. | B122: Замена аккумулятора для пожароохранной сигнализации в приёмо-контрольный прибор (без учета стоимости материалов) | C122: шт. | D122: 186
A123: 8.3. | B123: Диагностика, замена прибора приемно-контрольного (включая кодовые панели, настройку и пуско-наладку) (без учета стоимости материалов) | C123: шт. | D123: 866
A124: 8.4. | B124: Монтаж шлейфа сигнализации (кабель КСПВ) | C124: м.п. | D124: 74
A125: 8.5. | B125: Замена извещателя ОПС (дымового, инфракрасного, магнитоконтактного, без стоимости материалов) | C125: шт. | D125: 130
A126: 9. Драйв-тесты (Работы по радиоизмерению качества и покрытия сети)***
A127: 9.1. | B127: Стоимость Работ по проведению Драйв-теста Indoor продолжительностью Работ до 5 часов на одном Объекте тестирования | C127: Объект тестирования | D127: 3677
A128: 9.2. | B128: Стоимость Работ по проведению Драйв-теста Indoor, свыше 5 часов на одном Объекте тестирования. Ставка применяется по истечению 5 (пятого) часа выполнения Работ | C128: час | D128: 735
A129: 9.3. | B129: Стоимость Работ по проведению Драйв-теста Outdoor, независимо от времени выполнения Работ | C129: км | D129: 49.34
A130: 10. Иные Работы
A131: 10.1. | B131: Покос травы, вырубка поросли, обработка реагентами, уборка на территории размещения Объекта | C131: м.кв. | D131: 130
A132: 10.2. | B132: Оказание содействия при проведении государственного контроля (надзора), муниципального контроля организации и проведения проверок на территории размещения Объектов органами, уполномоченными на осуществление государственного контроля (надзора), муниципального контроля, либо оперативных - розыскных мероприятий уполномоченными органами по факту хищения оборудования Объектов | C132: час | D132: 735
A133: 10.3. | B133: Иные работы/услуги в отношении одного Объекта по одному обращению Заказчика в течение рабочего времени*****, независимо от количества представителей Подрядчика, участвующих в выполнении таких Работ на одном Объекте | C133: час | D133: 735
A134: 10.4. | B134: Работы по осмотру и проверке работоспособности нового Объекта. Оплата Работ по Драйв-тесту, выполняемых в ходе осмотра и проверки работоспособности нового Объекта, осуществляется отдельно в соответствии с условиями пункта 9 настоящего Приложения №10.3 | C134: Объект | D134: 3221
A135: 10.5. | B135: Обследование с целью определения схем монтажа комплекта радиоретранслятора, small-cell, пико-соты и т.д. | C135: Объект | D135: 2942
A136: 10.6. | B136: Организация минерализованной полосы шириной до 1,5 м. | C136: м.п. | D136: 447
A137: 10.7. | B137: Маркировка РЭС в соответствии с требованиями законодательства РФ (расклейка маркировочных табличек) | C137: Объект | D137: 1750
A138: 11. Материалы
A139: 11.1. | B139: Кабель питания DC (СИП 4*35) | C139: м.п. | D139: 214
A140: 11.2. | B140: Кабель питания DC (СИП 4*50) | C140: м.п. | D140: 289
...

Sheet Расстояния
A1: № пп | B1: № Объекта (БС) | C1: Тип Объекта * | D1: Адрес БС (ДС от 15.08.2023) | E1: Срок реагирования, в часах | F1: Объект находится в труднодоступной местности (ДА / НЕТ) | G1: Требуется авиа-/жд транспорт или иное (ДА / НЕТ, УКАЗАТЬ ВИД) | H1: Возможность компенсации длительного пребывания (ДА / НЕТ) | I1: Место нахождения комплекта ключей | J1: Расстояние до Объекта, км | K1: Осн./Доп. | L1: GPS-широта | M1: GPS-долгота
A2: 1 | B2: RO0305 | C2: 22:собст. АМС выше 10 м на крыше | D2: Егорлыкский район, станица Егорлыкская, улица Чапаева, 144 | E2: 2.62 | F2: нет | G2: нет | H2: нет | I2: Сальск | J2: 81 | K2: осн. | L2: 46.58075 | M2: 40.654667
A3: =A2+1 -> 2 | B3: RO0306 | C3: 21:собст. АМС до 10 м на крыше | D3: Целинский район, поселок Целина, 1-я линия, №1 | E3: 1.94 | F3: нет | G3: нет | H3: нет | I3: Сальск | J3: 47 | K3: осн. | L3: 46.53825 | M3: 41.061333
A4: =A3+1 -> 3 | B4: RO0307 | C4: 21:собст. АМС до 10 м на крыше | D4: Сальский район, г. Сальск, улица Промышленная, 1 | E4: 1.22 | F4: нет | G4: нет | H4: нет | I4: Сальск | J4: 11 | K4: осн. | L4: 46.473639 | M4: 41.564833
A5: =A4+1 -> 4 | B5: RO0308 | C5: 32:трубостойки/АМС на: трубе, элеваторе, водонап.башне | D5: Район Сальский, Город Сальск, Улица Николая Островского 6-е | E5: 1.28 | F5: нет | G5: нет | H5: нет | I5: Сальск | J5: 14 | K5: осн. | L5: 46.456389 | M5: 41.538889
A6: =A5+1 -> 5 | B6: RO0309 | C6: 31:трубостойки на чужой АМС на земле/крыше | D6: Сальский район, поселок Конезавод им. Буденного, улица Сальская, 53 | E6: 1 | F6: нет | G6: нет | H6: нет | I6: Сальск | J6: 0 | K6: осн. | L6: 46.538361 | M6: 41.577833
A7: =A6+1 -> 6 | B7: RO0310 | C7: 21:собст. АМС до 10 м на крыше | D7: Пролетарский район, г. Пролетарск, улица Чкалова, 12 | E7: 1.48 | F7: нет | G7: нет | H7: нет | I7: Сальск | J7: 24 | K7: осн. | L7: 46.71075 | M7: 41.70775
A8: =A7+1 -> 7 | B8: RO0311 | C8: 31:трубостойки на чужой АМС на земле/крыше | D8: Сальский район, поселок Гигант, улица Автодорожная, 66 | E8: 1.46 | F8: нет | G8: нет | H8: нет | I8: Сальск | J8: 23 | K8: осн. | L8: 46.515833 | M8: 41.356972
A9: =A8+1 -> 8 | B9: RO0312 | C9: 31:трубостойки на чужой АМС на земле/крыше | D9: Сальский район, село Новый Егорлык, улица Советская, 17А | E9: 1.78 | F9: нет | G9: нет | H9: нет | I9: Сальск | J9: 39 | K9: осн. | L9: 46.407667 | M9: 41.853639
A10: =A9+1 -> 9 | B10: RO0313 | C10: 31:трубостойки на чужой АМС на земле/крыше | D10: Орловский район, поселок Орловский, улица Ленина, 252 | E10: 2.24 | F10: нет | G10: нет | H10: нет | I10: Сальск | J10: 62 | K10: осн. | L10: 46.867667 | M10: 42.080472
A11: =A10+1 -> 10 | B11: RO0317 | C11: 13:собст. железобетонный столб с заглубленным фундаментом | D11: Сальский район, г. Сальск, улица Павлова, 2 | E11: 1.22 | F11: нет | G11: нет | H11: нет | I11: Сальск | J11: 11 | K11: осн. | L11: 46.475361 | M11: 41.532639
A12: =A11+1 -> 11 | B12: RO0318 | C12: 13:собст. железобетонный столб с заглубленным фундаментом | D12: Сальский район, г. Сальск, улица Юннатов, 3/2 | E12: 1.18 | F12: нет | G12: нет | H12: нет | I12: Сальск | J12: 9 | K12: осн. | L12: 46.485833 | M12: 41.550556
A13: =A12+1 -> 12 | B13: RO0319 | C13: 13:собст. железобетонный столб с заглубленным фундаментом | D13: Пролетарский район, г. Пролетарск, улица 50 лет Октября, 24 | E13: 1.5 | F13: нет | G13: нет | H13: нет | I13: Сальск | J13: 25 | K13: осн. | L13: 46.698056 | M13: 41.727778
A14: =A13+1 -> 13 | B14: RO0321 | C14: 13:собст. железобетонный столб с заглубленным фундаментом | D14: Сальский район, г. Сальск, улица Свободы, 302А/2 | E14: 1.3 | F14: нет | G14: нет | H14: нет | I14: Сальск | J14: 15 | K14: осн. | L14: 46.470556 | M14: 41.511944
... A1700: =A1699+1 -> 1699 | B1700: RO2832 | C1700: 30:трубостойки на АМС БК Пилар | D1700: Область Ростовская, Район Заветинский, Хутор Шебалин\примерно 15 м по направлению на север от границ земельного участка по адресу: ул. Гагарина, 7, кв.2 | E1700: 3.96 | F1700: нет | G1700: нет | H1700: нет | I1700: Волгодонск | J1700: 148 | K1700: доп. | L1700: 47.36459 | M1700: 43.61736
B1701: RO2370 | F1701: нет | G1701: нет | H1701: нет | J1701: 70 | K1701: осн.
B1702: RO2541 | F1702: нет | G1702: нет | H1702: нет | J1702: 25 | K1702: осн.
B1703: RO1219 | F1703: нет | G1703: нет | H1703: нет | J1703: 15 | K1703: осн.
B1704: RO0466 | F1704: нет | G1704: нет | H1704: нет | J1704: 50 | K1704: осн.
B1705: RO1169 | F1705: нет | G1705: нет | H1705: нет | J1705: 40 | K1705: осн.
B1706: RO2446 | F1706: нет | G1706: нет | H1706: нет | J1706: 5 | K1706: осн.
B1707: RO2976 | F1707: нет | G1707: нет | H1707: нет | J1707: 15 | K1707: осн.
B1708: RO1478 | F1708: нет | G1708: нет | H1708: нет | J1708: 58 | K1708: осн.
B1709: RO0869 | F1709: нет | G1709: нет | H1709: нет | I1709: Сальская | J1709: 88 | K1709: осн.
B1710: RO1384 | F1710: нет | G1710: нет | H1710: нет | I1710: Таганрогская | J1710: 33 | K1710: осн.
B1711: RO1478 | F1711: нет | G1711: нет | H1711: нет | I1711: Таганрогская | J1711: 54 | K1711: осн.
B1712: RO2277 | F1712: нет | G1712: нет | H1712: нет | I1712: Сальская | J1712: 30 | K1712: осн.
B1713: RO2339 | F1713: нет | G1713: нет | H1713: нет | I1713: Таганрогская | J1713: 10 | K1713: осн.
B1714: RO2717 | F1714: нет | G1714: нет | H1714: нет | I1714: Таганрогская | J1714: 62 | K1714: осн.
B1715: RO0950 | F1715: нет | G1715: нет | H1715: нет | I1715: Таганрогская | J1715: 48 | K1715: осн.
B1716: RO1064 | F1716: нет | G1716: нет | H1716: нет | I1716: Таганрогская NEW | J1716: 72 | K1716: осн.
B1717: RO1181 | F1717: нет | G1717: нет | H1717: нет | I1717: Таганрогская | J1717: 55 | K1717: осн.
B1718: RO1253 | F1718: нет | G1718: нет | H1718: нет | I1718: Сальская | J1718: 14 | K1718: осн.
B1719: RO1312 | F1719: нет | G1719: нет | H1719: нет | I1719: Таганрогская | J1719: 14 | K1719: осн.
B1720: RO2044 | F1720: нет | G1720: нет | H1720: нет | I1720: Таганрогская | J1720: 38 | K1720: осн.
... B1724: RO2969 | F1724: нет | G1724: нет | H1724: нет | I1724: Таганрогская | J1724: 6 | K1724: осн.
B1725: RO1983 | F1725: нет | G1725: нет | H1725: нет | J1725: 16 | K1725: осн.
B1726: RO1196 | F1726: нет | G1726: нет | H1726: нет | J1726: 64 | K1726: осн.
B1727: RO0498 | F1727: нет | G1727: нет | H1727: нет | J1727: 66 | K1727: осн.
B1728: RO1984 | F1728: нет | G1728: нет | H1728: нет | J1728: 69 | K1728: осн.
B1729: RO2646 | F1729: нет | G1729: нет | H1729: нет | J1729: 107 | K1729: осн.
B1730: RD0015 | F1730: нет | G1730: нет | H1730: нет | J1730: 45 | K1730: осн.
B1731: RO2648 | F1731: нет | G1731: нет | H1731: нет | J1731: 93 | K1731: осн.
B1732: RO2564 | F1732: нет | G1732: нет | H1732: нет | J1732: 40 | K1732: осн.
B1733: RO2512 | F1733: нет | G1733: нет | H1733: нет | J1733: 73 | K1733: осн.
B1734: RO1636 | F1734: нет | G1734: нет | H1734: нет | J1734: 95 | K1734: осн.
B1735: RO2508 | F1735: нет | G1735: нет | H1735: нет | J1735: 100 | K1735: осн.
B1736: RO2051 | F1736: нет | G1736: нет | H1736: нет | J1736: 72 | K1736: осн.
B1737: RO2703 | F1737: нет | G1737: нет | H1737: нет | J1737: 90 | K1737: осн.
B1738: RO2981 | F1738: нет | G1738: нет | H1738: нет | K1738: осн.
B1739: RO2616 | F1739: нет | G1739: нет | H1739: нет | J1739: 3 | K1739: осн.
B1740: RO2675 | F1740: нет | G1740: нет | H1740: нет | J1740: 85 | K1740: осн.
B1741: RO1173 | F1741: нет | G1741: нет | H1741: нет | J1741: 63 | K1741: осн.
B1742: RO1291 | F1742: нет | G1742: нет | H1742: нет | J1742: 101 | K1742: осн.
B1743: RO2668 | F1743: нет | G1743: нет | H1743: нет | J1743: 40 | K1743: осн.
B1744: RO0878 | F1744: нет | G1744: нет | H1744: нет | J1744: 68 | K1744: осн.
B1745: RO2673 | F1745: нет | G1745: нет | H1745: нет | J1745: 34 | K1745: осн.
B1746: RO0878 | F1746: нет | G1746: нет | H1746: нет | J1746: 62 | K1746: осн.
B1747: RO1925 | F1747: нет | G1747: нет | H1747: нет | J1747: 63 | K1747: осн.
B1748: RO2668 | F1748: нет | G1748: нет | H1748: нет | J1748: 25 | K1748: осн.
B1749: RO1603 | F1749: нет | G1749: нет | H1749: нет | J1749: 76 | K1749: осн.
B1750: RO1194 | F1750: нет | G1750: нет | H1750: нет | J1750: 75 | K1750: осн.
... B1764: RO1093 | F1764: нет | G1764: нет | H1764: нет | J1764: 40 | K1764: осн.
B1765: RO2902 | F1765: нет | G1765: нет | H1765: нет | K1765: осн.
B1766: RO2258 | F1766: нет | G1766: нет | H1766: нет | J1766: 126 | K1766: осн.
B1767: RO1042 | F1767: нет | G1767: нет | H1767: нет | J1767: 45 | K1767: осн.
B1768: RO0976 | F1768: нет | G1768: нет | H1768: нет | J1768: 26 | K1768: осн.
B1769: RO2451 | F1769: нет | G1769: нет | H1769: нет | J1769: 8 | K1769: осн.

Sheet Opex
M1: ПРИЛОЖЕНИЕ № 8 (Общий отчет)
M2: к Договору на выполнение работ
N3: № ТО-ЭСТ-РО-2025 от «01» сентября 2025 г.
A5: Отчет о выполнении Аварийно-восстановительных и Оперативных работ и работ по Техническому обслуживанию по типу расходов ОрЕх | P5: за период | T5: =CONCATENATE(ИНФ!C4, " ", ИНФ!C6, "-", ИНФ!C7) -> ОРЕХ 2612-2613 16.03.2026г-29.03.2026г.
B7: г. Ростов-на-Дону | N7: =ИНФ!D2 -> 46111
A8: Общество с ограниченной ответственностью «Т2-Мобайл» (Ростовский филиал) (сокращенное наименование ООО «Т2 Мобайл» Ростовский филиал), юридическое лицо, зарегистрированное по адресу: Российская Федерация, 108811, г. Москва, поселение Московский, Киевское шоссе 22-й километр, домовладение 6, строение 1, этаж 5, комната 33, в лице Руководителя Макрорегионального филиала "Юг" Общества с ограниченной ответственностью «Т2 Мобайл» Мотлях Константина Геннадьевича, действующего на основании доверенности №77/447-н/77-2024-3-169 от 15.02.2024 г. , именуемое в дальнейшем «Заказчик», с одной стороны, и Общество с ограниченной ответственностью «Эффективные сервисные технологии», юридическое лицо, зарегистрированное по адресу: Российская Федерация, 3350005, Краснодарский край, г. Краснодар, ул. им. Александра Покрышкина д. 25/А, корп.2, помещ. 21,22,23, в лице Директора Нестеренко Евгения Викторовича, действующего на основании Устава, именуемое в дальнейшем «Подрядчик», с другой стороны, совместно именуемые «Стороны», а по отдельности - «Сторона», составили Отчет о выполнении Аварийно – восстановительных и Оперативных работ и работ по Техническому обслуживанию к Акту выполненных работ № _____ от «__» ________ 20_ г. к Договору на выполнение работ № ТО-ЭСТ-РО-2025 от «01» сентября 2025 г. о нижеследующем:
O9: Оперативные работы, ТО, Инвентаризация | Q9: АВР по обеспечению временного энергоснабжения | U9: АВР
A10: № п/п | B10: № Объекта | C10: Расстояние до объекта | D10: Объект (основной/дополнительный) | E10: Объект, находящийся в труднодоступной местности | F10: Номер заявки | G10: Дата, Время заявки | H10: Дата и Время появления Подрядчика на Объекте | I10: Дата и Время ухода Подрядчика с Объекта | J10: ФИО сотрудника Исполнителя | K10: ФИО сотрудника Заказчика | L10: № п/п работ (по приложению №10) | M10: Наименование работ (по приложению №10) | N10: Описание фактически выполненных работ | O10: Оперативные работы, ТО, Инвентаризация. Количество | P10: Оперативные работы, ТО, Инвентаризация. Цена за единицу в рублях без НДС) | Q10: Генерация, ч | R10: Генерация более 24ч, сутки | S10: Генерация более 72ч, сутки | T10: Генерация, цена за единицу (в руб без НДС) | U10: АВР менее 5 часов в рабочее время, стоимость (в руб. без НДС) | V10: АВР менее 5 часов во внерабочее время, стоимость (в руб. без НДС) | W10: АВР свыше 5 часов в рабочее время (Ставка применяется по истечению 5 часа выполнения АВР), час | X10: АВР свыше 5 часов в нерабочее время (Ставка применяется по истечению 5 часа выполнения АВР), час | Y10: АВР свыше 5 часов (Ставка применяется по истечению 5 часа выполнения АВР) Цена за час (в руб. без НДС) | Z10: Отмена задания АВР, стоимость (в руб. без НДС) | AA10: Стоимость работ в заявке (в руб. без НДС) | AB10: Наименование Оборудования (Материалов), купленного по согласованию с Заказчиком | AC10: Кол-во Оборудования (Материалов), купленного по согласованию с Заказчиком | AD10: Стоимость Оборудования (Материалов), купленного по согласованию с Заказчиком руб. за штуку, без НДС | AE10: Общая стоимость Оборудования (Материалов), купленного по согласованию с Заказчиком,руб. без НДС | AF10: Стоимость километража, руб. | AG10: Стоимость Заявки с учетом километража, материалов и локации объекта, руб. без НДС | AH10: Тип штрафа согласно договору (пункт договора) | AI10: Размер штрафных санкций в процентах от стоимости работ | AJ10: Итоговая Стоимость Заявки с учетом штрафных санкций (руб. без НДС) | AK10: Счет ТПС (SAP) | AL10: Оплата за трудный доступ | AM10: Доплата по дополнительному объекту
A11: =ROW(A11)-10 -> 1 | B11: RO2821 | C11: 92 | D11: =VLOOKUP(B11, Расстояния!B:K, 10, 0) -> доп. | E11: =VLOOKUP(B11, Расстояния!B:F, 5, 0) -> нет | F11: WO06719799 | G11: 46104.678 | H11: 46104.698 | I11: 46104.747 | J11: Голиков | L11: 3.1.1. | M11: =VLOOKUP(L11, Работы!A:B, 2, 0) -> Стоимость аварийно-восстановительных работ, заявка по которым получена в течение рабочего времени | N11: Работы по заданию | P11: =IF(OR(L11="3.3.1.", L11="3.3.2.", L11="3.3.3.", L11="3.1.1.", L11="3.1.2.", L11="3.4.1.", L11="3.4.2."), 0, VLOOKUP(L11, Работы!$A$3:$D$184, 4, 0)) -> 0 | T11: =IF(OR(L11="3.3.1.", L11="3.3.2.", L11="3.3.3."), VLOOKUP(L11, Работы!$A$3:$D$184, 4, 0), 0) -> 0 | U11: =IF(OR(L11="3.1.1."), VLOOKUP(L11, Работы!$A$3:$D$184, 4, 0), 0) -> 3956 | V11: =IF(OR(L11="3.1.2."), VLOOKUP(L11, Работы!$A$3:$D$184, 4, 0), 0) -> 0 | Y11: =IF(OR(L11="3.2.1.", L11="3.2.2."), VLOOKUP(L11, Работы!$A$3:$D$184, 4, 0), 0) -> 0 | Z11: =IF(OR(L11="3.4.1.", L11="3.4.2."), VLOOKUP(L11, Работы!$A$3:$D$184, 4, 0), 0) -> 0 | AA11: =P11*O11+Q11*T11+R11*T11+S11*T11+U11+V11+W11*Y11+X11*Y11+Z11 -> 3956 | AE11: =AC11*AD11 -> 0 | AF11: =C11*Работы!$D$180 -> 4950.52 | AG11: =AA11+AE11+AF11+AL11+AM11 -> 9302.12 | AJ11: =AG11-AA11*AI11 -> 9302.12 | AK11: исправить километраж на "24" как в договоре | AL11: =IF(OR(E11="да"), 4040, 0) -> 0 | AM11: =IF(OR(D11="доп."), AA11*0.1, 0) -> 395.6
A12: =ROW(A12)-10 -> 2 | B12: RO2234 | C12: =VLOOKUP(B12, Расстояния!B:J, 9, 0) -> 71 | D12: =VLOOKUP(B12, Расстояния!B:K, 10, 0) -> осн. | E12: =VLOOKUP(B12, Расстояния!B:F, 5, 0) -> нет | F12: WO06718313 | G12: 46102.521 | H12: 46102.592 | I12: 46102.691 | J12: Шведков | L12: 10.3. | M12: =VLOOKUP(L12, Работы!A:B, 2, 0) -> Иные работы/услуги в отношении одного Объекта по одному обращению Заказчика в течение рабочего времени*****, независимо от количества представителей Подрядчика, участвующих в выполнении таких Работ на одном Объекте | N12: Диагностика ВЭС | O12: 1 | P12: =IF(OR(L12="3.3.1.", L12="3.3.2.", L12="3.3.3.", L12="3.1.1.", L12="3.1.2.", L12="3.4.1.", L12="3.4.2."), 0, VLOOKUP(L12, Работы!$A$3:$D$184, 4, 0)) -> 735 | T12: =IF(OR(L12="3.3.1.", L12="3.3.2.", L12="3.3.3."), VLOOKUP(L12, Работы!$A$3:$D$184, 4, 0), 0) -> 0 | U12: =IF(OR(L12="3.1.1."), VLOOKUP(L12, Работы!$A$3:$D$184, 4, 0), 0) -> 0 | V12: =IF(OR(L12="3.1.2."), VLOOKUP(L12, Работы!$A$3:$D$184, 4, 0), 0) -> 0 | Y12: =IF(OR(L12="3.2.1.", L12="3.2.2."), VLOOKUP(L12, Работы!$A$3:$D$184, 4, 0), 0) -> 0 | Z12: =IF(OR(L12="3.4.1.", L12="3.4.2."), VLOOKUP(L12, Работы!$A$3:$D$184, 4, 0), 0) -> 0 | AA12: =P12*O12+Q12*T12+R12*T12+S12*T12+U12+V12+W12*Y12+X12*Y12+Z12 -> 735 | AE12: =AC12*AD12 -> 0 | AF12: =C12*Работы!$D$180 -> 3820.51 | AG12: =AA12+AE12+AF12+AL12+AM12 -> 4555.51 | AJ12: =AG12-AA12*AI12 -> 4555.51 | AK12: удалить километраж, есть в WO06714417 | AL12: =IF(OR(E12="да"), 4040, 0) -> 0 | AM12: =IF(OR(D12="доп."), AA12*0.1, 0) -> 0
A13: =ROW(A13)-10 -> 3 | B13: RO0005 | C13: =VLOOKUP(B13, Расстояния!B:J, 9, 0) -> 61 | D13: =VLOOKUP(B13, Расстояния!B:K, 10, 0) -> осн. | E13: =VLOOKUP(B13, Расстояния!B:F, 5, 0) -> нет | F13: WO06714501 | G13: 46098.535 | H13: 46098.61 | I13: 46098.719 | J13: Шведков | L13: 3.3.1. | M13: =VLOOKUP(L13, Работы!A:B, 2, 0) -> Стоимость Аварийно-восстановительных работ по обеспечению временного электроснабжения. (Ставка применяется с 1 часа выполнения Работ, для оплаты каждых не полных суток выполнения Работ) | N13: Генерация | P13: =IF(OR(L13="3.3.1.", L13="3.3.2.", L13="3.3.3.", L13="3.1.1.", L13="3.1.2.", L13="3.4.1.", L13="3.4.2."), 0, VLOOKUP(L13, Работы!$A$3:$D$184, 4, 0)) -> 0 | Q13: =ROUNDUP((I13-H13)*24, 0) -> 3 | T13: =IF(OR(L13="3.3.1.", L13="3.3.2.", L13="3.3.3."), VLOOKUP(L13, Работы!$A$3:$D$184, 4, 0), 0) -> 903 | U13: =IF(OR(L13="3.1.1."), VLOOKUP(L13, Работы!$A$3:$D$184, 4, 0), 0) -> 0 | V13: =IF(OR(L13="3.1.2."), VLOOKUP(L13, Работы!$A$3:$D$184, 4, 0), 0) -> 0 | Y13: =IF(OR(L13="3.2.1.", L13="3.2.2."), VLOOKUP(L13, Работы!$A$3:$D$184, 4, 0), 0) -> 0 | Z13: =IF(OR(L13="3.4.1.", L13="3.4.2."), VLOOKUP(L13, Работы!$A$3:$D$184, 4, 0), 0) -> 0 | AA13: =P13*O13+Q13*T13+R13*T13+S13*T13+U13+V13+W13*Y13+X13*Y13+Z13 -> 2709 | AE13: =AC13*AD13 -> 0 | AF13: =C13*Работы!$D$180 -> 3282.41 | AG13: =AA13+AE13+AF13+AL13+AM13 -> 5991.41 | AJ13: =AG13-AA13*AI13 -> 5991.41 | AL13: =IF(OR(E13="да"), 4040, 0) -> 0 | AM13: =IF(OR(D13="доп."), AA13*0.1, 0) -> 0
A14: =ROW(A14)-10 -> 4 | B14: RO0005 | C14: 0 | D14: =VLOOKUP(B14, Расстояния!B:K, 10, 0) -> осн. | E14: =VLOOKUP(B14, Расстояния!B:F, 5, 0) -> нет | F14: WO06722800 | G14: 46106.9 | H14: 46106.912 | I14: 46106.912 | J14: Шведков | L14: 3.4.2. | M14: =VLOOKUP(L14, Работы!A:B, 2, 0) -> Стоимость отменённого вызова на Аварийно-восстановительные работы, заявка по которым получена во внерабочее время | N14: Отмена | P14: =IF(OR(L14="3.3.1.", L14="3.3.2.", L14="3.3.3.", L14="3.1.1.", L14="3.1.2.", L14="3.4.1.", L14="3.4.2."), 0, VLOOKUP(L14, Работы!$A$3:$D$184, 4, 0)) -> 0 | T14: =IF(OR(L14="3.3.1.", L14="3.3.2.", L14="3.3.3."), VLOOKUP(L14, Работы!$A$3:$D$184, 4, 0), 0) -> 0 | U14: =IF(OR(L14="3.1.1."), VLOOKUP(L14, Работы!$A$3:$D$184, 4, 0), 0) -> 0 | V14: =IF(OR(L14="3.1.2."), VLOOKUP(L14, Работы!$A$3:$D$184, 4, 0), 0) -> 0 | Y14: =IF(OR(L14="3.2.1.", L14="3.2.2."), VLOOKUP(L14, Работы!$A$3:$D$184, 4, 0), 0) -> 0 | Z14: =IF(OR(L14="3.4.1.", L14="3.4.2."), VLOOKUP(L14, Работы!$A$3:$D$184, 4, 0), 0) -> 1731 | AA14: =P14*O14+Q14*T14+R14*T14+S14*T14+U14+V14+W14*Y14+X14*Y14+Z14 -> 1731 | AE14: =AC14*AD14 -> 0 | AF14: =C14*Работы!$D$180 -> 0 | AG14: =AA14+AE14+AF14+AL14+AM14 -> 1731 | AJ14: =AG14-AA14*AI14 -> 1731 | AL14: =IF(OR(E14="да"), 4040, 0) -> 0 | AM14: =IF(OR(D14="доп."), AA14*0.1, 0) -> 0
A15: =ROW(A15)-10 -> 5 | B15: RO0005 | C15: =VLOOKUP(B15, Расстояния!B:J, 9, 0) -> 61 | D15: =VLOOKUP(B15, Расстояния!B:K, 10, 0) -> осн. | E15: =VLOOKUP(B15, Расстояния!B:F, 5, 0) -> нет | F15: WO06724161 | G15: 46107.955 | H15: 46108.026 | I15: 46111.026 | J15: Шведков | L15: 3.3.2. | M15: =VLOOKUP(L15, Работы!A:B, 2, 0) -> Стоимость Аварийно-восстановительных работ по обеспечению временного электроснабжения продолжительностью 24 часа. (Ставка применяется с 1 по 72 час выполнения Работ, для оплаты каждых полных суток (24 часа) выполнения Работ) | N15: Генерация | P15: =IF(OR(L15="3.3.1.", L15="3.3.2.", L15="3.3.3.", L15="3.1.1.", L15="3.1.2.", L15="3.4.1.", L15="3.4.2."), 0, VLOOKUP(L15, Работы!$A$3:$D$184, 4, 0)) -> 0 | R15: 3 | T15: =IF(OR(L15="3.3.1.", L15="3.3.2.", L15="3.3.3."), VLOOKUP(L15, Работы!$A$3:$D$184, 4, 0), 0) -> 32610 | U15: =IF(OR(L15="3.1.1."), VLOOKUP(L15, Работы!$A$3:$D$184, 4, 0), 0) -> 0 | V15: =IF(OR(L15="3.1.2."), VLOOKUP(L15, Работы!$A$3:$D$184, 4, 0), 0) -> 0 | Y15: =IF(OR(L15="3.2.1.", L15="3.2.2."), VLOOKUP(L15, Работы!$A$3:$D$184, 4, 0), 0) -> 0 | Z15: =IF(OR(L15="3.4.1.", L15="3.4.2."), VLOOKUP(L15, Работы!$A$3:$D$184, 4, 0), 0) -> 0 | AA15: =P15*O15+Q15*T15+R15*T15+S15*T15+U15+V15+W15*Y15+X15*Y15+Z15 -> 97830 | AE15: =AC15*AD15 -> 0 | AF15: =C15*Работы!$D$180 -> 3282.41 | AG15: =AA15+AE15+AF15+AL15+AM15 -> 101112.41 | AJ15: =AG15-AA15*AI15 -> 101112.41 | AL15: =IF(OR(E15="да"), 4040, 0) -> 0 | AM15: =IF(OR(D15="доп."), AA15*0.1, 0) -> 0
A16: =ROW(A16)-10 -> 6 | B16: RO0031 | C16: =VLOOKUP(B16, Расстояния!B:J, 9, 0) -> 67 | D16: =VLOOKUP(B16, Расстояния!B:K, 10, 0) -> осн. | E16: =VLOOKUP(B16, Расстояния!B:F, 5, 0) -> нет | H16: 46098.562 | I16: 46098.639 | J16: Черкашин | L16: 1.1. | M16: =VLOOKUP(L16, Работы!A:B, 2, 0) -> Техническое обслуживание БС | N16: Техническое обслуживание БС | O16: 1 | P16: =IF(OR(L16="3.3.1.", L16="3.3.2.", L16="3.3.3.", L16="3.1.1.", L16="3.1.2.", L16="3.4.1.", L16="3.4.2."), 0, VLOOKUP(L16, Работы!$A$3:$D$184, 4, 0)) -> 4143 | T16: =IF(OR(L16="3.3.1.", L16="3.3.2.", L16="3.3.3."), VLOOKUP(L16, Работы!$A$3:$D$184, 4, 0), 0) -> 0 | U16: =IF(OR(L16="3.1.1."), VLOOKUP(L16, Работы!$A$3:$D$184, 4, 0), 0) -> 0 | V16: =IF(OR(L16="3.1.2."), VLOOKUP(L16, Работы!$A$3:$D$184, 4, 0), 0) -> 0 | Y16: =IF(OR(L16="3.2.1.", L16="3.2.2."), VLOOKUP(L16, Работы!$A$3:$D$184, 4, 0), 0) -> 0 | Z16: =IF(OR(L16="3.4.1.", L16="3.4.2."), VLOOKUP(L16, Работы!$A$3:$D$184, 4, 0), 0) -> 0 | AA16: =P16*O16+Q16*T16+R16*T16+S16*T16+U16+V16+W16*Y16+X16*Y16+Z16 -> 4143 | AE16: =AC16*AD16 -> 0 | AF16: =C16*Работы!$D$180 -> 3605.27 | AG16: =AA16+AE16+AF16+AL16+AM16 -> 7748.27 | AJ16: =AG16-AA16*AI16 -> 7748.27 | AL16: =IF(OR(E16="да"), 4040, 0) -> 0 | AM16: =IF(OR(D16="доп."), AA16*0.1, 0) -> 0
A17: =ROW(A17)-10 -> 7 | B17: RO0034 | C17: =VLOOKUP(B17, Расстояния!B:J, 9, 0) -> 65 | D17: =VLOOKUP(B17, Расстояния!B:K, 10, 0) -> осн. | E17: =VLOOKUP(B17, Расстояния!B:F, 5, 0) -> нет | F17: WO06725961 | G17: 46110.453 | H17: 46110.531 | I17: 46110.537 | J17: Попов | L17: 3.3.1. | M17: =VLOOKUP(L17, Работы!A:B, 2, 0) -> Стоимость Аварийно-восстановительных работ по обеспечению временного электроснабжения. (Ставка применяется с 1 часа выполнения Работ, для оплаты каждых не полных суток выполнения Работ) | N17: Генерация | P17: =IF(OR(L17="3.3.1.", L17="3.3.2.", L17="3.3.3.", L17="3.1.1.", L17="3.1.2.", L17="3.4.1.", L17="3.4.2."), 0, VLOOKUP(L17, Работы!$A$3:$D$184, 4, 0)) -> 0 | Q17: =ROUNDUP((I17-H17)*24, 0) -> 1 | T17: =IF(OR(L17="3.3.1.", L17="3.3.2.", L17="3.3.3."), VLOOKUP(L17, Работы!$A$3:$D$184, 4, 0), 0) -> 903 | U17: =IF(OR(L17="3.1.1."), VLOOKUP(L17, Работы!$A$3:$D$184, 4, 0), 0) -> 0 | V17: =IF(OR(L17="3.1.2."), VLOOKUP(L17, Работы!$A$3:$D$184, 4, 0), 0) -> 0 | Y17: =IF(OR(L17="3.2.1.", L17="3.2.2."), VLOOKUP(L17, Работы!$A$3:$D$184, 4, 0), 0) -> 0 | Z17: =IF(OR(L17="3.4.1.", L17="3.4.2."), VLOOKUP(L17, Работы!$A$3:$D$184, 4, 0), 0) -> 0 | AA17: =P17*O17+Q17*T17+R17*T17+S17*T17+U17+V17+W17*Y17+X17*Y17+Z17 -> 903 | AE17: =AC17*AD17 -> 0 | AF17: =C17*Работы!$D$180 -> 3497.65 | AG17: =AA17+AE17+AF17+AL17+AM17 -> 4400.65 | AJ17: =AG17-AA17*AI17 -> 4400.65 | AL17: =IF(OR(E17="да"), 4040, 0) -> 0 | AM17: =IF(OR(D17="доп."), AA17*0.1, 0) -> 0
A18: =ROW(A18)-10 -> 8 | B18: RO0035 | C18: =VLOOKUP(B18, Расстояния!B:J, 9, 0) -> 66 | D18: =VLOOKUP(B18, Расстояния!B:K, 10, 0) -> осн. | E18: =VLOOKUP(B18, Расстояния!B:F, 5, 0) -> нет | F18: WO06724414 | G18: 46108.349 | H18: 46108.494 | I18: 46108.591 | J18: Голиков | L18: 3.1.1. | M18: =VLOOKUP(L18, Работы!A:B, 2, 0) -> Стоимость аварийно-восстановительных работ, заявка по которым получена в течение рабочего времени | N18: Переключение оптики | P18: =IF(OR(L18="3.3.1.", L18="3.3.2.", L18="3.3.3.", L18="3.1.1.", L18="3.1.2.", L18="3.4.1.", L18="3.4.2."), 0, VLOOKUP(L18, Работы!$A$3:$D$184, 4, 0)) -> 0 | T18: =IF(OR(L18="3.3.1.", L18="3.3.2.", L18="3.3.3."), VLOOKUP(L18, Работы!$A$3:$D$184, 4, 0), 0) -> 0 | U18: =IF(OR(L18="3.1.1."), VLOOKUP(L18, Работы!$A$3:$D$184, 4, 0), 0) -> 3956 | V18: =IF(OR(L18="3.1.2."), VLOOKUP(L18, Работы!$A$3:$D$184, 4, 0), 0) -> 0 | Y18: =IF(OR(L18="3.2.1.", L18="3.2.2."), VLOOKUP(L18, Работы!$A$3:$D$184, 4, 0), 0) -> 0 | Z18: =IF(OR(L18="3.4.1.", L18="3.4.2."), VLOOKUP(L18, Работы!$A$3:$D$184, 4, 0), 0) -> 0 | AA18: =P18*O18+Q18*T18+R18*T18+S18*T18+U18+V18+W18*Y18+X18*Y18+Z18 -> 3956 | AE18: =AC18*AD18 -> 0 | AF18: =C18*Работы!$D$180 -> 3551.46 | AG18: =AA18+AE18+AF18+AL18+AM18 -> 7507.46 | AJ18: =AG18-AA18*AI18 -> 7507.46 | AL18: =IF(OR(E18="да"), 4040, 0) -> 0 | AM18: =IF(OR(D18="доп."), AA18*0.1, 0) -> 0
A19: =ROW(A19)-10 -> 9 | B19: RO0035 | C19: 0 | D19: =VLOOKUP(B19, Расстояния!B:K, 10, 0) -> осн. | E19: =VLOOKUP(B19, Расстояния!B:F, 5, 0) -> нет | F19: WO06720758 | G19: 46105.469 | H19: 46108.494 | I19: 46108.591 | J19: Голиков | L19: 1.2. | M19: =VLOOKUP(L19, Работы!A:B, 2, 0) -> Диагностика и устранение дефектов АФУ сектора БС (локализация неисправности или перепуток Net Monitor'ом, проверка/ремонт разъёмов, соединительных джемперов, проверка КСВ) | N19: Проверка на перепутку | O19: 1 | P19: =IF(OR(L19="3.3.1.", L19="3.3.2.", L19="3.3.3.", L19="3.1.1.", L19="3.1.2.", L19="3.4.1.", L19="3.4.2."), 0, VLOOKUP(L19, Работы!$A$3:$D$184, 4, 0)) -> 4180 | T19: =IF(OR(L19="3.3.1.", L19="3.3.2.", L19="3.3.3."), VLOOKUP(L19, Работы!$A$3:$D$184, 4, 0), 0) -> 0 | U19: =IF(OR(L19="3.1.1."), VLOOKUP(L19, Работы!$A$3:$D$184, 4, 0), 0) -> 0 | V19: =IF(OR(L19="3.1.2."), VLOOKUP(L19, Работы!$A$3:$D$184, 4, 0), 0) -> 0 | Y19: =IF(OR(L19="3.2.1.", L19="3.2.2."), VLOOKUP(L19, Работы!$A$3:$D$184, 4, 0), 0) -> 0 | Z19: =IF(OR(L19="3.4.1.", L19="3.4.2."), VLOOKUP(L19, Работы!$A$3:$D$184, 4, 0), 0) -> 0 | AA19: =P19*O19+Q19*T19+R19*T19+S19*T19+U19+V19+W19*Y19+X19*Y19+Z19 -> 4180 | AE19: =AC19*AD19 -> 0 | AF19: =C19*Работы!$D$180 -> 0 | AG19: =AA19+AE19+AF19+AL19+AM19 -> 4180 | AJ19: =AG19-AA19*AI19 -> 4180 | AL19: =IF(OR(E19="да"), 4040, 0) -> 0 | AM19: =IF(OR(D19="доп."), AA19*0.1, 0) -> 0
A20: =ROW(A20)-10 -> 10 | B20: RO0038 | C20: 60 | D20: =VLOOKUP(B20, Расстояния!B:K, 10, 0) -> осн. | E20: =VLOOKUP(B20, Расстояния!B:F, 5, 0) -> нет | F20: WO06720033 | G20: 46105.026 | H20: 46105.101 | I20: 46105.101 | J20: Попов | L20: 3.4.2. | M20: =VLOOKUP(L20, Работы!A:B, 2, 0) -> Стоимость отменённого вызова на Аварийно-восстановительные работы, заявка по которым получена во внерабочее время | N20: Отмена | P20: =IF(OR(L20="3.3.1.", L20="3.3.2.", L20="3.3.3.", L20="3.1.1.", L20="3.1.2.", L20="3.4.1.", L20="3.4.2."), 0, VLOOKUP(L20, Работы!$A$3:$D$184, 4, 0)) -> 0 | T20: =IF(OR(L20="3.3.1.", L20="3.3.2.", L20="3.3.3."), VLOOKUP(L20, Работы!$A$3:$D$184, 4, 0), 0) -> 0 | U20: =IF(OR(L20="3.1.1."), VLOOKUP(L20, Работы!$A$3:$D$184, 4, 0), 0) -> 0 | V20: =IF(OR(L20="3.1.2."), VLOOKUP(L20, Работы!$A$3:$D$184, 4, 0), 0) -> 0 | Y20: =IF(OR(L20="3.2.1.", L20="3.2.2."), VLOOKUP(L20, Работы!$A$3:$D$184, 4, 0), 0) -> 0 | Z20: =IF(OR(L20="3.4.1.", L20="3.4.2."), VLOOKUP(L20, Работы!$A$3:$D$184, 4, 0), 0) -> 1731 | AA20: =P20*O20+Q20*T20+R20*T20+S20*T20+U20+V20+W20*Y20+X20*Y20+Z20 -> 1731 | AE20: =AC20*AD20 -> 0 | AF20: =C20*Работы!$D$180 -> 3228.6 | AG20: =AA20+AE20+AF20+AL20+AM20 -> 4959.6 | AJ20: =AG20-AA20*AI20 -> 4959.6 | AL20: =IF(OR(E20="да"), 4040, 0) -> 0 | AM20: =IF(OR(D20="доп."), AA20*0.1, 0) -> 0
A21: =ROW(A21)-10 -> 11 | B21: RO0045 | C21: =VLOOKUP(B21, Расстояния!B:J, 9, 0) -> 69 | D21: =VLOOKUP(B21, Расстояния!B:K, 10, 0) -> осн. | E21: =VLOOKUP(B21, Расстояния!B:F, 5, 0) -> нет | F21: WO06724537 | G21: 46108.403 | H21: 46108.488 | I21: 46108.741 | J21: Попов | L21: 3.3.1. | M21: =VLOOKUP(L21, Работы!A:B, 2, 0) -> Стоимость Аварийно-восстановительных работ по обеспечению временного электроснабжения. (Ставка применяется с 1 часа выполнения Работ, для оплаты каждых не полных суток выполнения Работ) | N21: Генерация | P21: =IF(OR(L21="3.3.1.", L21="3.3.2.", L21="3.3.3.", L21="3.1.1.", L21="3.1.2.", L21="3.4.1.", L21="3.4.2."), 0, VLOOKUP(L21, Работы!$A$3:$D$184, 4, 0)) -> 0 | Q21: =ROUNDUP((I21-H21)*24, 0) -> 7 | T21: =IF(OR(L21="3.3.1.", L21="3.3.2.", L21="3.3.3."), VLOOKUP(L21, Работы!$A$3:$D$184, 4, 0), 0) -> 903 | U21: =IF(OR(L21="3.1.1."), VLOOKUP(L21, Работы!$A$3:$D$184, 4, 0), 0) -> 0 | V21: =IF(OR(L21="3.1.2."), VLOOKUP(L21, Работы!$A$3:$D$184, 4, 0), 0) -> 0 | Y21: =IF(OR(L21="3.2.1.", L21="3.2.2."), VLOOKUP(L21, Работы!$A$3:$D$184, 4, 0), 0) -> 0 | Z21: =IF(OR(L21="3.4.1.", L21="3.4.2."), VLOOKUP(L21, Работы!$A$3:$D$184, 4, 0), 0) -> 0 | AA21: =P21*O21+Q21*T21+R21*T21+S21*T21+U21+V21+W21*Y21+X21*Y21+Z21 -> 6321 | AE21: =AC21*AD21 -> 0 | AF21: =C21*Работы!$D$180 -> 3712.89 | AG21: =AA21+AE21+AF21+AL21+AM21 -> 10033.89 | AJ21: =AG21-AA21*AI21 -> 10033.89 | AL21: =IF(OR(E21="да"), 4040, 0) -> 0 | AM21: =IF(OR(D21="доп."), AA21*0.1, 0) -> 0
A22: =ROW(A22)-10 -> 12 | B22: RO0045 | C22: =VLOOKUP(B22, Расстояния!B:J, 9, 0) -> 69 | D22: =VLOOKUP(B22, Расстояния!B:K, 10, 0) -> осн. | E22: =VLOOKUP(B22, Расстояния!B:F, 5, 0) -> нет | F22: WO06713613 | G22: 46097.7 | H22: 46097.777 | I22: 46098.078 | J22: Шведков | L22: 3.3.1. | M22: =VLOOKUP(L22, Работы!A:B, 2, 0) -> Стоимость Аварийно-восстановительных работ по обеспечению временного электроснабжения. (Ставка применяется с 1 часа выполнения Работ, для оплаты каждых не полных суток выполнения Работ) | N22: Генерация | P22: =IF(OR(L22="3.3.1.", L22="3.3.2.", L22="3.3.3.", L22="3.1.1.", L22="3.1.2.", L22="3.4.1.", L22="3.4.2."), 0, VLOOKUP(L22, Работы!$A$3:$D$184, 4, 0)) -> 0 | Q22: =ROUNDUP((I22-H22)*24, 0) -> 8 | T22: =IF(OR(L22="3.3.1.", L22="3.3.2.", L22="3.3.3."), VLOOKUP(L22, Работы!$A$3:$D$184, 4, 0), 0) -> 903 | U22: =IF(OR(L22="3.1.1."), VLOOKUP(L22, Работы!$A$3:$D$184, 4, 0), 0) -> 0 | V22: =IF(OR(L22="3.1.2."), VLOOKUP(L22, Работы!$A$3:$D$184, 4, 0), 0) -> 0 | Y22: =IF(OR(L22="3.2.1.", L22="3.2.2."), VLOOKUP(L22, Работы!$A$3:$D$184, 4, 0), 0) -> 0 | Z22: =IF(OR(L22="3.4.1.", L22="3.4.2."), VLOOKUP(L22, Работы!$A$3:$D$184, 4, 0), 0) -> 0 | AA22: =P22*O22+Q22*T22+R22*T22+S22*T22+U22+V22+W22*Y22+X22*Y22+Z22 -> 7224 | AE22: =AC22*AD22 -> 0 | AF22: =C22*Работы!$D$180 -> 3712.89 | AG22: =AA22+AE22+AF22+AL22+AM22 -> 10936.89 | AJ22: =AG22-AA22*AI22 -> 10936.89 | AL22: =IF(OR(E22="да"), 4040, 0) -> 0 | AM22: =IF(OR(D22="доп."), AA22*0.1, 0) -> 0
A23: =ROW(A23)-10 -> 13 | B23: RO0047 | C23: =VLOOKUP(B23, Расстояния!B:J, 9, 0) -> 64 | D23: =VLOOKUP(B23, Расстояния!B:K, 10, 0) -> осн. | E23: =VLOOKUP(B23, Расстояния!B:F, 5, 0) -> нет | F23: WO06697153 | G23: 46078.463 | H23: 46080.458 | I23: 46080.479 | J23: Пастушенко | L23: 10.3. | M23: =VLOOKUP(L23, Работы!A:B, 2, 0) -> Иные работы/услуги в отношении одного Объекта по одному обращению Заказчика в течение рабочего времени*****, независимо от количества представителей Подрядчика, участвующих в выполнении таких Работ на одном Объекте | N23: Работы по заданию. Осмотр БС. | O23: 1 | P23: =IF(OR(L23="3.3.1.", L23="3.3.2.", L23="3.3.3.", L23="3.1.1.", L23="3.1.2.", L23="3.4.1.", L23="3.4.2."), 0, VLOOKUP(L23, Работы!$A$3:$D$184, 4, 0)) -> 735 | T23: =IF(OR(L23="3.3.1.", L23="3.3.2.", L23="3.3.3."), VLOOKUP(L23, Работы!$A$3:$D$184, 4, 0), 0) -> 0 | U23: =IF(OR(L23="3.1.1."), VLOOKUP(L23, Работы!$A$3:$D$184, 4, 0), 0) -> 0 | V23: =IF(OR(L23="3.1.2."), VLOOKUP(L23, Работы!$A$3:$D$184, 4, 0), 0) -> 0 | Y23: =IF(OR(L23="3.2.1.", L23="3.2.2."), VLOOKUP(L23, Работы!$A$3:$D$184, 4, 0), 0) -> 0 | Z23: =IF(OR(L23="3.4.1.", L23="3.4.2."), VLOOKUP(L23, Работы!$A$3:$D$184, 4, 0), 0) -> 0 | AA23: =P23*O23+Q23*T23+R23*T23+S23*T23+U23+V23+W23*Y23+X23*Y23+Z23 -> 735 | AE23: =AC23*AD23 -> 0 | AF23: =C23*Работы!$D$180 -> 3443.84 | AG23: =AA23+AE23+AF23+AL23+AM23 -> 4178.84 | AJ23: =AG23-AA23*AI23 -> 4178.84 | AL23: =IF(OR(E23="да"), 4040, 0) -> 0 | AM23: =IF(OR(D23="доп."), AA23*0.1, 0) -> 0
A24: =ROW(A24)-10 -> 14 | B24: RO2241 | C24: =VLOOKUP(B24, Расстояния!B:J, 9, 0) -> 52 | D24: =VLOOKUP(B24, Расстояния!B:K, 10, 0) -> осн. | E24: =VLOOKUP(B24, Расстояния!B:F, 5, 0) -> нет | F24: WO06713841 | G24: 46098.169 | H24: 46098.244 | I24: 46098.402 | J24: Пастушенко | L24: 3.3.1. | M24: =VLOOKUP(L24, Работы!A:B, 2, 0) -> Стоимость Аварийно-восстановительных работ по обеспечению временного электроснабжения. (Ставка применяется с 1 часа выполнения Работ, для оплаты каждых не полных суток выполнения Работ) | N24: Генерация | P24: =IF(OR(L24="3.3.1.", L24="3.3.2.", L24="3.3.3.", L24="3.1.1.", L24="3.1.2.", L24="3.4.1.", L24="3.4.2."), 0, VLOOKUP(L24, Работы!$A$3:$D$184, 4, 0)) -> 0 | Q24: =ROUNDUP((I24-H24)*24, 0) -> 4 | T24: =IF(OR(L24="3.3.1.", L24="3.3.2.", L24="3.3.3."), VLOOKUP(L24, Работы!$A$3:$D$184, 4, 0), 0) -> 903 | U24: =IF(OR(L24="3.1.1."), VLOOKUP(L24, Работы!$A$3:$D$184, 4, 0), 0) -> 0 | V24: =IF(OR(L24="3.1.2."), VLOOKUP(L24, Работы!$A$3:$D$184, 4, 0), 0) -> 0 | Y24: =IF(OR(L24="3.2.1.", L24="3.2.2."), VLOOKUP(L24, Работы!$A$3:$D$184, 4, 0), 0) -> 0 | Z24: =IF(OR(L24="3.4.1.", L24="3.4.2."), VLOOKUP(L24, Работы!$A$3:$D$184, 4, 0), 0) -> 0 | AA24: =P24*O24+Q24*T24+R24*T24+S24*T24+U24+V24+W24*Y24+X24*Y24+Z24 -> 3612 | AE24: =AC24*AD24 -> 0 | AF24: =C24*Работы!$D$180 -> 2798.12 | AG24: =AA24+AE24+AF24+AL24+AM24 -> 6410.12 | AJ24: =AG24-AA24*AI24 -> 6410.12 | AL24: =IF(OR(E24="да"), 4040, 0) -> 0 | AM24: =IF(OR(D24="доп."), AA24*0.1, 0) -> 0
A25: =ROW(A25)-10 -> 15 | B25: RO0065 | C25: =VLOOKUP(B25, Расстояния!B:J, 9, 0) -> 70 | D25: =VLOOKUP(B25, Расстояния!B:K, 10, 0) -> осн. | E25: =VLOOKUP(B25, Расстояния!B:F, 5, 0) -> нет | F25: WO06720860 | G25: 46105.497 | H25: 46106.617 | I25: 46106.644 | J25: Голиков | L25: 1.2. | M25: =VLOOKUP(L25, Работы!A:B, 2, 0) -> Диагностика и устранение дефектов АФУ сектора БС (локализация неисправности или перепуток Net Monitor'ом, проверка/ремонт разъёмов, соединительных джемперов, проверка КСВ) | N25: Проверка на перепутку | O25: 1 | P25: =IF(OR(L25="3.3.1.", L25="3.3.2.", L25="3.3.3.", L25="3.1.1.", L25="3.1.2.", L25="3.4.1.", L25="3.4.2."), 0, VLOOKUP(L25, Работы!$A$3:$D$184, 4, 0)) -> 4180 | T25: =IF(OR(L25="3.3.1.", L25="3.3.2.", L25="3.3.3."), VLOOKUP(L25, Работы!$A$3:$D$184, 4, 0), 0) -> 0 | U25: =IF(OR(L25="3.1.1."), VLOOKUP(L25, Работы!$A$3:$D$184, 4, 0), 0) -> 0 | V25: =IF(OR(L25="3.1.2."), VLOOKUP(L25, Работы!$A$3:$D$184, 4, 0), 0) -> 0 | Y25: =IF(OR(L25="3.2.1.", L25="3.2.2."), VLOOKUP(L25, Работы!$A$3:$D$184, 4, 0), 0) -> 0 | Z25: =IF(OR(L25="3.4.1.", L25="3.4.2."), VLOOKUP(L25, Работы!$A$3:$D$184, 4, 0), 0) -> 0 | AA25: =P25*O25+Q25*T25+R25*T25+S25*T25+U25+V25+W25*Y25+X25*Y25+Z25 -> 4180 | AE25: =AC25*AD25 -> 0 | AF25: =C25*Работы!$D$180 -> 3766.7 | AG25: =AA25+AE25+AF25+AL25+AM25 -> 7946.7 | AJ25: =AG25-AA25*AI25 -> 7946.7 | AL25: =IF(OR(E25="да"), 4040, 0) -> 0 | AM25: =IF(OR(D25="доп."), AA25*0.1, 0) -> 0
A26: =ROW(A26)-10 -> 16 | B26: RO0065 | C26: 0 | D26: =VLOOKUP(B26, Расстояния!B:K, 10, 0) -> осн. | E26: =VLOOKUP(B26, Расстояния!B:F, 5, 0) -> нет | F26: WO06722580 | G26: 45741.633 | H26: 46106.617 | I26: 46106.644 | J26: Голиков | L26: 10.3. | M26: =VLOOKUP(L26, Работы!A:B, 2, 0) -> Иные работы/услуги в отношении одного Объекта по одному обращению Заказчика в течение рабочего времени*****, независимо от количества представителей Подрядчика, участвующих в выполнении таких Работ на одном Объекте | N26: Чистка фильтров | O26: 1 | P26: =IF(OR(L26="3.3.1.", L26="3.3.2.", L26="3.3.3.", L26="3.1.1.", L26="3.1.2.", L26="3.4.1.", L26="3.4.2."), 0, VLOOKUP(L26, Работы!$A$3:$D$184, 4, 0)) -> 735 | T26: =IF(OR(L26="3.3.1.", L26="3.3.2.", L26="3.3.3."), VLOOKUP(L26, Работы!$A$3:$D$184, 4, 0), 0) -> 0 | U26: =IF(OR(L26="3.1.1."), VLOOKUP(L26, Работы!$A$3:$D$184, 4, 0), 0) -> 0 | V26: =IF(OR(L26="3.1.2."), VLOOKUP(L26, Работы!$A$3:$D$184, 4, 0), 0) -> 0 | Y26: =IF(OR(L26="3.2.1.", L26="3.2.2."), VLOOKUP(L26, Работы!$A$3:$D$184, 4, 0), 0) -> 0 | Z26: =IF(OR(L26="3.4.1.", L26="3.4.2."), VLOOKUP(L26, Работы!$A$3:$D$184, 4, 0), 0) -> 0 | AA26: =P26*O26+Q26*T26+R26*T26+S26*T26+U26+V26+W26*Y26+X26*Y26+Z26 -> 735 | AE26: =AC26*AD26 -> 0 | AF26: =C26*Работы!$D$180 -> 0 | AG26: =AA26+AE26+AF26+AL26+AM26 -> 735 | AJ26: =AG26-AA26*AI26 -> 735 | AL26: =IF(OR(E26="да"), 4040, 0) -> 0 | AM26: =IF(OR(D26="доп."), AA26*0.1, 0) -> 0
A27: =ROW(A27)-10 -> 17 | B27: RO0085 | C27: =VLOOKUP(B27, Расстояния!B:J, 9, 0) -> 67 | D27: =VLOOKUP(B27, Расстояния!B:K, 10, 0) -> осн. | E27: =VLOOKUP(B27, Расстояния!B:F, 5, 0) -> нет | F27: WO06724695 | G27: 46108.454 | H27: 46108.485 | I27: 46108.72 | J27: Шведков | L27: 3.3.1. | M27: =VLOOKUP(L27, Работы!A:B, 2, 0) -> Стоимость Аварийно-восстановительных работ по обеспечению временного электроснабжения. (Ставка применяется с 1 часа выполнения Работ, для оплаты каждых не полных суток выполнения Работ) | N27: Генерация | P27: =IF(OR(L27="3.3.1.", L27="3.3.2.", L27="3.3.3.", L27="3.1.1.", L27="3.1.2.", L27="3.4.1.", L27="3.4.2."), 0, VLOOKUP(L27, Работы!$A$3:$D$184, 4, 0)) -> 0 | Q27: =ROUNDUP((I27-H27)*24, 0) -> 6 | T27: =IF(OR(L27="3.3.1.", L27="3.3.2.", L27="3.3.3."), VLOOKUP(L27, Работы!$A$3:$D$184, 4, 0), 0) -> 903 | U27: =IF(OR(L27="3.1.1."), VLOOKUP(L27, Работы!$A$3:$D$184, 4, 0), 0) -> 0 | V27: =IF(OR(L27="3.1.2."), VLOOKUP(L27, Работы!$A$3:$D$184, 4, 0), 0) -> 0 | Y27: =IF(OR(L27="3.2.1.", L27="3.2.2."), VLOOKUP(L27, Работы!$A$3:$D$184, 4, 0), 0) -> 0 | Z27: =IF(OR(L27="3.4.1.", L27="3.4.2."), VLOOKUP(L27, Работы!$A$3:$D$184, 4, 0), 0) -> 0 | AA27: =P27*O27+Q27*T27+R27*T27+S27*T27+U27+V27+W27*Y27+X27*Y27+Z27 -> 5418 | AE27: =AC27*AD27 -> 0 | AF27: =C27*Работы!$D$180 -> 3605.27 | AG27: =AA27+AE27+AF27+AL27+AM27 -> 9023.27 | AJ27: =AG27-AA27*AI27 -> 9023.27 | AL27: =IF(OR(E27="да"), 4040, 0) -> 0 | AM27: =IF(OR(D27="доп."), AA27*0.1, 0) -> 0
A28: =ROW(A28)-10 -> 18 | B28: RO0098 | C28: =VLOOKUP(B28, Расстояния!B:J, 9, 0) -> 66 | D28: =VLOOKUP(B28, Расстояния!B:K, 10, 0) -> осн. | E28: =VLOOKUP(B28, Расстояния!B:F, 5, 0) -> нет | H28: 46100.592 | I28: 46100.629 | J28: Ахундов | L28: 1.1. | M28: =VLOOKUP(L28, Работы!A:B, 2, 0) -> Техническое обслуживание БС | N28: Техническое обслуживание БС | O28: 1 | P28: =IF(OR(L28="3.3.1.", L28="3.3.2.", L28="3.3.3.", L28="3.1.1.", L28="3.1.2.", L28="3.4.1.", L28="3.4.2."), 0, VLOOKUP(L28, Работы!$A$3:$D$184, 4, 0)) -> 4143 | T28: =IF(OR(L28="3.3.1.", L28="3.3.2.", L28="3.3.3."), VLOOKUP(L28, Работы!$A$3:$D$184, 4, 0), 0) -> 0 | U28: =IF(OR(L28="3.1.1."), VLOOKUP(L28, Работы!$A$3:$D$184, 4, 0), 0) -> 0 | V28: =IF(OR(L28="3.1.2."), VLOOKUP(L28, Работы!$A$3:$D$184, 4, 0), 0) -> 0 | Y28: =IF(OR(L28="3.2.1.", L28="3.2.2."), VLOOKUP(L28, Работы!$A$3:$D$184, 4, 0), 0) -> 0 | Z28: =IF(OR(L28="3.4.1.", L28="3.4.2."), VLOOKUP(L28, Работы!$A$3:$D$184, 4, 0), 0) -> 0 | AA28: =P28*O28+Q28*T28+R28*T28+S28*T28+U28+V28+W28*Y28+X28*Y28+Z28 -> 4143 | AE28: =AC28*AD28 -> 0 | AF28: =C28*Работы!$D$180 -> 3551.46 | AG28: =AA28+AE28+AF28+AL28+AM28 -> 7694.46 | AJ28: =AG28-AA28*AI28 -> 7694.46 | AL28: =IF(OR(E28="да"), 4040, 0) -> 0 | AM28: =IF(OR(D28="доп."), AA28*0.1, 0) -> 0
A29: =ROW(A29)-10 -> 19 | B29: RO0099 | C29: =VLOOKUP(B29, Расстояния!B:J, 9, 0) -> 68 | D29: =VLOOKUP(B29, Расстояния!B:K, 10, 0) -> осн. | E29: =VLOOKUP(B29, Расстояния!B:F, 5, 0) -> нет | F29: WO06708638 | G29: 46091.592 | H29: 46092.388 | I29: 46092.471 | J29: Жадько | L29: 1.13. | M29: =VLOOKUP(L29, Работы!A:B, 2, 0) -> Изменение механического угла наклона или азимута одной антенны | N29: Изменение механического угла наклона одной антенны | O29: 1 | P29: =IF(OR(L29="3.3.1.", L29="3.3.2.", L29="3.3.3.", L29="3.1.1.", L29="3.1.2.", L29="3.4.1.", L29="3.4.2."), 0, VLOOKUP(L29, Работы!$A$3:$D$184, 4, 0)) -> 2085 | T29: =IF(OR(L29="3.3.1.", L29="3.3.2.", L29="3.3.3."), VLOOKUP(L29, Работы!$A$3:$D$184, 4, 0), 0) -> 0 | U29: =IF(OR(L29="3.1.1."), VLOOKUP(L29, Работы!$A$3:$D$184, 4, 0), 0) -> 0 | V29: =IF(OR(L29="3.1.2."), VLOOKUP(L29, Работы!$A$3:$D$184, 4, 0), 0) -> 0 | Y29: =IF(OR(L29="3.2.1.", L29="3.2.2."), VLOOKUP(L29, Работы!$A$3:$D$184, 4, 0), 0) -> 0 | Z29: =IF(OR(L29="3.4.1.", L29="3.4.2."), VLOOKUP(L29, Работы!$A$3:$D$184, 4, 0), 0) -> 0 | AA29: =P29*O29+Q29*T29+R29*T29+S29*T29+U29+V29+W29*Y29+X29*Y29+Z29 -> 2085 | AE29: =AC29*AD29 -> 0 | AF29: =C29*Работы!$D$180 -> 3659.08 | AG29: =AA29+AE29+AF29+AL29+AM29 -> 5744.08 | AJ29: =AG29-AA29*AI29 -> 5744.08 | AL29: =IF(OR(E29="да"), 4040, 0) -> 0 | AM29: =IF(OR(D29="доп."), AA29*0.1, 0) -> 0
A30: =ROW(A30)-10 -> 20 | B30: RO0099 | C30: 0 | D30: =VLOOKUP(B30, Расстояния!B:K, 10, 0) -> осн. | E30: =VLOOKUP(B30, Расстояния!B:F, 5, 0) -> нет | F30: WO06708638 | G30: 46091.592 | H30: 46092.388 | I30: 46092.471 | J30: Жадько | L30: 1.13. | M30: =VLOOKUP(L30, Работы!A:B, 2, 0) -> Изменение механического угла наклона или азимута одной антенны | N30: Изменение азимута одной антенны | O30: 1 | P30: =IF(OR(L30="3.3.1.", L30="3.3.2.", L30="3.3.3.", L30="3.1.1.", L30="3.1.2.", L30="3.4.1.", L30="3.4.2."), 0, VLOOKUP(L30, Работы!$A$3:$D$184, 4, 0)) -> 2085 | T30: =IF(OR(L30="3.3.1.", L30="3.3.2.", L30="3.3.3."), VLOOKUP(L30, Работы!$A$3:$D$184, 4, 0), 0) -> 0 | U30: =IF(OR(L30="3.1.1."), VLOOKUP(L30, Работы!$A$3:$D$184, 4, 0), 0) -> 0 | V30: =IF(OR(L30="3.1.2."), VLOOKUP(L30, Работы!$A$3:$D$184, 4, 0), 0) -> 0 | Y30: =IF(OR(L30="3.2.1.", L30="3.2.2."), VLOOKUP(L30, Работы!$A$3:$D$184, 4, 0), 0) -> 0 | Z30: =IF(OR(L30="3.4.1.", L30="3.4.2."), VLOOKUP(L30, Работы!$A$3:$D$184, 4, 0), 0) -> 0 | AA30: =P30*O30+Q30*T30+R30*T30+S30*T30+U30+V30+W30*Y30+X30*Y30+Z30 -> 2085 | AE30: =AC30*AD30 -> 0 | AF30: =C30*Работы!$D$180 -> 0 | AG30: =AA30+AE30+AF30+AL30+AM30 -> 2085 | AJ30: =AG30-AA30*AI30 -> 2085 | AL30: =IF(OR(E30="да"), 4040, 0) -> 0 | AM30: =IF(OR(D30="доп."), AA30*0.1, 0) -> 0
A31: =ROW(A31)-10 -> 21 | B31: RO0099 | C31: 0 | D31: =VLOOKUP(B31, Расстояния!B:K, 10, 0) -> осн. | E31: =VLOOKUP(B31, Расстояния!B:F, 5, 0) -> нет | F31: WO06708638 | G31: 46091.592 | H31: 46092.388 | I31: 46092.471 | J31: Жадько | T31: =IF(OR(L31="3.3.1.", L31="3.3.2.", L31="3.3.3."), VLOOKUP(L31, Работы!$A$3:$D$184, 4, 0), 0) -> 0 | U31: =IF(OR(L31="3.1.1."), VLOOKUP(L31, Работы!$A$3:$D$184, 4, 0), 0) -> 0 | V31: =IF(OR(L31="3.1.2."), VLOOKUP(L31, Работы!$A$3:$D$184, 4, 0), 0) -> 0 | Y31: =IF(OR(L31="3.2.1.", L31="3.2.2."), VLOOKUP(L31, Работы!$A$3:$D$184, 4, 0), 0) -> 0 | Z31: =IF(OR(L31="3.4.1.", L31="3.4.2."), VLOOKUP(L31, Работы!$A$3:$D$184, 4, 0), 0) -> 0 | AA31: =P31*O31+Q31*T31+R31*T31+S31*T31+U31+V31+W31*Y31+X31*Y31+Z31 -> 0 | AB31: Альп-работы | AC31: 1 | AD31: 18000 | AE31: =AC31*AD31 -> 18000 | AF31: =C31*Работы!$D$180 -> 0 | AG31: =AA31+AE31+AF31+AL31+AM31 -> 18000 | AJ31: =AG31-AA31*AI31 -> 18000 | AL31: =IF(OR(E31="да"), 4040, 0) -> 0 | AM31: =IF(OR(D31="доп."), AA31*0.1, 0) -> 0
A32: =ROW(A32)-10 -> 22 | B32: RO2901 | C32: =VLOOKUP(B32, Расстояния!B:J, 9, 0) -> 65 | D32: =VLOOKUP(B32, Расстояния!B:K, 10, 0) -> осн. | E32: =VLOOKUP(B32, Расстояния!B:F, 5, 0) -> нет | F32: WO06714405 | G32: 46098.492 | H32: 46098.541 | I32: 46098.731 | J32: Пастушенко | L32: 3.3.1. | M32: =VLOOKUP(L32, Работы!A:B, 2, 0) -> Стоимость Аварийно-восстановительных работ по обеспечению временного электроснабжения. (Ставка применяется с 1 часа выполнения Работ, для оплаты каждых не полных суток выполнения Работ) | N32: Генерация | P32: =IF(OR(L32="3.3.1.", L32="3.3.2.", L32="3.3.3.", L32="3.1.1.", L32="3.1.2.", L32="3.4.1.", L32="3.4.2."), 0, VLOOKUP(L32, Работы!$A$3:$D$184, 4, 0)) -> 0 | Q32: =ROUNDUP((I32-H32)*24, 0) -> 5 | T32: =IF(OR(L32="3.3.1.", L32="3.3.2.", L32="3.3.3."), VLOOKUP(L32, Работы!$A$3:$D$184, 4, 0), 0) -> 903 | U32: =IF(OR(L32="3.1.1."), VLOOKUP(L32, Работы!$A$3:$D$184, 4, 0), 0) -> 0 | V32: =IF(OR(L32="3.1.2."), VLOOKUP(L32, Работы!$A$3:$D$184, 4, 0), 0) -> 0 | Y32: =IF(OR(L32="3.2.1.", L32="3.2.2."), VLOOKUP(L32, Работы!$A$3:$D$184, 4, 0), 0) -> 0 | Z32: =IF(OR(L32="3.4.1.", L32="3.4.2."), VLOOKUP(L32, Работы!$A$3:$D$184, 4, 0), 0) -> 0 | AA32: =P32*O32+Q32*T32+R32*T32+S32*T32+U32+V32+W32*Y32+X32*Y32+Z32 -> 4515 | AE32: =AC32*AD32 -> 0 | AF32: =C32*Работы!$D$180 -> 3497.65 | AG32: =AA32+AE32+AF32+AL32+AM32 -> 8012.65 | AJ32: =AG32-AA32*AI32 -> 8012.65 | AL32: =IF(OR(E32="да"), 4040, 0) -> 0 | AM32: =IF(OR(D32="доп."), AA32*0.1, 0) -> 0
A33: =ROW(A33)-10 -> 23 | B33: RO2901 | C33: =VLOOKUP(B33, Расстояния!B:J, 9, 0) -> 65 | D33: =VLOOKUP(B33, Расстояния!B:K, 10, 0) -> осн. | E33: =VLOOKUP(B33, Расстояния!B:F, 5, 0) -> нет | F33: WO06715685 | G33: 46099.56 | H33: 46099.601 | I33: 46099.615 | J33: Пастушенко | L33: 3.3.1. | M33: =VLOOKUP(L33, Работы!A:B, 2, 0) -> Стоимость Аварийно-восстановительных работ по обеспечению временного электроснабжения. (Ставка применяется с 1 часа выполнения Работ, для оплаты каждых не полных суток выполнения Работ) | N33: Генерация | P33: =IF(OR(L33="3.3.1.", L33="3.3.2.", L33="3.3.3.", L33="3.1.1.", L33="3.1.2.", L33="3.4.1.", L33="3.4.2."), 0, VLOOKUP(L33, Работы!$A$3:$D$184, 4, 0)) -> 0 | Q33: =ROUNDUP((I33-H33)*24, 0) -> 1 | T33: =IF(OR(L33="3.3.1.", L33="3.3.2.", L33="3.3.3."), VLOOKUP(L33, Работы!$A$3:$D$184, 4, 0), 0) -> 903 | U33: =IF(OR(L33="3.1.1."), VLOOKUP(L33, Работы!$A$3:$D$184, 4, 0), 0) -> 0 | V33: =IF(OR(L33="3.1.2."), VLOOKUP(L33, Работы!$A$3:$D$184, 4, 0), 0) -> 0 | Y33: =IF(OR(L33="3.2.1.", L33="3.2.2."), VLOOKUP(L33, Работы!$A$3:$D$184, 4, 0), 0) -> 0 | Z33: =IF(OR(L33="3.4.1.", L33="3.4.2."), VLOOKUP(L33, Работы!$A$3:$D$184, 4, 0), 0) -> 0 | AA33: =P33*O33+Q33*T33+R33*T33+S33*T33+U33+V33+W33*Y33+X33*Y33+Z33 -> 903 | AE33: =AC33*AD33 -> 0 | AF33: =C33*Работы!$D$180 -> 3497.65 | AG33: =AA33+AE33+AF33+AL33+AM33 -> 4400.65 | AJ33: =AG33-AA33*AI33 -> 4400.65 | AL33: =IF(OR(E33="да"), 4040, 0) -> 0 | AM33: =IF(OR(D33="доп."), AA33*0.1, 0) -> 0
A34: =ROW(A34)-10 -> 24 | B34: RO0135 | C34: =VLOOKUP(B34, Расстояния!B:J, 9, 0) -> 66 | D34: =VLOOKUP(B34, Расстояния!B:K, 10, 0) -> осн. | E34: =VLOOKUP(B34, Расстояния!B:F, 5, 0) -> нет | F34: WO06724458 | G34: 46108.376 | H34: 46108.414 | I34: 46108.761 | J34: Голиков | L34: 3.1.1. | M34: =VLOOKUP(L34, Работы!A:B, 2, 0) -> Стоимость аварийно-восстановительных работ, заявка по которым получена в течение рабочего времени | N34: Чистка передатчика | P34: =IF(OR(L34="3.3.1.", L34="3.3.2.", L34="3.3.3.", L34="3.1.1.", L34="3.1.2.", L34="3.4.1.", L34="3.4.2."), 0, VLOOKUP(L34, Работы!$A$3:$D$184, 4, 0)) -> 0 | T34: =IF(OR(L34="3.3.1.", L34="3.3.2.", L34="3.3.3."), VLOOKUP(L34, Работы!$A$3:$D$184, 4, 0), 0) -> 0 | U34: =IF(OR(L34="3.1.1."), VLOOKUP(L34, Работы!$A$3:$D$184, 4, 0), 0) -> 3956 | V34: =IF(OR(L34="3.1.2."), VLOOKUP(L34, Работы!$A$3:$D$184, 4, 0), 0) -> 0 | Y34: =IF(OR(L34="3.2.1.", L34="3.2.2."), VLOOKUP(L34, Работы!$A$3:$D$184, 4, 0), 0) -> 0 | Z34: =IF(OR(L34="3.4.1.", L34="3.4.2."), VLOOKUP(L34, Работы!$A$3:$D$184, 4, 0), 0) -> 0 | AA34: =P34*O34+Q34*T34+R34*T34+S34*T34+U34+V34+W34*Y34+X34*Y34+Z34 -> 3956 | AE34: =AC34*AD34 -> 0 | AF34: =C34*Работы!$D$180 -> 3551.46 | AG34: =AA34+AE34+AF34+AL34+AM34 -> 7507.46 | AJ34: =AG34-AA34*AI34 -> 7507.46 | AL34: =IF(OR(E34="да"), 4040, 0) -> 0 | AM34: =IF(OR(D34="доп."), AA34*0.1, 0) -> 0
A35: =ROW(A35)-10 -> 25 | B35: RO0174 | C35: =VLOOKUP(B35, Расстояния!B:J, 9, 0) -> 67 | D35: =VLOOKUP(B35, Расстояния!B:K, 10, 0) -> осн. | E35: =VLOOKUP(B35, Расстояния!B:F, 5, 0) -> нет | H35: 46098.646 | I35: 46098.671 | J35: Котенко | L35: 1.1. | M35: =VLOOKUP(L35, Работы!A:B, 2, 0) -> Техническое обслуживание БС | N35: Техническое обслуживание БС | O35: 1 | P35: =IF(OR(L35="3.3.1.", L35="3.3.2.", L35="3.3.3.", L35="3.1.1.", L35="3.1.2.", L35="3.4.1.", L35="3.4.2."), 0, VLOOKUP(L35, Работы!$A$3:$D$184, 4, 0)) -> 4143 | T35: =IF(OR(L35="3.3.1.", L35="3.3.2.", L35="3.3.3."), VLOOKUP(L35, Работы!$A$3:$D$184, 4, 0), 0) -> 0 | U35: =IF(OR(L35="3.1.1."), VLOOKUP(L35, Работы!$A$3:$D$184, 4, 0), 0) -> 0 | V35: =IF(OR(L35="3.1.2."), VLOOKUP(L35, Работы!$A$3:$D$184, 4, 0), 0) -> 0 | Y35: =IF(OR(L35="3.2.1.", L35="3.2.2."), VLOOKUP(L35, Работы!$A$3:$D$184, 4, 0), 0) -> 0 | Z35: =IF(OR(L35="3.4.1.", L35="3.4.2."), VLOOKUP(L35, Работы!$A$3:$D$184, 4, 0), 0) -> 0 | AA35: =P35*O35+Q35*T35+R35*T35+S35*T35+U35+V35+W35*Y35+X35*Y35+Z35 -> 4143 | AE35: =AC35*AD35 -> 0 | AF35: =C35*Работы!$D$180 -> 3605.27 | AG35: =AA35+AE35+AF35+AL35+AM35 -> 7748.27 | AJ35: =AG35-AA35*AI35 -> 7748.27 | AL35: =IF(OR(E35="да"), 4040, 0) -> 0 | AM35: =IF(OR(D35="доп."), AA35*0.1, 0) -> 0
A36: =ROW(A36)-10 -> 26 | B36: RO0175 | C36: =VLOOKUP(B36, Расстояния!B:J, 9, 0) -> 70 | D36: =VLOOKUP(B36, Расстояния!B:K, 10, 0) -> осн. | E36: =VLOOKUP(B36, Расстояния!B:F, 5, 0) -> нет | F36: WO06723530 | G36: 46107.474 | H36: 46107.526 | I36: 46107.717 | J36: Голиков | L36: 3.1.1. | M36: =VLOOKUP(L36, Работы!A:B, 2, 0) -> Стоимость аварийно-восстановительных работ, заявка по которым получена в течение рабочего времени | N36: Замена 2-ух SFP, джампера | P36: =IF(OR(L36="3.3.1.", L36="3.3.2.", L36="3.3.3.", L36="3.1.1.", L36="3.1.2.", L36="3.4.1.", L36="3.4.2."), 0, VLOOKUP(L36, Работы!$A$3:$D$184, 4, 0)) -> 0 | T36: =IF(OR(L36="3.3.1.", L36="3.3.2.", L36="3.3.3."), VLOOKUP(L36, Работы!$A$3:$D$184, 4, 0), 0) -> 0 | U36: =IF(OR(L36="3.1.1."), VLOOKUP(L36, Работы!$A$3:$D$184, 4, 0), 0) -> 3956 | V36: =IF(OR(L36="3.1.2."), VLOOKUP(L36, Работы!$A$3:$D$184, 4, 0), 0) -> 0 | Y36: =IF(OR(L36="3.2.1.", L36="3.2.2."), VLOOKUP(L36, Работы!$A$3:$D$184, 4, 0), 0) -> 0 | Z36: =IF(OR(L36="3.4.1.", L36="3.4.2."), VLOOKUP(L36, Работы!$A$3:$D$184, 4, 0), 0) -> 0 | AA36: =P36*O36+Q36*T36+R36*T36+S36*T36+U36+V36+W36*Y36+X36*Y36+Z36 -> 3956 | AE36: =AC36*AD36 -> 0 | AF36: =C36*Работы!$D$180 -> 3766.7 | AG36: =AA36+AE36+AF36+AL36+AM36 -> 7722.7 | AJ36: =AG36-AA36*AI36 -> 7722.7 | AL36: =IF(OR(E36="да"), 4040, 0) -> 0 | AM36: =IF(OR(D36="доп."), AA36*0.1, 0) -> 0
A37: =ROW(A37)-10 -> 27 | B37: RO1075 | C37: =VLOOKUP(B37, Расстояния!B:J, 9, 0) -> 69 | D37: =VLOOKUP(B37, Расстояния!B:K, 10, 0) -> осн. | E37: =VLOOKUP(B37, Расстояния!B:F, 5, 0) -> нет | F37: WO06716427 | G37: 46100.369 | H37: 46100.407 | I37: 46100.549 | J37: Пастушенко | L37: 3.3.1. | M37: =VLOOKUP(L37, Работы!A:B, 2, 0) -> Стоимость Аварийно-восстановительных работ по обеспечению временного электроснабжения. (Ставка применяется с 1 часа выполнения Работ, для оплаты каждых не полных суток выполнения Работ) | N37: Генерация | P37: =IF(OR(L37="3.3.1.", L37="3.3.2.", L37="3.3.3.", L37="3.1.1.", L37="3.1.2.", L37="3.4.1.", L37="3.4.2."), 0, VLOOKUP(L37, Работы!$A$3:$D$184, 4, 0)) -> 0 | Q37: =ROUNDUP((I37-H37)*24, 0) -> 4 | T37: =IF(OR(L37="3.3.1.", L37="3.3.2.", L37="3.3.3."), VLOOKUP(L37, Работы!$A$3:$D$184, 4, 0), 0) -> 903 | U37: =IF(OR(L37="3.1.1."), VLOOKUP(L37, Работы!$A$3:$D$184, 4, 0), 0) -> 0 | V37: =IF(OR(L37="3.1.2."), VLOOKUP(L37, Работы!$A$3:$D$184, 4, 0), 0) -> 0 | Y37: =IF(OR(L37="3.2.1.", L37="3.2.2."), VLOOKUP(L37, Работы!$A$3:$D$184, 4, 0), 0) -> 0 | Z37: =IF(OR(L37="3.4.1.", L37="3.4.2."), VLOOKUP(L37, Работы!$A$3:$D$184, 4, 0), 0) -> 0 | AA37: =P37*O37+Q37*T37+R37*T37+S37*T37+U37+V37+W37*Y37+X37*Y37+Z37 -> 3612 | AE37: =AC37*AD37 -> 0 | AF37: =C37*Работы!$D$180 -> 3712.89 | AG37: =AA37+AE37+AF37+AL37+AM37 -> 7324.89 | AJ37: =AG37-AA37*AI37 -> 7324.89 | AL37: =IF(OR(E37="да"), 4040, 0) -> 0 | AM37: =IF(OR(D37="доп."), AA37*0.1, 0) -> 0
A38: =ROW(A38)-10 -> 28 | B38: RO0199 | C38: =VLOOKUP(B38, Расстояния!B:J, 9, 0) -> 63 | D38: =VLOOKUP(B38, Расстояния!B:K, 10, 0) -> осн. | E38: =VLOOKUP(B38, Расстояния!B:F, 5, 0) -> нет | F38: WO06714363 | G38: 46098.475 | H38: 46098.572 | I38: 46098.637 | J38: Юкин | L38: 3.1.1. | M38: =VLOOKUP(L38, Работы!A:B, 2, 0) -> Стоимость аварийно-восстановительных работ, заявка по которым получена в течение рабочего времени | N38: Сопровождение | P38: =IF(OR(L38="3.3.1.", L38="3.3.2.", L38="3.3.3.", L38="3.1.1.", L38="3.1.2.", L38="3.4.1.", L38="3.4.2."), 0, VLOOKUP(L38, Работы!$A$3:$D$184, 4, 0)) -> 0 | T38: =IF(OR(L38="3.3.1.", L38="3.3.2.", L38="3.3.3."), VLOOKUP(L38, Работы!$A$3:$D$184, 4, 0), 0) -> 0 | U38: =IF(OR(L38="3.1.1."), VLOOKUP(L38, Работы!$A$3:$D$184, 4, 0), 0) -> 3956 | V38: =IF(OR(L38="3.1.2."), VLOOKUP(L38, Работы!$A$3:$D$184, 4, 0), 0) -> 0 | Y38: =IF(OR(L38="3.2.1.", L38="3.2.2."), VLOOKUP(L38, Работы!$A$3:$D$184, 4, 0), 0) -> 0 | Z38: =IF(OR(L38="3.4.1.", L38="3.4.2."), VLOOKUP(L38, Работы!$A$3:$D$184, 4, 0), 0) -> 0 | AA38: =P38*O38+Q38*T38+R38*T38+S38*T38+U38+V38+W38*Y38+X38*Y38+Z38 -> 3956 | AE38: =AC38*AD38 -> 0 | AF38: =C38*Работы!$D$180 -> 3390.03 | AG38: =AA38+AE38+AF38+AL38+AM38 -> 7346.03 | AJ38: =AG38-AA38*AI38 -> 7346.03 | AL38: =IF(OR(E38="да"), 4040, 0) -> 0 | AM38: =IF(OR(D38="доп."), AA38*0.1, 0) -> 0
A39: =ROW(A39)-10 -> 29 | B39: RO0264 | C39: =VLOOKUP(B39, Расстояния!B:J, 9, 0) -> 64 | D39: =VLOOKUP(B39, Расстояния!B:K, 10, 0) -> осн. | E39: =VLOOKUP(B39, Расстояния!B:F, 5, 0) -> нет | F39: WO06726884 | G39: 46111.408 | H39: 46111.633 | I39: 46111.8 | J39: Голиков | L39: 2.2. | M39: =VLOOKUP(L39, Работы!A:B, 2, 0) -> Диагностика и замена модуля передатчиков БС на АМС, включая монтаж всех крепёжных элементов и кабелей, переключение джамперов и созданием логических объектов на стороне БС | N39: Чистка передатчика | O39: 1 | P39: =IF(OR(L39="3.3.1.", L39="3.3.2.", L39="3.3.3.", L39="3.1.1.", L39="3.1.2.", L39="3.4.1.", L39="3.4.2."), 0, VLOOKUP(L39, Работы!$A$3:$D$184, 4, 0)) -> 2830 | T39: =IF(OR(L39="3.3.1.", L39="3.3.2.", L39="3.3.3."), VLOOKUP(L39, Работы!$A$3:$D$184, 4, 0), 0) -> 0 | U39: =IF(OR(L39="3.1.1."), VLOOKUP(L39, Работы!$A$3:$D$184, 4, 0), 0) -> 0 | V39: =IF(OR(L39="3.1.2."), VLOOKUP(L39, Работы!$A$3:$D$184, 4, 0), 0) -> 0 | Y39: =IF(OR(L39="3.2.1.", L39="3.2.2."), VLOOKUP(L39, Работы!$A$3:$D$184, 4, 0), 0) -> 0 | Z39: =IF(OR(L39="3.4.1.", L39="3.4.2."), VLOOKUP(L39, Работы!$A$3:$D$184, 4, 0), 0) -> 0 | AA39: =P39*O39+Q39*T39+R39*T39+S39*T39+U39+V39+W39*Y39+X39*Y39+Z39 -> 2830 | AE39: =AC39*AD39 -> 0 | AF39: =C39*Работы!$D$180 -> 3443.84 | AG39: =AA39+AE39+AF39+AL39+AM39 -> 6273.84 | AJ39: =AG39-AA39*AI39 -> 6273.84 | AL39: =IF(OR(E39="да"), 4040, 0) -> 0 | AM39: =IF(OR(D39="доп."), AA39*0.1, 0) -> 0
A40: =ROW(A40)-10 -> 30 | B40: RO0270 | C40: =VLOOKUP(B40, Расстояния!B:J, 9, 0) -> 63 | D40: =VLOOKUP(B40, Расстояния!B:K, 10, 0) -> осн. | E40: =VLOOKUP(B40, Расстояния!B:F, 5, 0) -> нет | H40: 46101.562 | I40: 46101.646 | J40: Черкашин | L40: 1.1. | M40: =VLOOKUP(L40, Работы!A:B, 2, 0) -> Техническое обслуживание БС | N40: Техническое обслуживание БС | O40: 1 | P40: =IF(OR(L40="3.3.1.", L40="3.3.2.", L40="3.3.3.", L40="3.1.1.", L40="3.1.2.", L40="3.4.1.", L40="3.4.2."), 0, VLOOKUP(L40, Работы!$A$3:$D$184, 4, 0)) -> 4143 | T40: =IF(OR(L40="3.3.1.", L40="3.3.2.", L40="3.3.3."), VLOOKUP(L40, Работы!$A$3:$D$184, 4, 0), 0) -> 0 | U40: =IF(OR(L40="3.1.1."), VLOOKUP(L40, Работы!$A$3:$D$184, 4, 0), 0) -> 0 | V40: =IF(OR(L40="3.1.2."), VLOOKUP(L40, Работы!$A$3:$D$184, 4, 0), 0) -> 0 | Y40: =IF(OR(L40="3.2.1.", L40="3.2.2."), VLOOKUP(L40, Работы!$A$3:$D$184, 4, 0), 0) -> 0 | Z40: =IF(OR(L40="3.4.1.", L40="3.4.2."), VLOOKUP(L40, Работы!$A$3:$D$184, 4, 0), 0) -> 0 | AA40: =P40*O40+Q40*T40+R40*T40+S40*T40+U40+V40+W40*Y40+X40*Y40+Z40 -> 4143 | AE40: =AC40*AD40 -> 0 | AF40: =C40*Работы!$D$180 -> 3390.03 | AG40: =AA40+AE40+AF40+AL40+AM40 -> 7533.03 | AJ40: =AG40-AA40*AI40 -> 7533.03 | AL40: =IF(OR(E40="да"), 4040, 0) -> 0 | AM40: =IF(OR(D40="доп."), AA40*0.1, 0) -> 0
A41: =ROW(A41)-10 -> 31 | B41: RO1151 | C41: =VLOOKUP(B41, Расстояния!B:J, 9, 0) -> 69 | D41: =VLOOKUP(B41, Расстояния!B:K, 10, 0) -> осн. | E41: =VLOOKUP(B41, Расстояния!B:F, 5, 0) -> нет | F41: WO06716413 | G41: 46100.426 | H41: 46100.458 | I41: 46100.54 | J41: Пастушенко | L41: 3.3.1. | M41: =VLOOKUP(L41, Работы!A:B, 2, 0) -> Стоимость Аварийно-восстановительных работ по обеспечению временного электроснабжения. (Ставка применяется с 1 часа выполнения Работ, для оплаты каждых не полных суток выполнения Работ) | N41: Генерация | P41: =IF(OR(L41="3.3.1.", L41="3.3.2.", L41="3.3.3.", L41="3.1.1.", L41="3.1.2.", L41="3.4.1.", L41="3.4.2."), 0, VLOOKUP(L41, Работы!$A$3:$D$184, 4, 0)) -> 0 | Q41: =ROUNDUP((I41-H41)*24, 0) -> 2 | T41: =IF(OR(L41="3.3.1.", L41="3.3.2.", L41="3.3.3."), VLOOKUP(L41, Работы!$A$3:$D$184, 4, 0), 0) -> 903 | U41: =IF(OR(L41="3.1.1."), VLOOKUP(L41, Работы!$A$3:$D$184, 4, 0), 0) -> 0 | V41: =IF(OR(L41="3.1.2."), VLOOKUP(L41, Работы!$A$3:$D$184, 4, 0), 0) -> 0 | Y41: =IF(OR(L41="3.2.1.", L41="3.2.2."), VLOOKUP(L41, Работы!$A$3:$D$184, 4, 0), 0) -> 0 | Z41: =IF(OR(L41="3.4.1.", L41="3.4.2."), VLOOKUP(L41, Работы!$A$3:$D$184, 4, 0), 0) -> 0 | AA41: =P41*O41+Q41*T41+R41*T41+S41*T41+U41+V41+W41*Y41+X41*Y41+Z41 -> 1806 | AE41: =AC41*AD41 -> 0 | AF41: =C41*Работы!$D$180 -> 3712.89 | AG41: =AA41+AE41+AF41+AL41+AM41 -> 5518.89 | AJ41: =AG41-AA41*AI41 -> 5518.89 | AL41: =IF(OR(E41="да"), 4040, 0) -> 0 | AM41: =IF(OR(D41="доп."), AA41*0.1, 0) -> 0
A42: =ROW(A42)-10 -> 32 | B42: RO0303 | C42: =VLOOKUP(B42, Расстояния!B:J, 9, 0) -> 124 | D42: =VLOOKUP(B42, Расстояния!B:K, 10, 0) -> осн. | E42: =VLOOKUP(B42, Расстояния!B:F, 5, 0) -> нет | F42: WO06724512 | G42: 46108.393 | H42: 46112.616 | I42: 46112.761 | J42: Жадько | L42: 2.2. | M42: =VLOOKUP(L42, Работы!A:B, 2, 0) -> Диагностика и замена модуля передатчиков БС на АМС, включая монтаж всех крепёжных элементов и кабелей, переключение джамперов и созданием логических объектов на стороне БС | N42: Чистка передатчика | O42: 1 | P42: =IF(OR(L42="3.3.1.", L42="3.3.2.", L42="3.3.3.", L42="3.1.1.", L42="3.1.2.", L42="3.4.1.", L42="3.4.2."), 0, VLOOKUP(L42, Работы!$A$3:$D$184, 4, 0)) -> 2830 | T42: =IF(OR(L42="3.3.1.", L42="3.3.2.", L42="3.3.3."), VLOOKUP(L42, Работы!$A$3:$D$184, 4, 0), 0) -> 0 | U42: =IF(OR(L42="3.1.1."), VLOOKUP(L42, Работы!$A$3:$D$184, 4, 0), 0) -> 0 | V42: =IF(OR(L42="3.1.2."), VLOOKUP(L42, Работы!$A$3:$D$184, 4, 0), 0) -> 0 | Y42: =IF(OR(L42="3.2.1.", L42="3.2.2."), VLOOKUP(L42, Работы!$A$3:$D$184, 4, 0), 0) -> 0 | Z42: =IF(OR(L42="3.4.1.", L42="3.4.2."), VLOOKUP(L42, Работы!$A$3:$D$184, 4, 0), 0) -> 0 | AA42: =P42*O42+Q42*T42+R42*T42+S42*T42+U42+V42+W42*Y42+X42*Y42+Z42 -> 2830 | AE42: =AC42*AD42 -> 0 | AF42: =C42*Работы!$D$180 -> 6672.44 | AG42: =AA42+AE42+AF42+AL42+AM42 -> 9502.44 | AJ42: =AG42-AA42*AI42 -> 9502.44 | AL42: =IF(OR(E42="да"), 4040, 0) -> 0 | AM42: =IF(OR(D42="доп."), AA42*0.1, 0) -> 0
A43: =ROW(A43)-10 -> 33 | B43: RO0303 | C43: 0 | D43: =VLOOKUP(B43, Расстояния!B:K, 10, 0) -> осн. | E43: =VLOOKUP(B43, Расстояния!B:F, 5, 0) -> нет | F43: WO06724512 | G43: 46108.393 | H43: 46112.616 | I43: 46112.761 | J43: Жадько | L43: 2.2. | M43: =VLOOKUP(L43, Работы!A:B, 2, 0) -> Диагностика и замена модуля передатчиков БС на АМС, включая монтаж всех крепёжных элементов и кабелей, переключение джамперов и созданием логических объектов на стороне БС | N43: Чистка передатчика | O43: 1 | P43: =IF(OR(L43="3.3.1.", L43="3.3.2.", L43="3.3.3.", L43="3.1.1.", L43="3.1.2.", L43="3.4.1.", L43="3.4.2."), 0, VLOOKUP(L43, Работы!$A$3:$D$184, 4, 0)) -> 2830 | T43: =IF(OR(L43="3.3.1.", L43="3.3.2.", L43="3.3.3."), VLOOKUP(L43, Работы!$A$3:$D$184, 4, 0), 0) -> 0 | U43: =IF(OR(L43="3.1.1."), VLOOKUP(L43, Работы!$A$3:$D$184, 4, 0), 0) -> 0 | V43: =IF(OR(L43="3.1.2."), VLOOKUP(L43, Работы!$A$3:$D$184, 4, 0), 0) -> 0 | Y43: =IF(OR(L43="3.2.1.", L43="3.2.2."), VLOOKUP(L43, Работы!$A$3:$D$184, 4, 0), 0) -> 0 | Z43: =IF(OR(L43="3.4.1.", L43="3.4.2."), VLOOKUP(L43, Работы!$A$3:$D$184, 4, 0), 0) -> 0 | AA43: =P43*O43+Q43*T43+R43*T43+S43*T43+U43+V43+W43*Y43+X43*Y43+Z43 -> 2830 | AE43: =AC43*AD43 -> 0 | AF43: =C43*Работы!$D$180 -> 0 | AG43: =AA43+AE43+AF43+AL43+AM43 -> 2830 | AJ43: =AG43-AA43*AI43 -> 2830 | AL43: =IF(OR(E43="да"), 4040, 0) -> 0 | AM43: =IF(OR(D43="доп."), AA43*0.1, 0) -> 0
A44: =ROW(A44)-10 -> 34 | B44: RO0308 | C44: =VLOOKUP(B44, Расстояния!B:J, 9, 0) -> 14 | D44: =VLOOKUP(B44, Расстояния!B:K, 10, 0) -> осн. | E44: =VLOOKUP(B44, Расстояния!B:F, 5, 0) -> нет | H44: 46098.428 | I44: 46098.557 | J44: Ткаченко | L44: 1.1. | M44: =VLOOKUP(L44, Работы!A:B, 2, 0) -> Техническое обслуживание БС | N44: Техническое обслуживание БС | O44: 1 | P44: =IF(OR(L44="3.3.1.", L44="3.3.2.", L44="3.3.3.", L44="3.1.1.", L44="3.1.2.", L44="3.4.1.", L44="3.4.2."), 0, VLOOKUP(L44, Работы!$A$3:$D$184, 4, 0)) -> 4143 | T44: =IF(OR(L44="3.3.1.", L44="3.3.2.", L44="3.3.3."), VLOOKUP(L44, Работы!$A$3:$D$184, 4, 0), 0) -> 0 | U44: =IF(OR(L44="3.1.1."), VLOOKUP(L44, Работы!$A$3:$D$184, 4, 0), 0) -> 0 | V44: =IF(OR(L44="3.1.2."), VLOOKUP(L44, Работы!$A$3:$D$184, 4, 0), 0) -> 0 | Y44: =IF(OR(L44="3.2.1.", L44="3.2.2."), VLOOKUP(L44, Работы!$A$3:$D$184, 4, 0), 0) -> 0 | Z44: =IF(OR(L44="3.4.1.", L44="3.4.2."), VLOOKUP(L44, Работы!$A$3:$D$184, 4, 0), 0) -> 0 | AA44: =P44*O44+Q44*T44+R44*T44+S44*T44+U44+V44+W44*Y44+X44*Y44+Z44 -> 4143 | AE44: =AC44*AD44 -> 0 | AF44: =C44*Работы!$D$180 -> 753.34 | AG44: =AA44+AE44+AF44+AL44+AM44 -> 4896.34 | AJ44: =AG44-AA44*AI44 -> 4896.34 | AL44: =IF(OR(E44="да"), 4040, 0) -> 0 | AM44: =IF(OR(D44="доп."), AA44*0.1, 0) -> 0
A45: =ROW(A45)-10 -> 35 | B45: RO0308 | C45: 0 | D45: =VLOOKUP(B45, Расстояния!B:K, 10, 0) -> осн. | E45: =VLOOKUP(B45, Расстояния!B:F, 5, 0) -> нет | H45: 46098.428 | I45: 46098.557 | J45: Ткаченко | L45: 4.5 | M45: =VLOOKUP(L45, Работы!A:B, 2, 0) -> Стоимость проведения инвентаризации Объекта. | N45: Инвентаризация БС | O45: 1 | P45: =IF(OR(L45="3.3.1.", L45="3.3.2.", L45="3.3.3.", L45="3.1.1.", L45="3.1.2.", L45="3.4.1.", L45="3.4.2."), 0, VLOOKUP(L45, Работы!$A$3:$D$184, 4, 0)) -> 735 | T45: =IF(OR(L45="3.3.1.", L45="3.3.2.", L45="3.3.3."), VLOOKUP(L45, Работы!$A$3:$D$184, 4, 0), 0) -> 0 | U45: =IF(OR(L45="3.1.1."), VLOOKUP(L45, Работы!$A$3:$D$184, 4, 0), 0) -> 0 | V45: =IF(OR(L45="3.1.2."), VLOOKUP(L45, Работы!$A$3:$D$184, 4, 0), 0) -> 0 | Y45: =IF(OR(L45="3.2.1.", L45="3.2.2."), VLOOKUP(L45, Работы!$A$3:$D$184, 4, 0), 0) -> 0 | Z45: =IF(OR(L45="3.4.1.", L45="3.4.2."), VLOOKUP(L45, Работы!$A$3:$D$184, 4, 0), 0) -> 0 | AA45: =P45*O45+Q45*T45+R45*T45+S45*T45+U45+V45+W45*Y45+X45*Y45+Z45 -> 735 | AE45: =AC45*AD45 -> 0 | AF45: =C45*Работы!$D$180 -> 0 | AG45: =AA45+AE45+AF45+AL45+AM45 -> 735 | AJ45: =AG45-AA45*AI45 -> 735 | AL45: =IF(OR(E45="да"), 4040, 0) -> 0 | AM45: =IF(OR(D45="доп."), AA45*0.1, 0) -> 0
A46: =ROW(A46)-10 -> 36 | B46: RO0308 | C46: 0 | D46: =VLOOKUP(B46, Расстояния!B:K, 10, 0) -> осн. | E46: =VLOOKUP(B46, Расстояния!B:F, 5, 0) -> нет | H46: 46098.428 | I46: 46098.557 | J46: Ткаченко | L46: 10.3. | M46: =VLOOKUP(L46, Работы!A:B, 2, 0) -> Иные работы/услуги в отношении одного Объекта по одному обращению Заказчика в течение рабочего времени*****, независимо от количества представителей Подрядчика, участвующих в выполнении таких Работ на одном Объекте | N46: Чистка фильтра маршрутизатора | O46: 1 | P46: =IF(OR(L46="3.3.1.", L46="3.3.2.", L46="3.3.3.", L46="3.1.1.", L46="3.1.2.", L46="3.4.1.", L46="3.4.2."), 0, VLOOKUP(L46, Работы!$A$3:$D$184, 4, 0)) -> 735 | T46: =IF(OR(L46="3.3.1.", L46="3.3.2.", L46="3.3.3."), VLOOKUP(L46, Работы!$A$3:$D$184, 4, 0), 0) -> 0 | U46: =IF(OR(L46="3.1.1."), VLOOKUP(L46, Работы!$A$3:$D$184, 4, 0), 0) -> 0 | V46: =IF(OR(L46="3.1.2."), VLOOKUP(L46, Работы!$A$3:$D$184, 4, 0), 0) -> 0 | Y46: =IF(OR(L46="3.2.1.", L46="3.2.2."), VLOOKUP(L46, Работы!$A$3:$D$184, 4, 0), 0) -> 0 | Z46: =IF(OR(L46="3.4.1.", L46="3.4.2."), VLOOKUP(L46, Работы!$A$3:$D$184, 4, 0), 0) -> 0 | AA46: =P46*O46+Q46*T46+R46*T46+S46*T46+U46+V46+W46*Y46+X46*Y46+Z46 -> 735 | AE46: =AC46*AD46 -> 0 | AF46: =C46*Работы!$D$180 -> 0 | AG46: =AA46+AE46+AF46+AL46+AM46 -> 735 | AJ46: =AG46-AA46*AI46 -> 735 | AL46: =IF(OR(E46="да"), 4040, 0) -> 0 | AM46: =IF(OR(D46="доп."), AA46*0.1, 0) -> 0
A47: =ROW(A47)-10 -> 37 | B47: RO0316 | C47: 40 | D47: =VLOOKUP(B47, Расстояния!B:K, 10, 0) -> осн. | E47: =VLOOKUP(B47, Расстояния!B:F, 5, 0) -> нет | F47: WO06714307 | G47: 46098.456 | H47: 46098.491 | I47: 46098.491 | J47: Шведков | L47: 3.4.1. | M47: =VLOOKUP(L47, Работы!A:B, 2, 0) -> Стоимость отменённого вызова на Аварийно-восстановительные работы, заявка по которым получена в рабочее время | N47: Отмена | P47: =IF(OR(L47="3.3.1.", L47="3.3.2.", L47="3.3.3.", L47="3.1.1.", L47="3.1.2.", L47="3.4.1.", L47="3.4.2."), 0, VLOOKUP(L47, Работы!$A$3:$D$184, 4, 0)) -> 0 | T47: =IF(OR(L47="3.3.1.", L47="3.3.2.", L47="3.3.3."), VLOOKUP(L47, Работы!$A$3:$D$184, 4, 0), 0) -> 0 | U47: =IF(OR(L47="3.1.1."), VLOOKUP(L47, Работы!$A$3:$D$184, 4, 0), 0) -> 0 | V47: =IF(OR(L47="3.1.2."), VLOOKUP(L47, Работы!$A$3:$D$184, 4, 0), 0) -> 0 | Y47: =IF(OR(L47="3.2.1.", L47="3.2.2."), VLOOKUP(L47, Работы!$A$3:$D$184, 4, 0), 0) -> 0 | Z47: =IF(OR(L47="3.4.1.", L47="3.4.2."), VLOOKUP(L47, Работы!$A$3:$D$184, 4, 0), 0) -> 922 | AA47: =P47*O47+Q47*T47+R47*T47+S47*T47+U47+V47+W47*Y47+X47*Y47+Z47 -> 922 | AE47: =AC47*AD47 -> 0 | AF47: =C47*Работы!$D$180 -> 2152.4 | AG47: =AA47+AE47+AF47+AL47+AM47 -> 3074.4 | AJ47: =AG47-AA47*AI47 -> 3074.4 | AL47: =IF(OR(E47="да"), 4040, 0) -> 0 | AM47: =IF(OR(D47="доп."), AA47*0.1, 0) -> 0
A48: =ROW(A48)-10 -> 38 | B48: RO0317 | C48: =VLOOKUP(B48, Расстояния!B:J, 9, 0) -> 11 | D48: =VLOOKUP(B48, Расстояния!B:K, 10, 0) -> осн. | E48: =VLOOKUP(B48, Расстояния!B:F, 5, 0) -> нет | F48: WO06724258 | G48: 46108.214 | H48: 46108.272 | I48: 46108.292 | J48: Титенко | L48: 3.3.1. | M48: =VLOOKUP(L48, Работы!A:B, 2, 0) -> Стоимость Аварийно-восстановительных работ по обеспечению временного электроснабжения. (Ставка применяется с 1 часа выполнения Работ, для оплаты каждых не полных суток выполнения Работ) | N48: Генерация | P48: =IF(OR(L48="3.3.1.", L48="3.3.2.", L48="3.3.3.", L48="3.1.1.", L48="3.1.2.", L48="3.4.1.", L48="3.4.2."), 0, VLOOKUP(L48, Работы!$A$3:$D$184, 4, 0)) -> 0 | Q48: =ROUNDUP((I48-H48)*24, 0) -> 1 | T48: =IF(OR(L48="3.3.1.", L48="3.3.2.", L48="3.3.3."), VLOOKUP(L48, Работы!$A$3:$D$184, 4, 0), 0) -> 903 | U48: =IF(OR(L48="3.1.1."), VLOOKUP(L48, Работы!$A$3:$D$184, 4, 0), 0) -> 0 | V48: =IF(OR(L48="3.1.2."), VLOOKUP(L48, Работы!$A$3:$D$184, 4, 0), 0) -> 0 | Y48: =IF(OR(L48="3.2.1.", L48="3.2.2."), VLOOKUP(L48, Работы!$A$3:$D$184, 4, 0), 0) -> 0 | Z48: =IF(OR(L48="3.4.1.", L48="3.4.2."), VLOOKUP(L48, Работы!$A$3:$D$184, 4, 0), 0) -> 0 | AA48: =P48*O48+Q48*T48+R48*T48+S48*T48+U48+V48+W48*Y48+X48*Y48+Z48 -> 903 | AE48: =AC48*AD48 -> 0 | AF48: =C48*Работы!$D$180 -> 591.91 | AG48: =AA48+AE48+AF48+AL48+AM48 -> 1494.91 | AJ48: =AG48-AA48*AI48 -> 1494.91 | AL48: =IF(OR(E48="да"), 4040, 0) -> 0 | AM48: =IF(OR(D48="доп."), AA48*0.1, 0) -> 0
A49: =ROW(A49)-10 -> 39 | B49: RO0322 | C49: =VLOOKUP(B49, Расстояния!B:J, 9, 0) -> 25 | D49: =VLOOKUP(B49, Расстояния!B:K, 10, 0) -> осн. | E49: =VLOOKUP(B49, Расстояния!B:F, 5, 0) -> нет | F49: WO06720915 | G49: 46105.508 | H49: 46108.494 | I49: 46108.65 | J49: Ткаченко | L49: 1.2. | M49: =VLOOKUP(L49, Работы!A:B, 2, 0) -> Диагностика и устранение дефектов АФУ сектора БС (локализация неисправности или перепуток Net Monitor'ом, проверка/ремонт разъёмов, соединительных джемперов, проверка КСВ) | N49: Устранение перепутки | O49: 1 | P49: =IF(OR(L49="3.3.1.", L49="3.3.2.", L49="3.3.3.", L49="3.1.1.", L49="3.1.2.", L49="3.4.1.", L49="3.4.2."), 0, VLOOKUP(L49, Работы!$A$3:$D$184, 4, 0)) -> 4180 | T49: =IF(OR(L49="3.3.1.", L49="3.3.2.", L49="3.3.3."), VLOOKUP(L49, Работы!$A$3:$D$184, 4, 0), 0) -> 0 | U49: =IF(OR(L49="3.1.1."), VLOOKUP(L49, Работы!$A$3:$D$184, 4, 0), 0) -> 0 | V49: =IF(OR(L49="3.1.2."), VLOOKUP(L49, Работы!$A$3:$D$184, 4, 0), 0) -> 0 | Y49: =IF(OR(L49="3.2.1.", L49="3.2.2."), VLOOKUP(L49, Работы!$A$3:$D$184, 4, 0), 0) -> 0 | Z49: =IF(OR(L49="3.4.1.", L49="3.4.2."), VLOOKUP(L49, Работы!$A$3:$D$184, 4, 0), 0) -> 0 | AA49: =P49*O49+Q49*T49+R49*T49+S49*T49+U49+V49+W49*Y49+X49*Y49+Z49 -> 4180 | AE49: =AC49*AD49 -> 0 | AF49: =C49*Работы!$D$180 -> 1345.25 | AG49: =AA49+AE49+AF49+AL49+AM49 -> 5525.25 | AJ49: =AG49-AA49*AI49 -> 5525.25 | AL49: =IF(OR(E49="да"), 4040, 0) -> 0 | AM49: =IF(OR(D49="доп."), AA49*0.1, 0) -> 0
A50: =ROW(A50)-10 -> 40 | B50: RO0322 | C50: 0 | D50: =VLOOKUP(B50, Расстояния!B:K, 10, 0) -> осн. | E50: =VLOOKUP(B50, Расстояния!B:F, 5, 0) -> нет | H50: 46108.608 | I50: 46108.65 | J50: Ткаченко | L50: 1.1. | M50: =VLOOKUP(L50, Работы!A:B, 2, 0) -> Техническое обслуживание БС | N50: Техническое обслуживание БС | O50: 1 | P50: =IF(OR(L50="3.3.1.", L50="3.3.2.", L50="3.3.3.", L50="3.1.1.", L50="3.1.2.", L50="3.4.1.", L50="3.4.2."), 0, VLOOKUP(L50, Работы!$A$3:$D$184, 4, 0)) -> 4143 | T50: =IF(OR(L50="3.3.1.", L50="3.3.2.", L50="3.3.3."), VLOOKUP(L50, Работы!$A$3:$D$184, 4, 0), 0) -> 0 | U50: =IF(OR(L50="3.1.1."), VLOOKUP(L50, Работы!$A$3:$D$184, 4, 0), 0) -> 0 | V50: =IF(OR(L50="3.1.2."), VLOOKUP(L50, Работы!$A$3:$D$184, 4, 0), 0) -> 0 | Y50: =IF(OR(L50="3.2.1.", L50="3.2.2."), VLOOKUP(L50, Работы!$A$3:$D$184, 4, 0), 0) -> 0 | Z50: =IF(OR(L50="3.4.1.", L50="3.4.2."), VLOOKUP(L50, Работы!$A$3:$D$184, 4, 0), 0) -> 0 | AA50: =P50*O50+Q50*T50+R50*T50+S50*T50+U50+V50+W50*Y50+X50*Y50+Z50 -> 4143 | AE50: =AC50*AD50 -> 0 | AF50: =C50*Работы!$D$180 -> 0 | AG50: =AA50+AE50+AF50+AL50+AM50 -> 4143 | AJ50: =AG50-AA50*AI50 -> 4143 | AL50: =IF(OR(E50="да"), 4040, 0) -> 0 | AM50: =IF(OR(D50="доп."), AA50*0.1, 0) -> 0
A51: =ROW(A51)-10 -> 41 | B51: RO0322 | C51: 0 | D51: =VLOOKUP(B51, Расстояния!B:K, 10, 0) -> осн. | E51: =VLOOKUP(B51, Расстояния!B:F, 5, 0) -> нет | H51: 46108.608 | I51: 46108.65 | J51: Ткаченко | L51: 10.3. | M51: =VLOOKUP(L51, Работы!A:B, 2, 0) -> Иные работы/услуги в отношении одного Объекта по одному обращению Заказчика в течение рабочего времени*****, независимо от количества представителей Подрядчика, участвующих в выполнении таких Работ на одном Объекте | N51: Устранение SecOff | O51: 1 | P51: =IF(OR(L51="3.3.1.", L51="3.3.2.", L51="3.3.3.", L51="3.1.1.", L51="3.1.2.", L51="3.4.1.", L51="3.4.2."), 0, VLOOKUP(L51, Работы!$A$3:$D$184, 4, 0)) -> 735 | T51: =IF(OR(L51="3.3.1.", L51="3.3.2.", L51="3.3.3."), VLOOKUP(L51, Работы!$A$3:$D$184, 4, 0), 0) -> 0 | U51: =IF(OR(L51="3.1.1."), VLOOKUP(L51, Работы!$A$3:$D$184, 4, 0), 0) -> 0 | V51: =IF(OR(L51="3.1.2."), VLOOKUP(L51, Работы!$A$3:$D$184, 4, 0), 0) -> 0 | Y51: =IF(OR(L51="3.2.1.", L51="3.2.2."), VLOOKUP(L51, Работы!$A$3:$D$184, 4, 0), 0) -> 0 | Z51: =IF(OR(L51="3.4.1.", L51="3.4.2."), VLOOKUP(L51, Работы!$A$3:$D$184, 4, 0), 0) -> 0 | AA51: =P51*O51+Q51*T51+R51*T51+S51*T51+U51+V51+W51*Y51+X51*Y51+Z51 -> 735 | AE51: =AC51*AD51 -> 0 | AF51: =C51*Работы!$D$180 -> 0 | AG51: =AA51+AE51+AF51+AL51+AM51 -> 735 | AJ51: =AG51-AA51*AI51 -> 735 | AL51: =IF(OR(E51="да"), 4040, 0) -> 0 | AM51: =IF(OR(D51="доп."), AA51*0.1, 0) -> 0
A52: =ROW(A52)-10 -> 42 | B52: RO0326 | C52: =VLOOKUP(B52, Расстояния!B:J, 9, 0) -> 107 | D52: =VLOOKUP(B52, Расстояния!B:K, 10, 0) -> осн. | E52: =VLOOKUP(B52, Расстояния!B:F, 5, 0) -> нет | F52: WO06717286 | G52: 46101.403 | H52: 46101.479 | I52: 46101.515 | J52: Голиков | L52: 3.1.1. | M52: =VLOOKUP(L52, Работы!A:B, 2, 0) -> Стоимость аварийно-восстановительных работ, заявка по которым получена в течение рабочего времени | N52: Замена SFP на AREA | P52: =IF(OR(L52="3.3.1.", L52="3.3.2.", L52="3.3.3.", L52="3.1.1.", L52="3.1.2.", L52="3.4.1.", L52="3.4.2."), 0, VLOOKUP(L52, Работы!$A$3:$D$184, 4, 0)) -> 0 | T52: =IF(OR(L52="3.3.1.", L52="3.3.2.", L52="3.3.3."), VLOOKUP(L52, Работы!$A$3:$D$184, 4, 0), 0) -> 0 | U52: =IF(OR(L52="3.1.1."), VLOOKUP(L52, Работы!$A$3:$D$184, 4, 0), 0) -> 3956 | V52: =IF(OR(L52="3.1.2."), VLOOKUP(L52, Работы!$A$3:$D$184, 4, 0), 0) -> 0 | Y52: =IF(OR(L52="3.2.1.", L52="3.2.2."), VLOOKUP(L52, Работы!$A$3:$D$184, 4, 0), 0) -> 0 | Z52: =IF(OR(L52="3.4.1.", L52="3.4.2."), VLOOKUP(L52, Работы!$A$3:$D$184, 4, 0), 0) -> 0 | AA52: =P52*O52+Q52*T52+R52*T52+S52*T52+U52+V52+W52*Y52+X52*Y52+Z52 -> 3956 | AE52: =AC52*AD52 -> 0 | AF52: =C52*Работы!$D$180 -> 5757.67 | AG52: =AA52+AE52+AF52+AL52+AM52 -> 9713.67 | AJ52: =AG52-AA52*AI52 -> 9713.67 | AL52: =IF(OR(E52="да"), 4040, 0) -> 0 | AM52: =IF(OR(D52="доп."), AA52*0.1, 0) -> 0
A53: =ROW(A53)-10 -> 43 | B53: RO0327 | C53: =VLOOKUP(B53, Расстояния!B:J, 9, 0) -> 23 | D53: =VLOOKUP(B53, Расстояния!B:K, 10, 0) -> осн. | E53: =VLOOKUP(B53, Расстояния!B:F, 5, 0) -> нет | F53: WO06716548 | G53: 46100.476 | H53: 46100.532 | I53: 46100.626 | J53: Ткаченко | L53: 3.3.1. | M53: =VLOOKUP(L53, Работы!A:B, 2, 0) -> Стоимость Аварийно-восстановительных работ по обеспечению временного электроснабжения. (Ставка применяется с 1 часа выполнения Работ, для оплаты каждых не полных суток выполнения Работ) | N53: Генерация | P53: =IF(OR(L53="3.3.1.", L53="3.3.2.", L53="3.3.3.", L53="3.1.1.", L53="3.1.2.", L53="3.4.1.", L53="3.4.2."), 0, VLOOKUP(L53, Работы!$A$3:$D$184, 4, 0)) -> 0 | Q53: =ROUNDUP((I53-H53)*24, 0) -> 3 | T53: =IF(OR(L53="3.3.1.", L53="3.3.2.", L53="3.3.3."), VLOOKUP(L53, Работы!$A$3:$D$184, 4, 0), 0) -> 903 | U53: =IF(OR(L53="3.1.1."), VLOOKUP(L53, Работы!$A$3:$D$184, 4, 0), 0) -> 0 | V53: =IF(OR(L53="3.1.2."), VLOOKUP(L53, Работы!$A$3:$D$184, 4, 0), 0) -> 0 | Y53: =IF(OR(L53="3.2.1.", L53="3.2.2."), VLOOKUP(L53, Работы!$A$3:$D$184, 4, 0), 0) -> 0 | Z53: =IF(OR(L53="3.4.1.", L53="3.4.2."), VLOOKUP(L53, Работы!$A$3:$D$184, 4, 0), 0) -> 0 | AA53: =P53*O53+Q53*T53+R53*T53+S53*T53+U53+V53+W53*Y53+X53*Y53+Z53 -> 2709 | AE53: =AC53*AD53 -> 0 | AF53: =C53*Работы!$D$180 -> 1237.63 | AG53: =AA53+AE53+AF53+AL53+AM53 -> 3946.63 | AJ53: =AG53-AA53*AI53 -> 3946.63 | AL53: =IF(OR(E53="да"), 4040, 0) -> 0 | AM53: =IF(OR(D53="доп."), AA53*0.1, 0) -> 0
A54: =ROW(A54)-10 -> 44 | B54: RO0327 | C54: 0 | D54: =VLOOKUP(B54, Расстояния!B:K, 10, 0) -> осн. | E54: =VLOOKUP(B54, Расстояния!B:F, 5, 0) -> нет | F54: WO06716710 | G54: 46100.56 | H54: 46100.532 | I54: 46100.626 | J54: Ткаченко | L54: 5.13. | M54: =VLOOKUP(L54, Работы!A:B, 2, 0) -> Замена вводного автоматического выключателя, рубильника | N54: Замена вводного автомата | O54: 1 | P54: =IF(OR(L54="3.3.1.", L54="3.3.2.", L54="3.3.3.", L54="3.1.1.", L54="3.1.2.", L54="3.4.1.", L54="3.4.2."), 0, VLOOKUP(L54, Работы!$A$3:$D$184, 4, 0)) -> 987 | T54: =IF(OR(L54="3.3.1.", L54="3.3.2.", L54="3.3.3."), VLOOKUP(L54, Работы!$A$3:$D$184, 4, 0), 0) -> 0 | U54: =IF(OR(L54="3.1.1."), VLOOKUP(L54, Работы!$A$3:$D$184, 4, 0), 0) -> 0 | V54: =IF(OR(L54="3.1.2."), VLOOKUP(L54, Работы!$A$3:$D$184, 4, 0), 0) -> 0 | Y54: =IF(OR(L54="3.2.1.", L54="3.2.2."), VLOOKUP(L54, Работы!$A$3:$D$184, 4, 0), 0) -> 0 | Z54: =IF(OR(L54="3.4.1.", L54="3.4.2."), VLOOKUP(L54, Работы!$A$3:$D$184, 4, 0), 0) -> 0 | AA54: =P54*O54+Q54*T54+R54*T54+S54*T54+U54+V54+W54*Y54+X54*Y54+Z54 -> 987 | AE54: =AC54*AD54 -> 0 | AF54: =C54*Работы!$D$180 -> 0 | AG54: =AA54+AE54+AF54+AL54+AM54 -> 987 | AJ54: =AG54-AA54*AI54 -> 987 | AL54: =IF(OR(E54="да"), 4040, 0) -> 0 | AM54: =IF(OR(D54="доп."), AA54*0.1, 0) -> 0
A55: =ROW(A55)-10 -> 45 | B55: RO0327 | C55: 0 | D55: =VLOOKUP(B55, Расстояния!B:K, 10, 0) -> осн. | E55: =VLOOKUP(B55, Расстояния!B:F, 5, 0) -> нет | F55: WO06716710 | G55: 46100.56 | H55: 46100.532 | I55: 46100.626 | J55: Ткаченко | T55: =IF(OR(L55="3.3.1.", L55="3.3.2.", L55="3.3.3."), VLOOKUP(L55, Работы!$A$3:$D$184, 4, 0), 0) -> 0 | U55: =IF(OR(L55="3.1.1."), VLOOKUP(L55, Работы!$A$3:$D$184, 4, 0), 0) -> 0 | V55: =IF(OR(L55="3.1.2."), VLOOKUP(L55, Работы!$A$3:$D$184, 4, 0), 0) -> 0 | Y55: =IF(OR(L55="3.2.1.", L55="3.2.2."), VLOOKUP(L55, Работы!$A$3:$D$184, 4, 0), 0) -> 0 | Z55: =IF(OR(L55="3.4.1.", L55="3.4.2."), VLOOKUP(L55, Работы!$A$3:$D$184, 4, 0), 0) -> 0 | AA55: =P55*O55+Q55*T55+R55*T55+S55*T55+U55+V55+W55*Y55+X55*Y55+Z55 -> 0 | AB55: 3ех полюсный автомат ABB | AC55: 1 | AD55: 1650 | AE55: =AC55*AD55 -> 1650 | AF55: =C55*Работы!$D$180 -> 0 | AG55: =AA55+AE55+AF55+AL55+AM55 -> 1650 | AJ55: =AG55-AA55*AI55 -> 1650 | AL55: =IF(OR(E55="да"), 4040, 0) -> 0 | AM55: =IF(OR(D55="доп."), AA55*0.1, 0) -> 0
A56: =ROW(A56)-10 -> 46 | B56: RO0342 | C56: =VLOOKUP(B56, Расстояния!B:J, 9, 0) -> 10 | D56: =VLOOKUP(B56, Расстояния!B:K, 10, 0) -> осн. | E56: =VLOOKUP(B56, Расстояния!B:F, 5, 0) -> нет | H56: 46104.59 | I56: 46104.665 | J56: Ткаченко | L56: 1.1. | M56: =VLOOKUP(L56, Работы!A:B, 2, 0) -> Техническое обслуживание БС | N56: Техническое обслуживание БС | O56: 1 | P56: =IF(OR(L56="3.3.1.", L56="3.3.2.", L56="3.3.3.", L56="3.1.1.", L56="3.1.2.", L56="3.4.1.", L56="3.4.2."), 0, VLOOKUP(L56, Работы!$A$3:$D$184, 4, 0)) -> 4143 | T56: =IF(OR(L56="3.3.1.", L56="3.3.2.", L56="3.3.3."), VLOOKUP(L56, Работы!$A$3:$D$184, 4, 0), 0) -> 0 | U56: =IF(OR(L56="3.1.1."), VLOOKUP(L56, Работы!$A$3:$D$184, 4, 0), 0) -> 0 | V56: =IF(OR(L56="3.1.2."), VLOOKUP(L56, Работы!$A$3:$D$184, 4, 0), 0) -> 0 | Y56: =IF(OR(L56="3.2.1.", L56="3.2.2."), VLOOKUP(L56, Работы!$A$3:$D$184, 4, 0), 0) -> 0 | Z56: =IF(OR(L56="3.4.1.", L56="3.4.2."), VLOOKUP(L56, Работы!$A$3:$D$184, 4, 0), 0) -> 0 | AA56: =P56*O56+Q56*T56+R56*T56+S56*T56+U56+V56+W56*Y56+X56*Y56+Z56 -> 4143 | AE56: =AC56*AD56 -> 0 | AF56: =C56*Работы!$D$180 -> 538.1 | AG56: =AA56+AE56+AF56+AL56+AM56 -> 4681.1 | AJ56: =AG56-AA56*AI56 -> 4681.1 | AL56: =IF(OR(E56="да"), 4040, 0) -> 0 | AM56: =IF(OR(D56="доп."), AA56*0.1, 0) -> 0
A57: =ROW(A57)-10 -> 47 | B57: RO0343 | C57: =VLOOKUP(B57, Расстояния!B:J, 9, 0) -> 9 | D57: =VLOOKUP(B57, Расстояния!B:K, 10, 0) -> осн. | E57: =VLOOKUP(B57, Расстояния!B:F, 5, 0) -> нет | H57: 46099.543 | I57: 46099.655 | J57: Ткаченко | L57: 1.1. | M57: =VLOOKUP(L57, Работы!A:B, 2, 0) -> Техническое обслуживание БС | N57: Техническое обслуживание БС | O57: 1 | P57: =IF(OR(L57="3.3.1.", L57="3.3.2.", L57="3.3.3.", L57="3.1.1.", L57="3.1.2.", L57="3.4.1.", L57="3.4.2."), 0, VLOOKUP(L57, Работы!$A$3:$D$184, 4, 0)) -> 4143 | T57: =IF(OR(L57="3.3.1.", L57="3.3.2.", L57="3.3.3."), VLOOKUP(L57, Работы!$A$3:$D$184, 4, 0), 0) -> 0 | U57: =IF(OR(L57="3.1.1."), VLOOKUP(L57, Работы!$A$3:$D$184, 4, 0), 0) -> 0 | V57: =IF(OR(L57="3.1.2."), VLOOKUP(L57, Работы!$A$3:$D$184, 4, 0), 0) -> 0 | Y57: =IF(OR(L57="3.2.1.", L57="3.2.2."), VLOOKUP(L57, Работы!$A$3:$D$184, 4, 0), 0) -> 0 | Z57: =IF(OR(L57="3.4.1.", L57="3.4.2."), VLOOKUP(L57, Работы!$A$3:$D$184, 4, 0), 0) -> 0 | AA57: =P57*O57+Q57*T57+R57*T57+S57*T57+U57+V57+W57*Y57+X57*Y57+Z57 -> 4143 | AE57: =AC57*AD57 -> 0 | AF57: =C57*Работы!$D$180 -> 484.29 | AG57: =AA57+AE57+AF57+AL57+AM57 -> 4627.29 | AJ57: =AG57-AA57*AI57 -> 4627.29 | AL57: =IF(OR(E57="да"), 4040, 0) -> 0 | AM57: =IF(OR(D57="доп."), AA57*0.1, 0) -> 0
A58: =ROW(A58)-10 -> 48 | B58: RO0343 | C58: 0 | D58: =VLOOKUP(B58, Расстояния!B:K, 10, 0) -> осн. | E58: =VLOOKUP(B58, Расстояния!B:F, 5, 0) -> нет | F58: WO06715791 | G58: 46099.626 | H58: 46099.543 | I58: 46099.655 | J58: Ткаченко | L58: 3.9. | M58: =VLOOKUP(L58, Работы!A:B, 2, 0) -> Восстановление крепления кабелей РРЛ, оптических кабелей, цифровых кабелей (1xAlarm, 1xLMP, 4xE1, 2xEthernet), кабелей питания DC (СИП 4*35, 4*50, ВБбШв2*25) по кабельному мосту, АМС включая зажимы, стяжки | N58: Демонтаж фидерной трассы, креплений оптики | O58: 20 | P58: =IF(OR(L58="3.3.1.", L58="3.3.2.", L58="3.3.3.", L58="3.1.1.", L58="3.1.2.", L58="3.4.1.", L58="3.4.2."), 0, VLOOKUP(L58, Работы!$A$3:$D$184, 4, 0)) -> 158 | T58: =IF(OR(L58="3.3.1.", L58="3.3.2.", L58="3.3.3."), VLOOKUP(L58, Работы!$A$3:$D$184, 4, 0), 0) -> 0 | U58: =IF(OR(L58="3.1.1."), VLOOKUP(L58, Работы!$A$3:$D$184, 4, 0), 0) -> 0 | V58: =IF(OR(L58="3.1.2."), VLOOKUP(L58, Работы!$A$3:$D$184, 4, 0), 0) -> 0 | Y58: =IF(OR(L58="3.2.1.", L58="3.2.2."), VLOOKUP(L58, Работы!$A$3:$D$184, 4, 0), 0) -> 0 | Z58: =IF(OR(L58="3.4.1.", L58="3.4.2."), VLOOKUP(L58, Работы!$A$3:$D$184, 4, 0), 0) -> 0 | AA58: =P58*O58+Q58*T58+R58*T58+S58*T58+U58+V58+W58*Y58+X58*Y58+Z58 -> 3160 | AE58: =AC58*AD58 -> 0 | AF58: =C58*Работы!$D$180 -> 0 | AG58: =AA58+AE58+AF58+AL58+AM58 -> 3160 | AJ58: =AG58-AA58*AI58 -> 3160 | AL58: =IF(OR(E58="да"), 4040, 0) -> 0 | AM58: =IF(OR(D58="доп."), AA58*0.1, 0) -> 0
A59: =ROW(A59)-10 -> 49 | B59: RO0358 | C59: =VLOOKUP(B59, Расстояния!B:J, 9, 0) -> 107 | D59: =VLOOKUP(B59, Расстояния!B:K, 10, 0) -> осн. | E59: =VLOOKUP(B59, Расстояния!B:F, 5, 0) -> нет | F59: WO06720824 | G59: 46105.49 | H59: 46105.607 | I59: 46105.708 | J59: Ткаченко | L59: 3.3.1. | M59: =VLOOKUP(L59, Работы!A:B, 2, 0) -> Стоимость Аварийно-восстановительных работ по обеспечению временного электроснабжения. (Ставка применяется с 1 часа выполнения Работ, для оплаты каждых не полных суток выполнения Работ) | N59: Генерация | P59: =IF(OR(L59="3.3.1.", L59="3.3.2.", L59="3.3.3.", L59="3.1.1.", L59="3.1.2.", L59="3.4.1.", L59="3.4.2."), 0, VLOOKUP(L59, Работы!$A$3:$D$184, 4, 0)) -> 0 | Q59: =ROUNDUP((I59-H59)*24, 0) -> 3 | T59: =IF(OR(L59="3.3.1.", L59="3.3.2.", L59="3.3.3."), VLOOKUP(L59, Работы!$A$3:$D$184, 4, 0), 0) -> 903 | U59: =IF(OR(L59="3.1.1."), VLOOKUP(L59, Работы!$A$3:$D$184, 4, 0), 0) -> 0 | V59: =IF(OR(L59="3.1.2."), VLOOKUP(L59, Работы!$A$3:$D$184, 4, 0), 0) -> 0 | Y59: =IF(OR(L59="3.2.1.", L59="3.2.2."), VLOOKUP(L59, Работы!$A$3:$D$184, 4, 0), 0) -> 0 | Z59: =IF(OR(L59="3.4.1.", L59="3.4.2."), VLOOKUP(L59, Работы!$A$3:$D$184, 4, 0), 0) -> 0 | AA59: =P59*O59+Q59*T59+R59*T59+S59*T59+U59+V59+W59*Y59+X59*Y59+Z59 -> 2709 | AE59: =AC59*AD59 -> 0 | AF59: =C59*Работы!$D$180 -> 5757.67 | AG59: =AA59+AE59+AF59+AL59+AM59 -> 8466.67 | AJ59: =AG59-AA59*AI59 -> 8466.67 | AL59: =IF(OR(E59="да"), 4040, 0) -> 0 | AM59: =IF(OR(D59="доп."), AA59*0.1, 0) -> 0
A60: =ROW(A60)-10 -> 50 | B60: RO0358 | C60: 0 | D60: =VLOOKUP(B60, Расстояния!B:K, 10, 0) -> осн. | E60: =VLOOKUP(B60, Расстояния!B:F, 5, 0) -> нет | H60: 46105.652 | I60: 46105.708 | J60: Ткаченко | L60: 1.1. | M60: =VLOOKUP(L60, Работы!A:B, 2, 0) -> Техническое обслуживание БС | N60: Техническое обслуживание БС | O60: 1 | P60: =IF(OR(L60="3.3.1.", L60="3.3.2.", L60="3.3.3.", L60="3.1.1.", L60="3.1.2.", L60="3.4.1.", L60="3.4.2."), 0, VLOOKUP(L60, Работы!$A$3:$D$184, 4, 0)) -> 4143 | T60: =IF(OR(L60="3.3.1.", L60="3.3.2.", L60="3.3.3."), VLOOKUP(L60, Работы!$A$3:$D$184, 4, 0), 0) -> 0 | U60: =IF(OR(L60="3.1.1."), VLOOKUP(L60, Работы!$A$3:$D$184, 4, 0), 0) -> 0 | V60: =IF(OR(L60="3.1.2."), VLOOKUP(L60, Работы!$A$3:$D$184, 4, 0), 0) -> 0 | Y60: =IF(OR(L60="3.2.1.", L60="3.2.2."), VLOOKUP(L60, Работы!$A$3:$D$184, 4, 0), 0) -> 0 | Z60: =IF(OR(L60="3.4.1.", L60="3.4.2."), VLOOKUP(L60, Работы!$A$3:$D$184, 4, 0), 0) -> 0 | AA60: =P60*O60+Q60*T60+R60*T60+S60*T60+U60+V60+W60*Y60+X60*Y60+Z60 -> 4143 | AE60: =AC60*AD60 -> 0 | AF60: =C60*Работы!$D$180 -> 0 | AG60: =AA60+AE60+AF60+AL60+AM60 -> 4143 | AJ60: =AG60-AA60*AI60 -> 4143 | AL60: =IF(OR(E60="да"), 4040, 0) -> 0 | AM60: =IF(OR(D60="доп."), AA60*0.1, 0) -> 0
A61: =ROW(A61)-10 -> 51 | B61: RO0358 | C61: 0 | D61: =VLOOKUP(B61, Расстояния!B:K, 10, 0) -> осн. | E61: =VLOOKUP(B61, Расстояния!B:F, 5, 0) -> нет | H61: 46105.652 | I61: 46105.708 | J61: Ткаченко | L61: 4.5 | M61: =VLOOKUP(L61, Работы!A:B, 2, 0) -> Стоимость проведения инвентаризации Объекта. | N61: Инвентаризация БС | O61: 1 | P61: =IF(OR(L61="3.3.1.", L61="3.3.2.", L61="3.3.3.", L61="3.1.1.", L61="3.1.2.", L61="3.4.1.", L61="3.4.2."), 0, VLOOKUP(L61, Работы!$A$3:$D$184, 4, 0)) -> 735 | T61: =IF(OR(L61="3.3.1.", L61="3.3.2.", L61="3.3.3."), VLOOKUP(L61, Работы!$A$3:$D$184, 4, 0), 0) -> 0 | U61: =IF(OR(L61="3.1.1."), VLOOKUP(L61, Работы!$A$3:$D$184, 4, 0), 0) -> 0 | V61: =IF(OR(L61="3.1.2."), VLOOKUP(L61, Работы!$A$3:$D$184, 4, 0), 0) -> 0 | Y61: =IF(OR(L61="3.2.1.", L61="3.2.2."), VLOOKUP(L61, Работы!$A$3:$D$184, 4, 0), 0) -> 0 | Z61: =IF(OR(L61="3.4.1.", L61="3.4.2."), VLOOKUP(L61, Работы!$A$3:$D$184, 4, 0), 0) -> 0 | AA61: =P61*O61+Q61*T61+R61*T61+S61*T61+U61+V61+W61*Y61+X61*Y61+Z61 -> 735 | AE61: =AC61*AD61 -> 0 | AF61: =C61*Работы!$D$180 -> 0 | AG61: =AA61+AE61+AF61+AL61+AM61 -> 735 | AJ61: =AG61-AA61*AI61 -> 735 | AL61: =IF(OR(E61="да"), 4040, 0) -> 0 | AM61: =IF(OR(D61="доп."), AA61*0.1, 0) -> 0
A62: =ROW(A62)-10 -> 52 | B62: RO0359 | C62: =VLOOKUP(B62, Расстояния!B:J, 9, 0) -> 52 | D62: =VLOOKUP(B62, Расстояния!B:K, 10, 0) -> осн. | E62: =VLOOKUP(B62, Расстояния!B:F, 5, 0) -> нет | F62: WO06720686 | G62: 46105.456 | H62: 46105.535 | I62: 46105.74 | J62: Титенко | L62: 3.3.1. | M62: =VLOOKUP(L62, Работы!A:B, 2, 0) -> Стоимость Аварийно-восстановительных работ по обеспечению временного электроснабжения. (Ставка применяется с 1 часа выполнения Работ, для оплаты каждых не полных суток выполнения Работ) | N62: Генерация | P62: =IF(OR(L62="3.3.1.", L62="3.3.2.", L62="3.3.3.", L62="3.1.1.", L62="3.1.2.", L62="3.4.1.", L62="3.4.2."), 0, VLOOKUP(L62, Работы!$A$3:$D$184, 4, 0)) -> 0 | Q62: =ROUNDUP((I62-H62)*24, 0) -> 5 | T62: =IF(OR(L62="3.3.1.", L62="3.3.2.", L62="3.3.3."), VLOOKUP(L62, Работы!$A$3:$D$184, 4, 0), 0) -> 903 | U62: =IF(OR(L62="3.1.1."), VLOOKUP(L62, Работы!$A$3:$D$184, 4, 0), 0) -> 0 | V62: =IF(OR(L62="3.1.2."), VLOOKUP(L62, Работы!$A$3:$D$184, 4, 0), 0) -> 0 | Y62: =IF(OR(L62="3.2.1.", L62="3.2.2."), VLOOKUP(L62, Работы!$A$3:$D$184, 4, 0), 0) -> 0 | Z62: =IF(OR(L62="3.4.1.", L62="3.4.2."), VLOOKUP(L62, Работы!$A$3:$D$184, 4, 0), 0) -> 0 | AA62: =P62*O62+Q62*T62+R62*T62+S62*T62+U62+V62+W62*Y62+X62*Y62+Z62 -> 4515 | AE62: =AC62*AD62 -> 0 | AF62: =C62*Работы!$D$180 -> 2798.12 | AG62: =AA62+AE62+AF62+AL62+AM62 -> 7313.12 | AJ62: =AG62-AA62*AI62 -> 7313.12 | AL62: =IF(OR(E62="да"), 4040, 0) -> 0 | AM62: =IF(OR(D62="доп."), AA62*0.1, 0) -> 0
A63: =ROW(A63)-10 -> 53 | B63: RO0369 | C63: =VLOOKUP(B63, Расстояния!B:J, 9, 0) -> 68 | D63: =VLOOKUP(B63, Расстояния!B:K, 10, 0) -> осн. | E63: =VLOOKUP(B63, Расстояния!B:F, 5, 0) -> нет | F63: WO06722685 | G63: 46106.542 | H63: 46106.688 | I63: 46106.785 | J63: Титенко | L63: 3.3.1. | M63: =VLOOKUP(L63, Работы!A:B, 2, 0) -> Стоимость Аварийно-восстановительных работ по обеспечению временного электроснабжения. (Ставка применяется с 1 часа выполнения Работ, для оплаты каждых не полных суток выполнения Работ) | N63: Генерация | P63: =IF(OR(L63="3.3.1.", L63="3.3.2.", L63="3.3.3.", L63="3.1.1.", L63="3.1.2.", L63="3.4.1.", L63="3.4.2."), 0, VLOOKUP(L63, Работы!$A$3:$D$184, 4, 0)) -> 0 | Q63: =ROUNDUP((I63-H63)*24, 0) -> 3 | T63: =IF(OR(L63="3.3.1.", L63="3.3.2.", L63="3.3.3."), VLOOKUP(L63, Работы!$A$3:$D$184, 4, 0), 0) -> 903 | U63: =IF(OR(L63="3.1.1."), VLOOKUP(L63, Работы!$A$3:$D$184, 4, 0), 0) -> 0 | V63: =IF(OR(L63="3.1.2."), VLOOKUP(L63, Работы!$A$3:$D$184, 4, 0), 0) -> 0 | Y63: =IF(OR(L63="3.2.1.", L63="3.2.2."), VLOOKUP(L63, Работы!$A$3:$D$184, 4, 0), 0) -> 0 | Z63: =IF(OR(L63="3.4.1.", L63="3.4.2."), VLOOKUP(L63, Работы!$A$3:$D$184, 4, 0), 0) -> 0 | AA63: =P63*O63+Q63*T63+R63*T63+S63*T63+U63+V63+W63*Y63+X63*Y63+Z63 -> 2709 | AE63: =AC63*AD63 -> 0 | AF63: =C63*Работы!$D$180 -> 3659.08 | AG63: =AA63+AE63+AF63+AL63+AM63 -> 6368.08 | AJ63: =AG63-AA63*AI63 -> 6368.08 | AL63: =IF(OR(E63="да"), 4040, 0) -> 0 | AM63: =IF(OR(D63="доп."), AA63*0.1, 0) -> 0
A64: =ROW(A64)-10 -> 54 | B64: RO0399 | C64: =VLOOKUP(B64, Расстояния!B:J, 9, 0) -> 66 | D64: =VLOOKUP(B64, Расстояния!B:K, 10, 0) -> осн. | E64: =VLOOKUP(B64, Расстояния!B:F, 5, 0) -> нет | F64: WO06725097 | G64: 46108.59 | H64: 46111.447 | I64: 46111.493 | J64: Голиков | L64: 1.13. | M64: =VLOOKUP(L64, Работы!A:B, 2, 0) -> Изменение механического угла наклона или азимута одной антенны | N64: Изменение азимута одной антенны | O64: 1 | P64: =IF(OR(L64="3.3.1.", L64="3.3.2.", L64="3.3.3.", L64="3.1.1.", L64="3.1.2.", L64="3.4.1.", L64="3.4.2."), 0, VLOOKUP(L64, Работы!$A$3:$D$184, 4, 0)) -> 2085 | T64: =IF(OR(L64="3.3.1.", L64="3.3.2.", L64="3.3.3."), VLOOKUP(L64, Работы!$A$3:$D$184, 4, 0), 0) -> 0 | U64: =IF(OR(L64="3.1.1."), VLOOKUP(L64, Работы!$A$3:$D$184, 4, 0), 0) -> 0 | V64: =IF(OR(L64="3.1.2."), VLOOKUP(L64, Работы!$A$3:$D$184, 4, 0), 0) -> 0 | Y64: =IF(OR(L64="3.2.1.", L64="3.2.2."), VLOOKUP(L64, Работы!$A$3:$D$184, 4, 0), 0) -> 0 | Z64: =IF(OR(L64="3.4.1.", L64="3.4.2."), VLOOKUP(L64, Работы!$A$3:$D$184, 4, 0), 0) -> 0 | AA64: =P64*O64+Q64*T64+R64*T64+S64*T64+U64+V64+W64*Y64+X64*Y64+Z64 -> 2085 | AE64: =AC64*AD64 -> 0 | AF64: =C64*Работы!$D$180 -> 3551.46 | AG64: =AA64+AE64+AF64+AL64+AM64 -> 5636.46 | AJ64: =AG64-AA64*AI64 -> 5636.46 | AL64: =IF(OR(E64="да"), 4040, 0) -> 0 | AM64: =IF(OR(D64="доп."), AA64*0.1, 0) -> 0
A65: =ROW(A65)-10 -> 55 | B65: RO0408 | C65: =VLOOKUP(B65, Расстояния!B:J, 9, 0) -> 6 | D65: =VLOOKUP(B65, Расстояния!B:K, 10, 0) -> осн. | E65: =VLOOKUP(B65, Расстояния!B:F, 5, 0) -> нет | H65: 46108.424 | I65: 46108.521 | J65: Баженов | L65: 1.1. | M65: =VLOOKUP(L65, Работы!A:B, 2, 0) -> Техническое обслуживание БС | N65: Техническое обслуживание БС | O65: 1 | P65: =IF(OR(L65="3.3.1.", L65="3.3.2.", L65="3.3.3.", L65="3.1.1.", L65="3.1.2.", L65="3.4.1.", L65="3.4.2."), 0, VLOOKUP(L65, Работы!$A$3:$D$184, 4, 0)) -> 4143 | T65: =IF(OR(L65="3.3.1.", L65="3.3.2.", L65="3.3.3."), VLOOKUP(L65, Работы!$A$3:$D$184, 4, 0), 0) -> 0 | U65: =IF(OR(L65="3.1.1."), VLOOKUP(L65, Работы!$A$3:$D$184, 4, 0), 0) -> 0 | V65: =IF(OR(L65="3.1.2."), VLOOKUP(L65, Работы!$A$3:$D$184, 4, 0), 0) -> 0 | Y65: =IF(OR(L65="3.2.1.", L65="3.2.2."), VLOOKUP(L65, Работы!$A$3:$D$184, 4, 0), 0) -> 0 | Z65: =IF(OR(L65="3.4.1.", L65="3.4.2."), VLOOKUP(L65, Работы!$A$3:$D$184, 4, 0), 0) -> 0 | AA65: =P65*O65+Q65*T65+R65*T65+S65*T65+U65+V65+W65*Y65+X65*Y65+Z65 -> 4143 | AE65: =AC65*AD65 -> 0 | AF65: =C65*Работы!$D$180 -> 322.86 | AG65: =AA65+AE65+AF65+AL65+AM65 -> 4465.86 | AJ65: =AG65-AA65*AI65 -> 4465.86 | AL65: =IF(OR(E65="да"), 4040, 0) -> 0 | AM65: =IF(OR(D65="доп."), AA65*0.1, 0) -> 0
A66: =ROW(A66)-10 -> 56 | B66: RO0409 | C66: =VLOOKUP(B66, Расстояния!B:J, 9, 0) -> 5 | D66: =VLOOKUP(B66, Расстояния!B:K, 10, 0) -> осн. | E66: =VLOOKUP(B66, Расстояния!B:F, 5, 0) -> нет | H66: 46100.436 | I66: 46100.528 | J66: Баженов | L66: 1.1. | M66: =VLOOKUP(L66, Работы!A:B, 2, 0) -> Техническое обслуживание БС | N66: Техническое обслуживание БС | O66: 1 | P66: =IF(OR(L66="3.3.1.", L66="3.3.2.", L66="3.3.3.", L66="3.1.1.", L66="3.1.2.", L66="3.4.1.", L66="3.4.2."), 0, VLOOKUP(L66, Работы!$A$3:$D$184, 4, 0)) -> 4143 | T66: =IF(OR(L66="3.3.1.", L66="3.3.2.", L66="3.3.3."), VLOOKUP(L66, Работы!$A$3:$D$184, 4, 0), 0) -> 0 | U66: =IF(OR(L66="3.1.1."), VLOOKUP(L66, Работы!$A$3:$D$184, 4, 0), 0) -> 0 | V66: =IF(OR(L66="3.1.2."), VLOOKUP(L66, Работы!$A$3:$D$184, 4, 0), 0) -> 0 | Y66: =IF(OR(L66="3.2.1.", L66="3.2.2."), VLOOKUP(L66, Работы!$A$3:$D$184, 4, 0), 0) -> 0 | Z66: =IF(OR(L66="3.4.1.", L66="3.4.2."), VLOOKUP(L66, Работы!$A$3:$D$184, 4, 0), 0) -> 0 | AA66: =P66*O66+Q66*T66+R66*T66+S66*T66+U66+V66+W66*Y66+X66*Y66+Z66 -> 4143 | AE66: =AC66*AD66 -> 0 | AF66: =C66*Работы!$D$180 -> 269.05 | AG66: =AA66+AE66+AF66+AL66+AM66 -> 4412.05 | AJ66: =AG66-AA66*AI66 -> 4412.05 | AL66: =IF(OR(E66="да"), 4040, 0) -> 0 | AM66: =IF(OR(D66="доп."), AA66*0.1, 0) -> 0
A67: =ROW(A67)-10 -> 57 | B67: RO0409 | C67: 0 | D67: =VLOOKUP(B67, Расстояния!B:K, 10, 0) -> осн. | E67: =VLOOKUP(B67, Расстояния!B:F, 5, 0) -> нет | H67: 46100.436 | I67: 46100.528 | J67: Баженов | L67: 4.5 | M67: =VLOOKUP(L67, Работы!A:B, 2, 0) -> Стоимость проведения инвентаризации Объекта. | N67: Инвентаризация БС | O67: 1 | P67: =IF(OR(L67="3.3.1.", L67="3.3.2.", L67="3.3.3.", L67="3.1.1.", L67="3.1.2.", L67="3.4.1.", L67="3.4.2."), 0, VLOOKUP(L67, Работы!$A$3:$D$184, 4, 0)) -> 735 | T67: =IF(OR(L67="3.3.1.", L67="3.3.2.", L67="3.3.3."), VLOOKUP(L67, Работы!$A$3:$D$184, 4, 0), 0) -> 0 | U67: =IF(OR(L67="3.1.1."), VLOOKUP(L67, Работы!$A$3:$D$184, 4, 0), 0) -> 0 | V67: =IF(OR(L67="3.1.2."), VLOOKUP(L67, Работы!$A$3:$D$184, 4, 0), 0) -> 0 | Y67: =IF(OR(L67="3.2.1.", L67="3.2.2."), VLOOKUP(L67, Работы!$A$3:$D$184, 4, 0), 0) -> 0 | Z67: =IF(OR(L67="3.4.1.", L67="3.4.2."), VLOOKUP(L67, Работы!$A$3:$D$184, 4, 0), 0) -> 0 | AA67: =P67*O67+Q67*T67+R67*T67+S67*T67+U67+V67+W67*Y67+X67*Y67+Z67 -> 735 | AE67: =AC67*AD67 -> 0 | AF67: =C67*Работы!$D$180 -> 0 | AG67: =AA67+AE67+AF67+AL67+AM67 -> 735 | AJ67: =AG67-AA67*AI67 -> 735 | AL67: =IF(OR(E67="да"), 4040, 0) -> 0 | AM67: =IF(OR(D67="доп."), AA67*0.1, 0) -> 0
A68: =ROW(A68)-10 -> 58 | B68: RO0411 | C68: =VLOOKUP(B68, Расстояния!B:J, 9, 0) -> 5 | D68: =VLOOKUP(B68, Расстояния!B:K, 10, 0) -> осн. | E68: =VLOOKUP(B68, Расстояния!B:F, 5, 0) -> нет | H68: 46101.532 | I68: 46101.59 | J68: Баженов | L68: 1.1. | M68: =VLOOKUP(L68, Работы!A:B, 2, 0) -> Техническое обслуживание БС | N68: Техническое обслуживание БС | O68: 1 | P68: =IF(OR(L68="3.3.1.", L68="3.3.2.", L68="3.3.3.", L68="3.1.1.", L68="3.1.2.", L68="3.4.1.", L68="3.4.2."), 0, VLOOKUP(L68, Работы!$A$3:$D$184, 4, 0)) -> 4143 | T68: =IF(OR(L68="3.3.1.", L68="3.3.2.", L68="3.3.3."), VLOOKUP(L68, Работы!$A$3:$D$184, 4, 0), 0) -> 0 | U68: =IF(OR(L68="3.1.1."), VLOOKUP(L68, Работы!$A$3:$D$184, 4, 0), 0) -> 0 | V68: =IF(OR(L68="3.1.2."), VLOOKUP(L68, Работы!$A$3:$D$184, 4, 0), 0) -> 0 | Y68: =IF(OR(L68="3.2.1.", L68="3.2.2."), VLOOKUP(L68, Работы!$A$3:$D$184, 4, 0), 0) -> 0 | Z68: =IF(OR(L68="3.4.1.", L68="3.4.2."), VLOOKUP(L68, Работы!$A$3:$D$184, 4, 0), 0) -> 0 | AA68: =P68*O68+Q68*T68+R68*T68+S68*T68+U68+V68+W68*Y68+X68*Y68+Z68 -> 4143 | AE68: =AC68*AD68 -> 0 | AF68: =C68*Работы!$D$180 -> 269.05 | AG68: =AA68+AE68+AF68+AL68+AM68 -> 4412.05 | AJ68: =AG68-AA68*AI68 -> 4412.05 | AL68: =IF(OR(E68="да"), 4040, 0) -> 0 | AM68: =IF(OR(D68="доп."), AA68*0.1, 0) -> 0
A69: =ROW(A69)-10 -> 59 | B69: RO0411 | C69: 0 | D69: =VLOOKUP(B69, Расстояния!B:K, 10, 0) -> осн. | E69: =VLOOKUP(B69, Расстояния!B:F, 5, 0) -> нет | H69: 46101.532 | I69: 46101.59 | J69: Баженов | L69: 4.5 | M69: =VLOOKUP(L69, Работы!A:B, 2, 0) -> Стоимость проведения инвентаризации Объекта. | N69: Инвентаризация БС | O69: 1 | P69: =IF(OR(L69="3.3.1.", L69="3.3.2.", L69="3.3.3.", L69="3.1.1.", L69="3.1.2.", L69="3.4.1.", L69="3.4.2."), 0, VLOOKUP(L69, Работы!$A$3:$D$184, 4, 0)) -> 735 | T69: =IF(OR(L69="3.3.1.", L69="3.3.2.", L69="3.3.3."), VLOOKUP(L69, Работы!$A$3:$D$184, 4, 0), 0) -> 0 | U69: =IF(OR(L69="3.1.1."), VLOOKUP(L69, Работы!$A$3:$D$184, 4, 0), 0) -> 0 | V69: =IF(OR(L69="3.1.2."), VLOOKUP(L69, Работы!$A$3:$D$184, 4, 0), 0) -> 0 | Y69: =IF(OR(L69="3.2.1.", L69="3.2.2."), VLOOKUP(L69, Работы!$A$3:$D$184, 4, 0), 0) -> 0 | Z69: =IF(OR(L69="3.4.1.", L69="3.4.2."), VLOOKUP(L69, Работы!$A$3:$D$184, 4, 0), 0) -> 0 | AA69: =P69*O69+Q69*T69+R69*T69+S69*T69+U69+V69+W69*Y69+X69*Y69+Z69 -> 735 | AE69: =AC69*AD69 -> 0 | AF69: =C69*Работы!$D$180 -> 0 | AG69: =AA69+AE69+AF69+AL69+AM69 -> 735 | AJ69: =AG69-AA69*AI69 -> 735 | AL69: =IF(OR(E69="да"), 4040, 0) -> 0 | AM69: =IF(OR(D69="доп."), AA69*0.1, 0) -> 0
A70: =ROW(A70)-10 -> 60 | B70: RO0412 | C70: =VLOOKUP(B70, Расстояния!B:J, 9, 0) -> 6 | D70: =VLOOKUP(B70, Расстояния!B:K, 10, 0) -> осн. | E70: =VLOOKUP(B70, Расстояния!B:F, 5, 0) -> нет | H70: 46100.613 | I70: 46100.669 | J70: Баженов | L70: 1.1. | M70: =VLOOKUP(L70, Работы!A:B, 2, 0) -> Техническое обслуживание БС | N70: Техническое обслуживание БС | O70: 1 | P70: =IF(OR(L70="3.3.1.", L70="3.3.2.", L70="3.3.3.", L70="3.1.1.", L70="3.1.2.", L70="3.4.1.", L70="3.4.2."), 0, VLOOKUP(L70, Работы!$A$3:$D$184, 4, 0)) -> 4143 | T70: =IF(OR(L70="3.3.1.", L70="3.3.2.", L70="3.3.3."), VLOOKUP(L70, Работы!$A$3:$D$184, 4, 0), 0) -> 0 | U70: =IF(OR(L70="3.1.1."), VLOOKUP(L70, Работы!$A$3:$D$184, 4, 0), 0) -> 0 | V70: =IF(OR(L70="3.1.2."), VLOOKUP(L70, Работы!$A$3:$D$184, 4, 0), 0) -> 0 | Y70: =IF(OR(L70="3.2.1.", L70="3.2.2."), VLOOKUP(L70, Работы!$A$3:$D$184, 4, 0), 0) -> 0 | Z70: =IF(OR(L70="3.4.1.", L70="3.4.2."), VLOOKUP(L70, Работы!$A$3:$D$184, 4, 0), 0) -> 0 | AA70: =P70*O70+Q70*T70+R70*T70+S70*T70+U70+V70+W70*Y70+X70*Y70+Z70 -> 4143 | AE70: =AC70*AD70 -> 0 | AF70: =C70*Работы!$D$180 -> 322.86 | AG70: =AA70+AE70+AF70+AL70+AM70 -> 4465.86 | AJ70: =AG70-AA70*AI70 -> 4465.86 | AL70: =IF(OR(E70="да"), 4040, 0) -> 0 | AM70: =IF(OR(D70="доп."), AA70*0.1, 0) -> 0
A71: =ROW(A71)-10 -> 61 | B71: RO0412 | C71: 0 | D71: =VLOOKUP(B71, Расстояния!B:K, 10, 0) -> осн. | E71: =VLOOKUP(B71, Расстояния!B:F, 5, 0) -> нет | H71: 46100.613 | I71: 46100.669 | J71: Баженов | L71: 4.5 | M71: =VLOOKUP(L71, Работы!A:B, 2, 0) -> Стоимость проведения инвентаризации Объекта. | N71: Инвентаризация БС | O71: 1 | P71: =IF(OR(L71="3.3.1.", L71="3.3.2.", L71="3.3.3.", L71="3.1.1.", L71="3.1.2.", L71="3.4.1.", L71="3.4.2."), 0, VLOOKUP(L71, Работы!$A$3:$D$184, 4, 0)) -> 735 | T71: =IF(OR(L71="3.3.1.", L71="3.3.2.", L71="3.3.3."), VLOOKUP(L71, Работы!$A$3:$D$184, 4, 0), 0) -> 0 | U71: =IF(OR(L71="3.1.1."), VLOOKUP(L71, Работы!$A$3:$D$184, 4, 0), 0) -> 0 | V71: =IF(OR(L71="3.1.2."), VLOOKUP(L71, Работы!$A$3:$D$184, 4, 0), 0) -> 0 | Y71: =IF(OR(L71="3.2.1.", L71="3.2.2."), VLOOKUP(L71, Работы!$A$3:$D$184, 4, 0), 0) -> 0 | Z71: =IF(OR(L71="3.4.1.", L71="3.4.2."), VLOOKUP(L71, Работы!$A$3:$D$184, 4, 0), 0) -> 0 | AA71: =P71*O71+Q71*T71+R71*T71+S71*T71+U71+V71+W71*Y71+X71*Y71+Z71 -> 735 | AE71: =AC71*AD71 -> 0 | AF71: =C71*Работы!$D$180 -> 0 | AG71: =AA71+AE71+AF71+AL71+AM71 -> 735 | AJ71: =AG71-AA71*AI71 -> 735 | AL71: =IF(OR(E71="да"), 4040, 0) -> 0 | AM71: =IF(OR(D71="доп."), AA71*0.1, 0) -> 0
A72: =ROW(A72)-10 -> 62 | B72: RO0413 | C72: =VLOOKUP(B72, Расстояния!B:J, 9, 0) -> 2 | D72: =VLOOKUP(B72, Расстояния!B:K, 10, 0) -> осн. | E72: =VLOOKUP(B72, Расстояния!B:F, 5, 0) -> нет | H72: 46101.419 | I72: 46101.504 | J72: Баженов | L72: 1.1. | M72: =VLOOKUP(L72, Работы!A:B, 2, 0) -> Техническое обслуживание БС | N72: Техническое обслуживание БС | O72: 1 | P72: =IF(OR(L72="3.3.1.", L72="3.3.2.", L72="3.3.3.", L72="3.1.1.", L72="3.1.2.", L72="3.4.1.", L72="3.4.2."), 0, VLOOKUP(L72, Работы!$A$3:$D$184, 4, 0)) -> 4143 | T72: =IF(OR(L72="3.3.1.", L72="3.3.2.", L72="3.3.3."), VLOOKUP(L72, Работы!$A$3:$D$184, 4, 0), 0) -> 0 | U72: =IF(OR(L72="3.1.1."), VLOOKUP(L72, Работы!$A$3:$D$184, 4, 0), 0) -> 0 | V72: =IF(OR(L72="3.1.2."), VLOOKUP(L72, Работы!$A$3:$D$184, 4, 0), 0) -> 0 | Y72: =IF(OR(L72="3.2.1.", L72="3.2.2."), VLOOKUP(L72, Работы!$A$3:$D$184, 4, 0), 0) -> 0 | Z72: =IF(OR(L72="3.4.1.", L72="3.4.2."), VLOOKUP(L72, Работы!$A$3:$D$184, 4, 0), 0) -> 0 | AA72: =P72*O72+Q72*T72+R72*T72+S72*T72+U72+V72+W72*Y72+X72*Y72+Z72 -> 4143 | AE72: =AC72*AD72 -> 0 | AF72: =C72*Работы!$D$180 -> 107.62 | AG72: =AA72+AE72+AF72+AL72+AM72 -> 4250.62 | AJ72: =AG72-AA72*AI72 -> 4250.62 | AL72: =IF(OR(E72="да"), 4040, 0) -> 0 | AM72: =IF(OR(D72="доп."), AA72*0.1, 0) -> 0
A73: =ROW(A73)-10 -> 63 | B73: RO0413 | C73: 0 | D73: =VLOOKUP(B73, Расстояния!B:K, 10, 0) -> осн. | E73: =VLOOKUP(B73, Расстояния!B:F, 5, 0) -> нет | H73: 46101.419 | I73: 46101.504 | J73: Баженов | L73: 4.5 | M73: =VLOOKUP(L73, Работы!A:B, 2, 0) -> Стоимость проведения инвентаризации Объекта. | N73: Инвентаризация БС | O73: 1 | P73: =IF(OR(L73="3.3.1.", L73="3.3.2.", L73="3.3.3.", L73="3.1.1.", L73="3.1.2.", L73="3.4.1.", L73="3.4.2."), 0, VLOOKUP(L73, Работы!$A$3:$D$184, 4, 0)) -> 735 | T73: =IF(OR(L73="3.3.1.", L73="3.3.2.", L73="3.3.3."), VLOOKUP(L73, Работы!$A$3:$D$184, 4, 0), 0) -> 0 | U73: =IF(OR(L73="3.1.1."), VLOOKUP(L73, Работы!$A$3:$D$184, 4, 0), 0) -> 0 | V73: =IF(OR(L73="3.1.2."), VLOOKUP(L73, Работы!$A$3:$D$184, 4, 0), 0) -> 0 | Y73: =IF(OR(L73="3.2.1.", L73="3.2.2."), VLOOKUP(L73, Работы!$A$3:$D$184, 4, 0), 0) -> 0 | Z73: =IF(OR(L73="3.4.1.", L73="3.4.2."), VLOOKUP(L73, Работы!$A$3:$D$184, 4, 0), 0) -> 0 | AA73: =P73*O73+Q73*T73+R73*T73+S73*T73+U73+V73+W73*Y73+X73*Y73+Z73 -> 735 | AE73: =AC73*AD73 -> 0 | AF73: =C73*Работы!$D$180 -> 0 | AG73: =AA73+AE73+AF73+AL73+AM73 -> 735 | AJ73: =AG73-AA73*AI73 -> 735 | AL73: =IF(OR(E73="да"), 4040, 0) -> 0 | AM73: =IF(OR(D73="доп."), AA73*0.1, 0) -> 0
A74: =ROW(A74)-10 -> 64 | B74: RO0414 | C74: =VLOOKUP(B74, Расстояния!B:J, 9, 0) -> 7 | D74: =VLOOKUP(B74, Расстояния!B:K, 10, 0) -> осн. | E74: =VLOOKUP(B74, Расстояния!B:F, 5, 0) -> нет | F74: WO06715431 | G74: 46099.445 | H74: 46104.401 | I74: 46104.5 | J74: Баженов | L74: 4.2. | M74: =VLOOKUP(L74, Работы!A:B, 2, 0) -> Замена корзины РРЛ, внутренних блоков РРЛ, узла доступа, узла агрегации, включая перенос блоков, монтаж всех крепежных элементов, кабелей и интеграцию | N74: Работы с корзиной | O74: 1 | P74: =IF(OR(L74="3.3.1.", L74="3.3.2.", L74="3.3.3.", L74="3.1.1.", L74="3.1.2.", L74="3.4.1.", L74="3.4.2."), 0, VLOOKUP(L74, Работы!$A$3:$D$184, 4, 0)) -> 1238 | T74: =IF(OR(L74="3.3.1.", L74="3.3.2.", L74="3.3.3."), VLOOKUP(L74, Работы!$A$3:$D$184, 4, 0), 0) -> 0 | U74: =IF(OR(L74="3.1.1."), VLOOKUP(L74, Работы!$A$3:$D$184, 4, 0), 0) -> 0 | V74: =IF(OR(L74="3.1.2."), VLOOKUP(L74, Работы!$A$3:$D$184, 4, 0), 0) -> 0 | Y74: =IF(OR(L74="3.2.1.", L74="3.2.2."), VLOOKUP(L74, Работы!$A$3:$D$184, 4, 0), 0) -> 0 | Z74: =IF(OR(L74="3.4.1.", L74="3.4.2."), VLOOKUP(L74, Работы!$A$3:$D$184, 4, 0), 0) -> 0 | AA74: =P74*O74+Q74*T74+R74*T74+S74*T74+U74+V74+W74*Y74+X74*Y74+Z74 -> 1238 | AE74: =AC74*AD74 -> 0 | AF74: =C74*Работы!$D$180 -> 376.67 | AG74: =AA74+AE74+AF74+AL74+AM74 -> 1614.67 | AJ74: =AG74-AA74*AI74 -> 1614.67 | AL74: =IF(OR(E74="да"), 4040, 0) -> 0 | AM74: =IF(OR(D74="доп."), AA74*0.1, 0) -> 0
A75: =ROW(A75)-10 -> 65 | B75: RO0414 | C75: 0 | D75: =VLOOKUP(B75, Расстояния!B:K, 10, 0) -> осн. | E75: =VLOOKUP(B75, Расстояния!B:F, 5, 0) -> нет | H75: 46104.449 | I75: 46104.5 | J75: Баженов | L75: 1.1. | M75: =VLOOKUP(L75, Работы!A:B, 2, 0) -> Техническое обслуживание БС | N75: Техническое обслуживание БС | O75: 1 | P75: =IF(OR(L75="3.3.1.", L75="3.3.2.", L75="3.3.3.", L75="3.1.1.", L75="3.1.2.", L75="3.4.1.", L75="3.4.2."), 0, VLOOKUP(L75, Работы!$A$3:$D$184, 4, 0)) -> 4143 | T75: =IF(OR(L75="3.3.1.", L75="3.3.2.", L75="3.3.3."), VLOOKUP(L75, Работы!$A$3:$D$184, 4, 0), 0) -> 0 | U75: =IF(OR(L75="3.1.1."), VLOOKUP(L75, Работы!$A$3:$D$184, 4, 0), 0) -> 0 | V75: =IF(OR(L75="3.1.2."), VLOOKUP(L75, Работы!$A$3:$D$184, 4, 0), 0) -> 0 | Y75: =IF(OR(L75="3.2.1.", L75="3.2.2."), VLOOKUP(L75, Работы!$A$3:$D$184, 4, 0), 0) -> 0 | Z75: =IF(OR(L75="3.4.1.", L75="3.4.2."), VLOOKUP(L75, Работы!$A$3:$D$184, 4, 0), 0) -> 0 | AA75: =P75*O75+Q75*T75+R75*T75+S75*T75+U75+V75+W75*Y75+X75*Y75+Z75 -> 4143 | AE75: =AC75*AD75 -> 0 | AF75: =C75*Работы!$D$180 -> 0 | AG75: =AA75+AE75+AF75+AL75+AM75 -> 4143 | AJ75: =AG75-AA75*AI75 -> 4143 | AL75: =IF(OR(E75="да"), 4040, 0) -> 0 | AM75: =IF(OR(D75="доп."), AA75*0.1, 0) -> 0
A76: =ROW(A76)-10 -> 66 | B76: RO0414 | C76: 0 | D76: =VLOOKUP(B76, Расстояния!B:K, 10, 0) -> осн. | E76: =VLOOKUP(B76, Расстояния!B:F, 5, 0) -> нет | H76: 46104.449 | I76: 46104.5 | J76: Баженов | L76: 4.5 | M76: =VLOOKUP(L76, Работы!A:B, 2, 0) -> Стоимость проведения инвентаризации Объекта. | N76: Инвентаризация БС | O76: 1 | P76: =IF(OR(L76="3.3.1.", L76="3.3.2.", L76="3.3.3.", L76="3.1.1.", L76="3.1.2.", L76="3.4.1.", L76="3.4.2."), 0, VLOOKUP(L76, Работы!$A$3:$D$184, 4, 0)) -> 735 | T76: =IF(OR(L76="3.3.1.", L76="3.3.2.", L76="3.3.3."), VLOOKUP(L76, Работы!$A$3:$D$184, 4, 0), 0) -> 0 | U76: =IF(OR(L76="3.1.1."), VLOOKUP(L76, Работы!$A$3:$D$184, 4, 0), 0) -> 0 | V76: =IF(OR(L76="3.1.2."), VLOOKUP(L76, Работы!$A$3:$D$184, 4, 0), 0) -> 0 | Y76: =IF(OR(L76="3.2.1.", L76="3.2.2."), VLOOKUP(L76, Работы!$A$3:$D$184, 4, 0), 0) -> 0 | Z76: =IF(OR(L76="3.4.1.", L76="3.4.2."), VLOOKUP(L76, Работы!$A$3:$D$184, 4, 0), 0) -> 0 | AA76: =P76*O76+Q76*T76+R76*T76+S76*T76+U76+V76+W76*Y76+X76*Y76+Z76 -> 735 | AE76: =AC76*AD76 -> 0 | AF76: =C76*Работы!$D$180 -> 0 | AG76: =AA76+AE76+AF76+AL76+AM76 -> 735 | AJ76: =AG76-AA76*AI76 -> 735 | AL76: =IF(OR(E76="да"), 4040, 0) -> 0 | AM76: =IF(OR(D76="доп."), AA76*0.1, 0) -> 0
A77: =ROW(A77)-10 -> 67 | B77: RO0414 | C77: 5 | D77: =VLOOKUP(B77, Расстояния!B:K, 10, 0) -> осн. | E77: =VLOOKUP(B77, Расстояния!B:F, 5, 0) -> нет | F77: WO06713085 | G77: 46097.455 | H77: 46097.483 | I77: 46097.483 | J77: Католиков | L77: 3.4.1. | M77: =VLOOKUP(L77, Работы!A:B, 2, 0) -> Стоимость отменённого вызова на Аварийно-восстановительные работы, заявка по которым получена в рабочее время | N77: Отмена | P77: =IF(OR(L77="3.3.1.", L77="3.3.2.", L77="3.3.3.", L77="3.1.1.", L77="3.1.2.", L77="3.4.1.", L77="3.4.2."), 0, VLOOKUP(L77, Работы!$A$3:$D$184, 4, 0)) -> 0 | T77: =IF(OR(L77="3.3.1.", L77="3.3.2.", L77="3.3.3."), VLOOKUP(L77, Работы!$A$3:$D$184, 4, 0), 0) -> 0 | U77: =IF(OR(L77="3.1.1."), VLOOKUP(L77, Работы!$A$3:$D$184, 4, 0), 0) -> 0 | V77: =IF(OR(L77="3.1.2."), VLOOKUP(L77, Работы!$A$3:$D$184, 4, 0), 0) -> 0 | Y77: =IF(OR(L77="3.2.1.", L77="3.2.2."), VLOOKUP(L77, Работы!$A$3:$D$184, 4, 0), 0) -> 0 | Z77: =IF(OR(L77="3.4.1.", L77="3.4.2."), VLOOKUP(L77, Работы!$A$3:$D$184, 4, 0), 0) -> 922 | AA77: =P77*O77+Q77*T77+R77*T77+S77*T77+U77+V77+W77*Y77+X77*Y77+Z77 -> 922 | AE77: =AC77*AD77 -> 0 | AF77: =C77*Работы!$D$180 -> 269.05 | AG77: =AA77+AE77+AF77+AL77+AM77 -> 1191.05 | AJ77: =AG77-AA77*AI77 -> 1191.05 | AL77: =IF(OR(E77="да"), 4040, 0) -> 0 | AM77: =IF(OR(D77="доп."), AA77*0.1, 0) -> 0
A78: =ROW(A78)-10 -> 68 | B78: RO0415 | C78: =VLOOKUP(B78, Расстояния!B:J, 9, 0) -> 4 | D78: =VLOOKUP(B78, Расстояния!B:K, 10, 0) -> осн. | E78: =VLOOKUP(B78, Расстояния!B:F, 5, 0) -> нет | F78: WO06719226 | G78: 46104.429 | H78: 46104.474 | I78: 46104.509 | J78: Католиков | L78: 3.3.1. | M78: =VLOOKUP(L78, Работы!A:B, 2, 0) -> Стоимость Аварийно-восстановительных работ по обеспечению временного электроснабжения. (Ставка применяется с 1 часа выполнения Работ, для оплаты каждых не полных суток выполнения Работ) | N78: Генерация | P78: =IF(OR(L78="3.3.1.", L78="3.3.2.", L78="3.3.3.", L78="3.1.1.", L78="3.1.2.", L78="3.4.1.", L78="3.4.2."), 0, VLOOKUP(L78, Работы!$A$3:$D$184, 4, 0)) -> 0 | Q78: =ROUNDUP((I78-H78)*24, 0) -> 1 | T78: =IF(OR(L78="3.3.1.", L78="3.3.2.", L78="3.3.3."), VLOOKUP(L78, Работы!$A$3:$D$184, 4, 0), 0) -> 903 | U78: =IF(OR(L78="3.1.1."), VLOOKUP(L78, Работы!$A$3:$D$184, 4, 0), 0) -> 0 | V78: =IF(OR(L78="3.1.2."), VLOOKUP(L78, Работы!$A$3:$D$184, 4, 0), 0) -> 0 | Y78: =IF(OR(L78="3.2.1.", L78="3.2.2."), VLOOKUP(L78, Работы!$A$3:$D$184, 4, 0), 0) -> 0 | Z78: =IF(OR(L78="3.4.1.", L78="3.4.2."), VLOOKUP(L78, Работы!$A$3:$D$184, 4, 0), 0) -> 0 | AA78: =P78*O78+Q78*T78+R78*T78+S78*T78+U78+V78+W78*Y78+X78*Y78+Z78 -> 903 | AE78: =AC78*AD78 -> 0 | AF78: =C78*Работы!$D$180 -> 215.24 | AG78: =AA78+AE78+AF78+AL78+AM78 -> 1118.24 | AJ78: =AG78-AA78*AI78 -> 1118.24 | AL78: =IF(OR(E78="да"), 4040, 0) -> 0 | AM78: =IF(OR(D78="доп."), AA78*0.1, 0) -> 0
A79: =ROW(A79)-10 -> 69 | B79: RO0421 | C79: =VLOOKUP(B79, Расстояния!B:J, 9, 0) -> 6 | D79: =VLOOKUP(B79, Расстояния!B:K, 10, 0) -> осн. | E79: =VLOOKUP(B79, Расстояния!B:F, 5, 0) -> нет | H79: 46109.621 | I79: 46109.738 | J79: Баженов | L79: 1.1. | M79: =VLOOKUP(L79, Работы!A:B, 2, 0) -> Техническое обслуживание БС | N79: Техническое обслуживание БС | O79: 1 | P79: =IF(OR(L79="3.3.1.", L79="3.3.2.", L79="3.3.3.", L79="3.1.1.", L79="3.1.2.", L79="3.4.1.", L79="3.4.2."), 0, VLOOKUP(L79, Работы!$A$3:$D$184, 4, 0)) -> 4143 | T79: =IF(OR(L79="3.3.1.", L79="3.3.2.", L79="3.3.3."), VLOOKUP(L79, Работы!$A$3:$D$184, 4, 0), 0) -> 0 | U79: =IF(OR(L79="3.1.1."), VLOOKUP(L79, Работы!$A$3:$D$184, 4, 0), 0) -> 0 | V79: =IF(OR(L79="3.1.2."), VLOOKUP(L79, Работы!$A$3:$D$184, 4, 0), 0) -> 0 | Y79: =IF(OR(L79="3.2.1.", L79="3.2.2."), VLOOKUP(L79, Работы!$A$3:$D$184, 4, 0), 0) -> 0 | Z79: =IF(OR(L79="3.4.1.", L79="3.4.2."), VLOOKUP(L79, Работы!$A$3:$D$184, 4, 0), 0) -> 0 | AA79: =P79*O79+Q79*T79+R79*T79+S79*T79+U79+V79+W79*Y79+X79*Y79+Z79 -> 4143 | AE79: =AC79*AD79 -> 0 | AF79: =C79*Работы!$D$180 -> 322.86 | AG79: =AA79+AE79+AF79+AL79+AM79 -> 4465.86 | AJ79: =AG79-AA79*AI79 -> 4465.86 | AL79: =IF(OR(E79="да"), 4040, 0) -> 0 | AM79: =IF(OR(D79="доп."), AA79*0.1, 0) -> 0
A80: =ROW(A80)-10 -> 70 | B80: RO0421 | C80: 0 | D80: =VLOOKUP(B80, Расстояния!B:K, 10, 0) -> осн. | E80: =VLOOKUP(B80, Расстояния!B:F, 5, 0) -> нет | F80: WO06724496 | G80: 46108.389 | H80: 46109.621 | I80: 46109.738 | J80: Баженов | L80: 2.2. | M80: =VLOOKUP(L80, Работы!A:B, 2, 0) -> Диагностика и замена модуля передатчиков БС на АМС, включая монтаж всех крепёжных элементов и кабелей, переключение джамперов и созданием логических объектов на стороне БС | N80: Чистка передатчика | O80: 1 | P80: =IF(OR(L80="3.3.1.", L80="3.3.2.", L80="3.3.3.", L80="3.1.1.", L80="3.1.2.", L80="3.4.1.", L80="3.4.2."), 0, VLOOKUP(L80, Работы!$A$3:$D$184, 4, 0)) -> 2830 | T80: =IF(OR(L80="3.3.1.", L80="3.3.2.", L80="3.3.3."), VLOOKUP(L80, Работы!$A$3:$D$184, 4, 0), 0) -> 0 | U80: =IF(OR(L80="3.1.1."), VLOOKUP(L80, Работы!$A$3:$D$184, 4, 0), 0) -> 0 | V80: =IF(OR(L80="3.1.2."), VLOOKUP(L80, Работы!$A$3:$D$184, 4, 0), 0) -> 0 | Y80: =IF(OR(L80="3.2.1.", L80="3.2.2."), VLOOKUP(L80, Работы!$A$3:$D$184, 4, 0), 0) -> 0 | Z80: =IF(OR(L80="3.4.1.", L80="3.4.2."), VLOOKUP(L80, Работы!$A$3:$D$184, 4, 0), 0) -> 0 | AA80: =P80*O80+Q80*T80+R80*T80+S80*T80+U80+V80+W80*Y80+X80*Y80+Z80 -> 2830 | AE80: =AC80*AD80 -> 0 | AF80: =C80*Работы!$D$180 -> 0 | AG80: =AA80+AE80+AF80+AL80+AM80 -> 2830 | AJ80: =AG80-AA80*AI80 -> 2830 | AL80: =IF(OR(E80="да"), 4040, 0) -> 0 | AM80: =IF(OR(D80="доп."), AA80*0.1, 0) -> 0
A81: =ROW(A81)-10 -> 71 | B81: RO0436 | C81: =VLOOKUP(B81, Расстояния!B:J, 9, 0) -> 3 | D81: =VLOOKUP(B81, Расстояния!B:K, 10, 0) -> осн. | E81: =VLOOKUP(B81, Расстояния!B:F, 5, 0) -> нет | F81: WO06716466 | G81: 46100.451 | H81: 46100.453 | I81: 46100.462 | J81: Баженов | L81: 3.1.1. | M81: =VLOOKUP(L81, Работы!A:B, 2, 0) -> Стоимость аварийно-восстановительных работ, заявка по которым получена в течение рабочего времени | N81: Проверка БС | P81: =IF(OR(L81="3.3.1.", L81="3.3.2.", L81="3.3.3.", L81="3.1.1.", L81="3.1.2.", L81="3.4.1.", L81="3.4.2."), 0, VLOOKUP(L81, Работы!$A$3:$D$184, 4, 0)) -> 0 | T81: =IF(OR(L81="3.3.1.", L81="3.3.2.", L81="3.3.3."), VLOOKUP(L81, Работы!$A$3:$D$184, 4, 0), 0) -> 0 | U81: =IF(OR(L81="3.1.1."), VLOOKUP(L81, Работы!$A$3:$D$184, 4, 0), 0) -> 3956 | V81: =IF(OR(L81="3.1.2."), VLOOKUP(L81, Работы!$A$3:$D$184, 4, 0), 0) -> 0 | Y81: =IF(OR(L81="3.2.1.", L81="3.2.2."), VLOOKUP(L81, Работы!$A$3:$D$184, 4, 0), 0) -> 0 | Z81: =IF(OR(L81="3.4.1.", L81="3.4.2."), VLOOKUP(L81, Работы!$A$3:$D$184, 4, 0), 0) -> 0 | AA81: =P81*O81+Q81*T81+R81*T81+S81*T81+U81+V81+W81*Y81+X81*Y81+Z81 -> 3956 | AE81: =AC81*AD81 -> 0 | AF81: =C81*Работы!$D$180 -> 161.43 | AG81: =AA81+AE81+AF81+AL81+AM81 -> 4117.43 | AJ81: =AG81-AA81*AI81 -> 4117.43 | AL81: =IF(OR(E81="да"), 4040, 0) -> 0 | AM81: =IF(OR(D81="доп."), AA81*0.1, 0) -> 0
A82: =ROW(A82)-10 -> 72 | B82: RO0436 | C82: =VLOOKUP(B82, Расстояния!B:J, 9, 0) -> 3 | D82: =VLOOKUP(B82, Расстояния!B:K, 10, 0) -> осн. | E82: =VLOOKUP(B82, Расстояния!B:F, 5, 0) -> нет | H82: 46107.446 | I82: 46107.502 | J82: Баженов | L82: 1.1. | M82: =VLOOKUP(L82, Работы!A:B, 2, 0) -> Техническое обслуживание БС | N82: Техническое обслуживание БС | O82: 1 | P82: =IF(OR(L82="3.3.1.", L82="3.3.2.", L82="3.3.3.", L82="3.1.1.", L82="3.1.2.", L82="3.4.1.", L82="3.4.2."), 0, VLOOKUP(L82, Работы!$A$3:$D$184, 4, 0)) -> 4143 | T82: =IF(OR(L82="3.3.1.", L82="3.3.2.", L82="3.3.3."), VLOOKUP(L82, Работы!$A$3:$D$184, 4, 0), 0) -> 0 | U82: =IF(OR(L82="3.1.1."), VLOOKUP(L82, Работы!$A$3:$D$184, 4, 0), 0) -> 0 | V82: =IF(OR(L82="3.1.2."), VLOOKUP(L82, Работы!$A$3:$D$184, 4, 0), 0) -> 0 | Y82: =IF(OR(L82="3.2.1.", L82="3.2.2."), VLOOKUP(L82, Работы!$A$3:$D$184, 4, 0), 0) -> 0 | Z82: =IF(OR(L82="3.4.1.", L82="3.4.2."), VLOOKUP(L82, Работы!$A$3:$D$184, 4, 0), 0) -> 0 | AA82: =P82*O82+Q82*T82+R82*T82+S82*T82+U82+V82+W82*Y82+X82*Y82+Z82 -> 4143 | AE82: =AC82*AD82 -> 0 | AF82: =C82*Работы!$D$180 -> 161.43 | AG82: =AA82+AE82+AF82+AL82+AM82 -> 4304.43 | AJ82: =AG82-AA82*AI82 -> 4304.43 | AL82: =IF(OR(E82="да"), 4040, 0) -> 0 | AM82: =IF(OR(D82="доп."), AA82*0.1, 0) -> 0
A83: =ROW(A83)-10 -> 73 | B83: RO0436 | C83: =VLOOKUP(B83, Расстояния!B:J, 9, 0) -> 3 | D83: =VLOOKUP(B83, Расстояния!B:K, 10, 0) -> осн. | E83: =VLOOKUP(B83, Расстояния!B:F, 5, 0) -> нет | F83: WO06724848 | G83: 46108.504 | H83: 46108.538 | I83: 46108.585 | J83: Баженов | L83: 5.17. | M83: =VLOOKUP(L83, Работы!A:B, 2, 0) -> Настройка, прописка ИБП, включая подключение и тестирование внешних аварий | N83: Настройка СП | O83: 1 | P83: =IF(OR(L83="3.3.1.", L83="3.3.2.", L83="3.3.3.", L83="3.1.1.", L83="3.1.2.", L83="3.4.1.", L83="3.4.2."), 0, VLOOKUP(L83, Работы!$A$3:$D$184, 4, 0)) -> 735 | T83: =IF(OR(L83="3.3.1.", L83="3.3.2.", L83="3.3.3."), VLOOKUP(L83, Работы!$A$3:$D$184, 4, 0), 0) -> 0 | U83: =IF(OR(L83="3.1.1."), VLOOKUP(L83, Работы!$A$3:$D$184, 4, 0), 0) -> 0 | V83: =IF(OR(L83="3.1.2."), VLOOKUP(L83, Работы!$A$3:$D$184, 4, 0), 0) -> 0 | Y83: =IF(OR(L83="3.2.1.", L83="3.2.2."), VLOOKUP(L83, Работы!$A$3:$D$184, 4, 0), 0) -> 0 | Z83: =IF(OR(L83="3.4.1.", L83="3.4.2."), VLOOKUP(L83, Работы!$A$3:$D$184, 4, 0), 0) -> 0 | AA83: =P83*O83+Q83*T83+R83*T83+S83*T83+U83+V83+W83*Y83+X83*Y83+Z83 -> 735 | AE83: =AC83*AD83 -> 0 | AF83: =C83*Работы!$D$180 -> 161.43 | AG83: =AA83+AE83+AF83+AL83+AM83 -> 896.43 | AJ83: =AG83-AA83*AI83 -> 896.43 | AL83: =IF(OR(E83="да"), 4040, 0) -> 0 | AM83: =IF(OR(D83="доп."), AA83*0.1, 0) -> 0
A84: =ROW(A84)-10 -> 74 | B84: RO0442 | C84: 60 | D84: =VLOOKUP(B84, Расстояния!B:K, 10, 0) -> осн. | E84: =VLOOKUP(B84, Расстояния!B:F, 5, 0) -> нет | F84: WO06726281 | G84: 46110.931 | H84: 46111.001 | I84: 46111.001 | J84: Попов | L84: 3.4.2. | M84: =VLOOKUP(L84, Работы!A:B, 2, 0) -> Стоимость отменённого вызова на Аварийно-восстановительные работы, заявка по которым получена во внерабочее время | N84: Отмена | P84: =IF(OR(L84="3.3.1.", L84="3.3.2.", L84="3.3.3.", L84="3.1.1.", L84="3.1.2.", L84="3.4.1.", L84="3.4.2."), 0, VLOOKUP(L84, Работы!$A$3:$D$184, 4, 0)) -> 0 | T84: =IF(OR(L84="3.3.1.", L84="3.3.2.", L84="3.3.3."), VLOOKUP(L84, Работы!$A$3:$D$184, 4, 0), 0) -> 0 | U84: =IF(OR(L84="3.1.1."), VLOOKUP(L84, Работы!$A$3:$D$184, 4, 0), 0) -> 0 | V84: =IF(OR(L84="3.1.2."), VLOOKUP(L84, Работы!$A$3:$D$184, 4, 0), 0) -> 0 | Y84: =IF(OR(L84="3.2.1.", L84="3.2.2."), VLOOKUP(L84, Работы!$A$3:$D$184, 4, 0), 0) -> 0 | Z84: =IF(OR(L84="3.4.1.", L84="3.4.2."), VLOOKUP(L84, Работы!$A$3:$D$184, 4, 0), 0) -> 1731 | AA84: =P84*O84+Q84*T84+R84*T84+S84*T84+U84+V84+W84*Y84+X84*Y84+Z84 -> 1731 | AE84: =AC84*AD84 -> 0 | AF84: =C84*Работы!$D$180 -> 3228.6 | AG84: =AA84+AE84+AF84+AL84+AM84 -> 4959.6 | AJ84: =AG84-AA84*AI84 -> 4959.6 | AL84: =IF(OR(E84="да"), 4040, 0) -> 0 | AM84: =IF(OR(D84="доп."), AA84*0.1, 0) -> 0
A85: =ROW(A85)-10 -> 75 | B85: RO0468 | C85: =VLOOKUP(B85, Расстояния!B:J, 9, 0) -> 63 | D85: =VLOOKUP(B85, Расстояния!B:K, 10, 0) -> осн. | E85: =VLOOKUP(B85, Расстояния!B:F, 5, 0) -> нет | F85: WO06715857 | G85: 46099.681 | H85: 46103.556 | I85: 46103.63 | J85: Баженов | L85: 5.3. | M85: =VLOOKUP(L85, Работы!A:B, 2, 0) -> Осмотр и тестирование аккумуляторов источников бесперебойного питания (ИБП) по упрощенной методике (разряд на штатную нагрузку ИБП до 2 (двух) часов с измерением их параметров) | N85: Видеотест АКБ | O85: 1 | P85: =IF(OR(L85="3.3.1.", L85="3.3.2.", L85="3.3.3.", L85="3.1.1.", L85="3.1.2.", L85="3.4.1.", L85="3.4.2."), 0, VLOOKUP(L85, Работы!$A$3:$D$184, 4, 0)) -> 1778 | T85: =IF(OR(L85="3.3.1.", L85="3.3.2.", L85="3.3.3."), VLOOKUP(L85, Работы!$A$3:$D$184, 4, 0), 0) -> 0 | U85: =IF(OR(L85="3.1.1."), VLOOKUP(L85, Работы!$A$3:$D$184, 4, 0), 0) -> 0 | V85: =IF(OR(L85="3.1.2."), VLOOKUP(L85, Работы!$A$3:$D$184, 4, 0), 0) -> 0 | Y85: =IF(OR(L85="3.2.1.", L85="3.2.2."), VLOOKUP(L85, Работы!$A$3:$D$184, 4, 0), 0) -> 0 | Z85: =IF(OR(L85="3.4.1.", L85="3.4.2."), VLOOKUP(L85, Работы!$A$3:$D$184, 4, 0), 0) -> 0 | AA85: =P85*O85+Q85*T85+R85*T85+S85*T85+U85+V85+W85*Y85+X85*Y85+Z85 -> 1778 | AE85: =AC85*AD85 -> 0 | AF85: =C85*Работы!$D$180 -> 3390.03 | AG85: =AA85+AE85+AF85+AL85+AM85 -> 5168.03 | AJ85: =AG85-AA85*AI85 -> 5168.03 | AL85: =IF(OR(E85="да"), 4040, 0) -> 0 | AM85: =IF(OR(D85="доп."), AA85*0.1, 0) -> 0
A86: =ROW(A86)-10 -> 76 | B86: RO0471 | C86: =VLOOKUP(B86, Расстояния!B:J, 9, 0) -> 53 | D86: =VLOOKUP(B86, Расстояния!B:K, 10, 0) -> осн. | E86: =VLOOKUP(B86, Расстояния!B:F, 5, 0) -> нет | F86: WO06719222 | G86: 46104.428 | H86: 46105.835 | I86: 46105.866 | J86: Голиков | L86: 6.13. | M86: =VLOOKUP(L86, Работы!A:B, 2, 0) -> Вскрытие либо замена замка двери контейнера БС и климат. шкафа, калитки ограждения, люка АМС | N86: Ремонт магнита двери и контейнера | O86: 1 | P86: =IF(OR(L86="3.3.1.", L86="3.3.2.", L86="3.3.3.", L86="3.1.1.", L86="3.1.2.", L86="3.4.1.", L86="3.4.2."), 0, VLOOKUP(L86, Работы!$A$3:$D$184, 4, 0)) -> 1471 | T86: =IF(OR(L86="3.3.1.", L86="3.3.2.", L86="3.3.3."), VLOOKUP(L86, Работы!$A$3:$D$184, 4, 0), 0) -> 0 | U86: =IF(OR(L86="3.1.1."), VLOOKUP(L86, Работы!$A$3:$D$184, 4, 0), 0) -> 0 | V86: =IF(OR(L86="3.1.2."), VLOOKUP(L86, Работы!$A$3:$D$184, 4, 0), 0) -> 0 | Y86: =IF(OR(L86="3.2.1.", L86="3.2.2."), VLOOKUP(L86, Работы!$A$3:$D$184, 4, 0), 0) -> 0 | Z86: =IF(OR(L86="3.4.1.", L86="3.4.2."), VLOOKUP(L86, Работы!$A$3:$D$184, 4, 0), 0) -> 0 | AA86: =P86*O86+Q86*T86+R86*T86+S86*T86+U86+V86+W86*Y86+X86*Y86+Z86 -> 1471 | AE86: =AC86*AD86 -> 0 | AF86: =C86*Работы!$D$180 -> 2851.93 | AG86: =AA86+AE86+AF86+AL86+AM86 -> 4322.93 | AJ86: =AG86-AA86*AI86 -> 4322.93 | AL86: =IF(OR(E86="да"), 4040, 0) -> 0 | AM86: =IF(OR(D86="доп."), AA86*0.1, 0) -> 0
A87: =ROW(A87)-10 -> 77 | B87: RO0474 | C87: =VLOOKUP(B87, Расстояния!B:J, 9, 0) -> 65 | D87: =VLOOKUP(B87, Расстояния!B:K, 10, 0) -> осн. | E87: =VLOOKUP(B87, Расстояния!B:F, 5, 0) -> нет | F87: WO06719511 | G87: 46104.526 | H87: 46104.606 | I87: 46104.715 | J87: Кривинец | L87: 3.3.1. | M87: =VLOOKUP(L87, Работы!A:B, 2, 0) -> Стоимость Аварийно-восстановительных работ по обеспечению временного электроснабжения. (Ставка применяется с 1 часа выполнения Работ, для оплаты каждых не полных суток выполнения Работ) | N87: Генерация | P87: =IF(OR(L87="3.3.1.", L87="3.3.2.", L87="3.3.3.", L87="3.1.1.", L87="3.1.2.", L87="3.4.1.", L87="3.4.2."), 0, VLOOKUP(L87, Работы!$A$3:$D$184, 4, 0)) -> 0 | Q87: =ROUNDUP((I87-H87)*24, 0) -> 3 | T87: =IF(OR(L87="3.3.1.", L87="3.3.2.", L87="3.3.3."), VLOOKUP(L87, Работы!$A$3:$D$184, 4, 0), 0) -> 903 | U87: =IF(OR(L87="3.1.1."), VLOOKUP(L87, Работы!$A$3:$D$184, 4, 0), 0) -> 0 | V87: =IF(OR(L87="3.1.2."), VLOOKUP(L87, Работы!$A$3:$D$184, 4, 0), 0) -> 0 | Y87: =IF(OR(L87="3.2.1.", L87="3.2.2."), VLOOKUP(L87, Работы!$A$3:$D$184, 4, 0), 0) -> 0 | Z87: =IF(OR(L87="3.4.1.", L87="3.4.2."), VLOOKUP(L87, Работы!$A$3:$D$184, 4, 0), 0) -> 0 | AA87: =P87*O87+Q87*T87+R87*T87+S87*T87+U87+V87+W87*Y87+X87*Y87+Z87 -> 2709 | AE87: =AC87*AD87 -> 0 | AF87: =C87*Работы!$D$180 -> 3497.65 | AG87: =AA87+AE87+AF87+AL87+AM87 -> 6206.65 | AJ87: =AG87-AA87*AI87 -> 6206.65 | AL87: =IF(OR(E87="да"), 4040, 0) -> 0 | AM87: =IF(OR(D87="доп."), AA87*0.1, 0) -> 0
A88: =ROW(A88)-10 -> 78 | B88: RO0480 | C88: =VLOOKUP(B88, Расстояния!B:J, 9, 0) -> 27 | D88: =VLOOKUP(B88, Расстояния!B:K, 10, 0) -> осн. | E88: =VLOOKUP(B88, Расстояния!B:F, 5, 0) -> нет | F88: WO06720289 | G88: 46105.34 | H88: 46105.401 | I88: 46105.401 | J88: Католиков | L88: 3.4.1. | M88: =VLOOKUP(L88, Работы!A:B, 2, 0) -> Стоимость отменённого вызова на Аварийно-восстановительные работы, заявка по которым получена в рабочее время | N88: Отмена | P88: =IF(OR(L88="3.3.1.", L88="3.3.2.", L88="3.3.3.", L88="3.1.1.", L88="3.1.2.", L88="3.4.1.", L88="3.4.2."), 0, VLOOKUP(L88, Работы!$A$3:$D$184, 4, 0)) -> 0 | T88: =IF(OR(L88="3.3.1.", L88="3.3.2.", L88="3.3.3."), VLOOKUP(L88, Работы!$A$3:$D$184, 4, 0), 0) -> 0 | U88: =IF(OR(L88="3.1.1."), VLOOKUP(L88, Работы!$A$3:$D$184, 4, 0), 0) -> 0 | V88: =IF(OR(L88="3.1.2."), VLOOKUP(L88, Работы!$A$3:$D$184, 4, 0), 0) -> 0 | Y88: =IF(OR(L88="3.2.1.", L88="3.2.2."), VLOOKUP(L88, Работы!$A$3:$D$184, 4, 0), 0) -> 0 | Z88: =IF(OR(L88="3.4.1.", L88="3.4.2."), VLOOKUP(L88, Работы!$A$3:$D$184, 4, 0), 0) -> 922 | AA88: =P88*O88+Q88*T88+R88*T88+S88*T88+U88+V88+W88*Y88+X88*Y88+Z88 -> 922 | AE88: =AC88*AD88 -> 0 | AF88: =C88*Работы!$D$180 -> 1452.87 | AG88: =AA88+AE88+AF88+AL88+AM88 -> 2374.87 | AJ88: =AG88-AA88*AI88 -> 2374.87 | AL88: =IF(OR(E88="да"), 4040, 0) -> 0 | AM88: =IF(OR(D88="доп."), AA88*0.1, 0) -> 0
A89: =ROW(A89)-10 -> 79 | B89: RO0481 | C89: =VLOOKUP(B89, Расстояния!B:J, 9, 0) -> 26 | D89: =VLOOKUP(B89, Расстояния!B:K, 10, 0) -> осн. | E89: =VLOOKUP(B89, Расстояния!B:F, 5, 0) -> нет | F89: WO06718732 | G89: 46103.648 | H89: 46103.703 | I89: 46103.719 | J89: Баженов | L89: 3.1.2. | M89: =VLOOKUP(L89, Работы!A:B, 2, 0) -> Стоимость аварийно-восстановительных работ, заявка по которым получена во внерабочее время | N89: DOOR/Проверка БС | P89: =IF(OR(L89="3.3.1.", L89="3.3.2.", L89="3.3.3.", L89="3.1.1.", L89="3.1.2.", L89="3.4.1.", L89="3.4.2."), 0, VLOOKUP(L89, Работы!$A$3:$D$184, 4, 0)) -> 0 | T89: =IF(OR(L89="3.3.1.", L89="3.3.2.", L89="3.3.3."), VLOOKUP(L89, Работы!$A$3:$D$184, 4, 0), 0) -> 0 | U89: =IF(OR(L89="3.1.1."), VLOOKUP(L89, Работы!$A$3:$D$184, 4, 0), 0) -> 0 | V89: =IF(OR(L89="3.1.2."), VLOOKUP(L89, Работы!$A$3:$D$184, 4, 0), 0) -> 7187 | Y89: =IF(OR(L89="3.2.1.", L89="3.2.2."), VLOOKUP(L89, Работы!$A$3:$D$184, 4, 0), 0) -> 0 | Z89: =IF(OR(L89="3.4.1.", L89="3.4.2."), VLOOKUP(L89, Работы!$A$3:$D$184, 4, 0), 0) -> 0 | AA89: =P89*O89+Q89*T89+R89*T89+S89*T89+U89+V89+W89*Y89+X89*Y89+Z89 -> 7187 | AE89: =AC89*AD89 -> 0 | AF89: =C89*Работы!$D$180 -> 1399.06 | AG89: =AA89+AE89+AF89+AL89+AM89 -> 8586.06 | AJ89: =AG89-AA89*AI89 -> 8586.06 | AL89: =IF(OR(E89="да"), 4040, 0) -> 0 | AM89: =IF(OR(D89="доп."), AA89*0.1, 0) -> 0
A90: =ROW(A90)-10 -> 80 | B90: RO0481 | C90: =VLOOKUP(B90, Расстояния!B:J, 9, 0) -> 26 | D90: =VLOOKUP(B90, Расстояния!B:K, 10, 0) -> осн. | E90: =VLOOKUP(B90, Расстояния!B:F, 5, 0) -> нет | F90: WO06722588 | G90: 46106.639 | H90: 46106.69 | I90: 46106.69 | J90: Католиков | L90: 3.4.1. | M90: =VLOOKUP(L90, Работы!A:B, 2, 0) -> Стоимость отменённого вызова на Аварийно-восстановительные работы, заявка по которым получена в рабочее время | N90: Отмена | P90: =IF(OR(L90="3.3.1.", L90="3.3.2.", L90="3.3.3.", L90="3.1.1.", L90="3.1.2.", L90="3.4.1.", L90="3.4.2."), 0, VLOOKUP(L90, Работы!$A$3:$D$184, 4, 0)) -> 0 | T90: =IF(OR(L90="3.3.1.", L90="3.3.2.", L90="3.3.3."), VLOOKUP(L90, Работы!$A$3:$D$184, 4, 0), 0) -> 0 | U90: =IF(OR(L90="3.1.1."), VLOOKUP(L90, Работы!$A$3:$D$184, 4, 0), 0) -> 0 | V90: =IF(OR(L90="3.1.2."), VLOOKUP(L90, Работы!$A$3:$D$184, 4, 0), 0) -> 0 | Y90: =IF(OR(L90="3.2.1.", L90="3.2.2."), VLOOKUP(L90, Работы!$A$3:$D$184, 4, 0), 0) -> 0 | Z90: =IF(OR(L90="3.4.1.", L90="3.4.2."), VLOOKUP(L90, Работы!$A$3:$D$184, 4, 0), 0) -> 922 | AA90: =P90*O90+Q90*T90+R90*T90+S90*T90+U90+V90+W90*Y90+X90*Y90+Z90 -> 922 | AE90: =AC90*AD90 -> 0 | AF90: =C90*Работы!$D$180 -> 1399.06 | AG90: =AA90+AE90+AF90+AL90+AM90 -> 2321.06 | AJ90: =AG90-AA90*AI90 -> 2321.06 | AL90: =IF(OR(E90="да"), 4040, 0) -> 0 | AM90: =IF(OR(D90="доп."), AA90*0.1, 0) -> 0
A91: =ROW(A91)-10 -> 81 | B91: RO0483 | C91: 0 | D91: =VLOOKUP(B91, Расстояния!B:K, 10, 0) -> осн. | E91: =VLOOKUP(B91, Расстояния!B:F, 5, 0) -> нет | F91: WO06713156 | G91: 46097.484 | H91: 46096.683 | I91: 46096.753 | J91: Баженов | L91: 10.3. | M91: =VLOOKUP(L91, Работы!A:B, 2, 0) -> Иные работы/услуги в отношении одного Объекта по одному обращению Заказчика в течение рабочего времени*****, независимо от количества представителей Подрядчика, участвующих в выполнении таких Работ на одном Объекте | N91: Монтаж проводов для АКБ*2 | O91: 1 | P91: =IF(OR(L91="3.3.1.", L91="3.3.2.", L91="3.3.3.", L91="3.1.1.", L91="3.1.2.", L91="3.4.1.", L91="3.4.2."), 0, VLOOKUP(L91, Работы!$A$3:$D$184, 4, 0)) -> 735 | T91: =IF(OR(L91="3.3.1.", L91="3.3.2.", L91="3.3.3."), VLOOKUP(L91, Работы!$A$3:$D$184, 4, 0), 0) -> 0 | U91: =IF(OR(L91="3.1.1."), VLOOKUP(L91, Работы!$A$3:$D$184, 4, 0), 0) -> 0 | V91: =IF(OR(L91="3.1.2."), VLOOKUP(L91, Работы!$A$3:$D$184, 4, 0), 0) -> 0 | Y91: =IF(OR(L91="3.2.1.", L91="3.2.2."), VLOOKUP(L91, Работы!$A$3:$D$184, 4, 0), 0) -> 0 | Z91: =IF(OR(L91="3.4.1.", L91="3.4.2."), VLOOKUP(L91, Работы!$A$3:$D$184, 4, 0), 0) -> 0 | AA91: =P91*O91+Q91*T91+R91*T91+S91*T91+U91+V91+W91*Y91+X91*Y91+Z91 -> 735 | AE91: =AC91*AD91 -> 0 | AF91: =C91*Работы!$D$180 -> 0 | AG91: =AA91+AE91+AF91+AL91+AM91 -> 735 | AJ91: =AG91-AA91*AI91 -> 735 | AL91: =IF(OR(E91="да"), 4040, 0) -> 0 | AM91: =IF(OR(D91="доп."), AA91*0.1, 0) -> 0
A92: =ROW(A92)-10 -> 82 | B92: RO0483 | C92: 0 | D92: =VLOOKUP(B92, Расстояния!B:K, 10, 0) -> осн. | E92: =VLOOKUP(B92, Расстояния!B:F, 5, 0) -> нет | F92: WO06713156 | G92: 46097.484 | H92: 46096.683 | I92: 46096.753 | J92: Баженов | T92: =IF(OR(L92="3.3.1.", L92="3.3.2.", L92="3.3.3."), VLOOKUP(L92, Работы!$A$3:$D$184, 4, 0), 0) -> 0 | U92: =IF(OR(L92="3.1.1."), VLOOKUP(L92, Работы!$A$3:$D$184, 4, 0), 0) -> 0 | V92: =IF(OR(L92="3.1.2."), VLOOKUP(L92, Работы!$A$3:$D$184, 4, 0), 0) -> 0 | Y92: =IF(OR(L92="3.2.1.", L92="3.2.2."), VLOOKUP(L92, Работы!$A$3:$D$184, 4, 0), 0) -> 0 | Z92: =IF(OR(L92="3.4.1.", L92="3.4.2."), VLOOKUP(L92, Работы!$A$3:$D$184, 4, 0), 0) -> 0 | AA92: =P92*O92+Q92*T92+R92*T92+S92*T92+U92+V92+W92*Y92+X92*Y92+Z92 -> 0 | AB92: провод 1*50 2метра + 2шт наконечника | AC92: 1 | AD92: 2100 | AE92: =AC92*AD92 -> 2100 | AF92: =C92*Работы!$D$180 -> 0 | AG92: =AA92+AE92+AF92+AL92+AM92 -> 2100 | AJ92: =AG92-AA92*AI92 -> 2100 | AL92: =IF(OR(E92="да"), 4040, 0) -> 0 | AM92: =IF(OR(D92="доп."), AA92*0.1, 0) -> 0
A93: =ROW(A93)-10 -> 83 | B93: RO0483 | C93: 0 | D93: =VLOOKUP(B93, Расстояния!B:K, 10, 0) -> осн. | E93: =VLOOKUP(B93, Расстояния!B:F, 5, 0) -> нет | F93: WO06713156 | G93: 46097.484 | H93: 46096.683 | I93: 46096.753 | J93: Баженов | L93: 6.18. | M93: =VLOOKUP(L93, Работы!A:B, 2, 0) -> Замена антивандальной защиты (работы, с учетом стоимости расходных материалов, без учета стоимости металла) | N93: Монтаж защиты АКБ | O93: 0.033 | P93: =IF(OR(L93="3.3.1.", L93="3.3.2.", L93="3.3.3.", L93="3.1.1.", L93="3.1.2.", L93="3.4.1.", L93="3.4.2."), 0, VLOOKUP(L93, Работы!$A$3:$D$184, 4, 0)) -> 76316 | T93: =IF(OR(L93="3.3.1.", L93="3.3.2.", L93="3.3.3."), VLOOKUP(L93, Работы!$A$3:$D$184, 4, 0), 0) -> 0 | U93: =IF(OR(L93="3.1.1."), VLOOKUP(L93, Работы!$A$3:$D$184, 4, 0), 0) -> 0 | V93: =IF(OR(L93="3.1.2."), VLOOKUP(L93, Работы!$A$3:$D$184, 4, 0), 0) -> 0 | Y93: =IF(OR(L93="3.2.1.", L93="3.2.2."), VLOOKUP(L93, Работы!$A$3:$D$184, 4, 0), 0) -> 0 | Z93: =IF(OR(L93="3.4.1.", L93="3.4.2."), VLOOKUP(L93, Работы!$A$3:$D$184, 4, 0), 0) -> 0 | AA93: =P93*O93+Q93*T93+R93*T93+S93*T93+U93+V93+W93*Y93+X93*Y93+Z93 -> 2518.428 | AE93: =AC93*AD93 -> 0 | AF93: =C93*Работы!$D$180 -> 0 | AG93: =AA93+AE93+AF93+AL93+AM93 -> 2518.428 | AJ93: =AG93-AA93*AI93 -> 2518.428 | AL93: =IF(OR(E93="да"), 4040, 0) -> 0 | AM93: =IF(OR(D93="доп."), AA93*0.1, 0) -> 0
A94: =ROW(A94)-10 -> 84 | B94: RO0483 | C94: 0 | D94: =VLOOKUP(B94, Расстояния!B:K, 10, 0) -> осн. | E94: =VLOOKUP(B94, Расстояния!B:F, 5, 0) -> нет | F94: WO06713156 | G94: 46097.484 | H94: 46096.683 | I94: 46096.753 | J94: Баженов | L94: 11.6. | M94: =VLOOKUP(L94, Работы!A:B, 2, 0) -> Антивандальная защита (без учета стоимости расходных материалов, с учетом стоимости металла) | N94: Изготовление защиты АКБ | O94: 0.033 | P94: =IF(OR(L94="3.3.1.", L94="3.3.2.", L94="3.3.3.", L94="3.1.1.", L94="3.1.2.", L94="3.4.1.", L94="3.4.2."), 0, VLOOKUP(L94, Работы!$A$3:$D$184, 4, 0)) -> 64605 | T94: =IF(OR(L94="3.3.1.", L94="3.3.2.", L94="3.3.3."), VLOOKUP(L94, Работы!$A$3:$D$184, 4, 0), 0) -> 0 | U94: =IF(OR(L94="3.1.1."), VLOOKUP(L94, Работы!$A$3:$D$184, 4, 0), 0) -> 0 | V94: =IF(OR(L94="3.1.2."), VLOOKUP(L94, Работы!$A$3:$D$184, 4, 0), 0) -> 0 | Y94: =IF(OR(L94="3.2.1.", L94="3.2.2."), VLOOKUP(L94, Работы!$A$3:$D$184, 4, 0), 0) -> 0 | Z94: =IF(OR(L94="3.4.1.", L94="3.4.2."), VLOOKUP(L94, Работы!$A$3:$D$184, 4, 0), 0) -> 0 | AA94: =P94*O94+Q94*T94+R94*T94+S94*T94+U94+V94+W94*Y94+X94*Y94+Z94 -> 2131.965 | AE94: =AC94*AD94 -> 0 | AF94: =C94*Работы!$D$180 -> 0 | AG94: =AA94+AE94+AF94+AL94+AM94 -> 2131.965 | AJ94: =AG94-AA94*AI94 -> 2131.965 | AL94: =IF(OR(E94="да"), 4040, 0) -> 0 | AM94: =IF(OR(D94="доп."), AA94*0.1, 0) -> 0
A95: =ROW(A95)-10 -> 85 | B95: RO0485 | C95: =VLOOKUP(B95, Расстояния!B:J, 9, 0) -> 43 | D95: =VLOOKUP(B95, Расстояния!B:K, 10, 0) -> осн. | E95: =VLOOKUP(B95, Расстояния!B:F, 5, 0) -> нет | H95: 46099.552 | I95: 46099.622 | J95: Баженов | L95: 1.1. | M95: =VLOOKUP(L95, Работы!A:B, 2, 0) -> Техническое обслуживание БС | N95: Техническое обслуживание БС | O95: 1 | P95: =IF(OR(L95="3.3.1.", L95="3.3.2.", L95="3.3.3.", L95="3.1.1.", L95="3.1.2.", L95="3.4.1.", L95="3.4.2."), 0, VLOOKUP(L95, Работы!$A$3:$D$184, 4, 0)) -> 4143 | T95: =IF(OR(L95="3.3.1.", L95="3.3.2.", L95="3.3.3."), VLOOKUP(L95, Работы!$A$3:$D$184, 4, 0), 0) -> 0 | U95: =IF(OR(L95="3.1.1."), VLOOKUP(L95, Работы!$A$3:$D$184, 4, 0), 0) -> 0 | V95: =IF(OR(L95="3.1.2."), VLOOKUP(L95, Работы!$A$3:$D$184, 4, 0), 0) -> 0 | Y95: =IF(OR(L95="3.2.1.", L95="3.2.2."), VLOOKUP(L95, Работы!$A$3:$D$184, 4, 0), 0) -> 0 | Z95: =IF(OR(L95="3.4.1.", L95="3.4.2."), VLOOKUP(L95, Работы!$A$3:$D$184, 4, 0), 0) -> 0 | AA95: =P95*O95+Q95*T95+R95*T95+S95*T95+U95+V95+W95*Y95+X95*Y95+Z95 -> 4143 | AE95: =AC95*AD95 -> 0 | AF95: =C95*Работы!$D$180 -> 2313.83 | AG95: =AA95+AE95+AF95+AL95+AM95 -> 6456.83 | AJ95: =AG95-AA95*AI95 -> 6456.83 | AL95: =IF(OR(E95="да"), 4040, 0) -> 0 | AM95: =IF(OR(D95="доп."), AA95*0.1, 0) -> 0
A96: =ROW(A96)-10 -> 86 | B96: RO0487 | C96: =VLOOKUP(B96, Расстояния!B:J, 9, 0) -> 27 | D96: =VLOOKUP(B96, Расстояния!B:K, 10, 0) -> осн. | E96: =VLOOKUP(B96, Расстояния!B:F, 5, 0) -> нет | F96: WO06720288 | G96: 46105.34 | H96: 46105.397 | I96: 46105.397 | J96: Баженов | L96: 3.4.1. | M96: =VLOOKUP(L96, Работы!A:B, 2, 0) -> Стоимость отменённого вызова на Аварийно-восстановительные работы, заявка по которым получена в рабочее время | N96: Отмена | P96: =IF(OR(L96="3.3.1.", L96="3.3.2.", L96="3.3.3.", L96="3.1.1.", L96="3.1.2.", L96="3.4.1.", L96="3.4.2."), 0, VLOOKUP(L96, Работы!$A$3:$D$184, 4, 0)) -> 0 | T96: =IF(OR(L96="3.3.1.", L96="3.3.2.", L96="3.3.3."), VLOOKUP(L96, Работы!$A$3:$D$184, 4, 0), 0) -> 0 | U96: =IF(OR(L96="3.1.1."), VLOOKUP(L96, Работы!$A$3:$D$184, 4, 0), 0) -> 0 | V96: =IF(OR(L96="3.1.2."), VLOOKUP(L96, Работы!$A$3:$D$184, 4, 0), 0) -> 0 | Y96: =IF(OR(L96="3.2.1.", L96="3.2.2."), VLOOKUP(L96, Работы!$A$3:$D$184, 4, 0), 0) -> 0 | Z96: =IF(OR(L96="3.4.1.", L96="3.4.2."), VLOOKUP(L96, Работы!$A$3:$D$184, 4, 0), 0) -> 922 | AA96: =P96*O96+Q96*T96+R96*T96+S96*T96+U96+V96+W96*Y96+X96*Y96+Z96 -> 922 | AE96: =AC96*AD96 -> 0 | AF96: =C96*Работы!$D$180 -> 1452.87 | AG96: =AA96+AE96+AF96+AL96+AM96 -> 2374.87 | AJ96: =AG96-AA96*AI96 -> 2374.87 | AL96: =IF(OR(E96="да"), 4040, 0) -> 0 | AM96: =IF(OR(D96="доп."), AA96*0.1, 0) -> 0
A97: =ROW(A97)-10 -> 87 | B97: RO0487 | C97: =VLOOKUP(B97, Расстояния!B:J, 9, 0) -> 27 | D97: =VLOOKUP(B97, Расстояния!B:K, 10, 0) -> осн. | E97: =VLOOKUP(B97, Расстояния!B:F, 5, 0) -> нет | F97: WO06720624 | G97: 46105.438 | H97: 46105.535 | I97: 46105.626 | J97: Баженов | L97: 5.17. | M97: =VLOOKUP(L97, Работы!A:B, 2, 0) -> Настройка, прописка ИБП, включая подключение и тестирование внешних аварий | N97: Настройка СП | O97: 1 | P97: =IF(OR(L97="3.3.1.", L97="3.3.2.", L97="3.3.3.", L97="3.1.1.", L97="3.1.2.", L97="3.4.1.", L97="3.4.2."), 0, VLOOKUP(L97, Работы!$A$3:$D$184, 4, 0)) -> 735 | T97: =IF(OR(L97="3.3.1.", L97="3.3.2.", L97="3.3.3."), VLOOKUP(L97, Работы!$A$3:$D$184, 4, 0), 0) -> 0 | U97: =IF(OR(L97="3.1.1."), VLOOKUP(L97, Работы!$A$3:$D$184, 4, 0), 0) -> 0 | V97: =IF(OR(L97="3.1.2."), VLOOKUP(L97, Работы!$A$3:$D$184, 4, 0), 0) -> 0 | Y97: =IF(OR(L97="3.2.1.", L97="3.2.2."), VLOOKUP(L97, Работы!$A$3:$D$184, 4, 0), 0) -> 0 | Z97: =IF(OR(L97="3.4.1.", L97="3.4.2."), VLOOKUP(L97, Работы!$A$3:$D$184, 4, 0), 0) -> 0 | AA97: =P97*O97+Q97*T97+R97*T97+S97*T97+U97+V97+W97*Y97+X97*Y97+Z97 -> 735 | AE97: =AC97*AD97 -> 0 | AF97: =C97*Работы!$D$180 -> 1452.87 | AG97: =AA97+AE97+AF97+AL97+AM97 -> 2187.87 | AJ97: =AG97-AA97*AI97 -> 2187.87 | AL97: =IF(OR(E97="да"), 4040, 0) -> 0 | AM97: =IF(OR(D97="доп."), AA97*0.1, 0) -> 0
A98: =ROW(A98)-10 -> 88 | B98: RO0487 | C98: 0 | D98: =VLOOKUP(B98, Расстояния!B:K, 10, 0) -> осн. | E98: =VLOOKUP(B98, Расстояния!B:F, 5, 0) -> нет | F98: WO06720624 | G98: 46105.438 | H98: 46105.535 | I98: 46105.626 | J98: Баженов | L98: 5.3. | M98: =VLOOKUP(L98, Работы!A:B, 2, 0) -> Осмотр и тестирование аккумуляторов источников бесперебойного питания (ИБП) по упрощенной методике (разряд на штатную нагрузку ИБП до 2 (двух) часов с измерением их параметров) | N98: Видеотест АКБ | O98: 1 | P98: =IF(OR(L98="3.3.1.", L98="3.3.2.", L98="3.3.3.", L98="3.1.1.", L98="3.1.2.", L98="3.4.1.", L98="3.4.2."), 0, VLOOKUP(L98, Работы!$A$3:$D$184, 4, 0)) -> 1778 | T98: =IF(OR(L98="3.3.1.", L98="3.3.2.", L98="3.3.3."), VLOOKUP(L98, Работы!$A$3:$D$184, 4, 0), 0) -> 0 | U98: =IF(OR(L98="3.1.1."), VLOOKUP(L98, Работы!$A$3:$D$184, 4, 0), 0) -> 0 | V98: =IF(OR(L98="3.1.2."), VLOOKUP(L98, Работы!$A$3:$D$184, 4, 0), 0) -> 0 | Y98: =IF(OR(L98="3.2.1.", L98="3.2.2."), VLOOKUP(L98, Работы!$A$3:$D$184, 4, 0), 0) -> 0 | Z98: =IF(OR(L98="3.4.1.", L98="3.4.2."), VLOOKUP(L98, Работы!$A$3:$D$184, 4, 0), 0) -> 0 | AA98: =P98*O98+Q98*T98+R98*T98+S98*T98+U98+V98+W98*Y98+X98*Y98+Z98 -> 1778 | AE98: =AC98*AD98 -> 0 | AF98: =C98*Работы!$D$180 -> 0 | AG98: =AA98+AE98+AF98+AL98+AM98 -> 1778 | AJ98: =AG98-AA98*AI98 -> 1778 | AL98: =IF(OR(E98="да"), 4040, 0) -> 0 | AM98: =IF(OR(D98="доп."), AA98*0.1, 0) -> 0
A99: =ROW(A99)-10 -> 89 | B99: RO0487 | C99: 0 | D99: =VLOOKUP(B99, Расстояния!B:K, 10, 0) -> осн. | E99: =VLOOKUP(B99, Расстояния!B:F, 5, 0) -> нет | H99: 46105.535 | I99: 46105.626 | J99: Баженов | L99: 1.1. | M99: =VLOOKUP(L99, Работы!A:B, 2, 0) -> Техническое обслуживание БС | N99: Техническое обслуживание БС | O99: 1 | P99: =IF(OR(L99="3.3.1.", L99="3.3.2.", L99="3.3.3.", L99="3.1.1.", L99="3.1.2.", L99="3.4.1.", L99="3.4.2."), 0, VLOOKUP(L99, Работы!$A$3:$D$184, 4, 0)) -> 4143 | T99: =IF(OR(L99="3.3.1.", L99="3.3.2.", L99="3.3.3."), VLOOKUP(L99, Работы!$A$3:$D$184, 4, 0), 0) -> 0 | U99: =IF(OR(L99="3.1.1."), VLOOKUP(L99, Работы!$A$3:$D$184, 4, 0), 0) -> 0 | V99: =IF(OR(L99="3.1.2."), VLOOKUP(L99, Работы!$A$3:$D$184, 4, 0), 0) -> 0 | Y99: =IF(OR(L99="3.2.1.", L99="3.2.2."), VLOOKUP(L99, Работы!$A$3:$D$184, 4, 0), 0) -> 0 | Z99: =IF(OR(L99="3.4.1.", L99="3.4.2."), VLOOKUP(L99, Работы!$A$3:$D$184, 4, 0), 0) -> 0 | AA99: =P99*O99+Q99*T99+R99*T99+S99*T99+U99+V99+W99*Y99+X99*Y99+Z99 -> 4143 | AE99: =AC99*AD99 -> 0 | AF99: =C99*Работы!$D$180 -> 0 | AG99: =AA99+AE99+AF99+AL99+AM99 -> 4143 | AJ99: =AG99-AA99*AI99 -> 4143 | AL99: =IF(OR(E99="да"), 4040, 0) -> 0 | AM99: =IF(OR(D99="доп."), AA99*0.1, 0) -> 0
A100: =ROW(A100)-10 -> 90 | B100: RO0492 | C100: 115 | D100: =VLOOKUP(B100, Расстояния!B:K, 10, 0) -> осн. | E100: =VLOOKUP(B100, Расстояния!B:F, 5, 0) -> нет | F100: WO06715863 | G100: 46099.685 | H100: 46100.5 | I100: 46100.604 | J100: Юкин | L100: 3.1.1. | M100: =VLOOKUP(L100, Работы!A:B, 2, 0) -> Стоимость аварийно-восстановительных работ, заявка по которым получена в течение рабочего времени | N100: Осмотр территории, Выезд из Ростова. | P100: =IF(OR(L100="3.3.1.", L100="3.3.2.", L100="3.3.3.", L100="3.1.1.", L100="3.1.2.", L100="3.4.1.", L100="3.4.2."), 0, VLOOKUP(L100, Работы!$A$3:$D$184, 4, 0)) -> 0 | T100: =IF(OR(L100="3.3.1.", L100="3.3.2.", L100="3.3.3."), VLOOKUP(L100, Работы!$A$3:$D$184, 4, 0), 0) -> 0 | U100: =IF(OR(L100="3.1.1."), VLOOKUP(L100, Работы!$A$3:$D$184, 4, 0), 0) -> 3956 | V100: =IF(OR(L100="3.1.2."), VLOOKUP(L100, Работы!$A$3:$D$184, 4, 0), 0) -> 0 | Y100: =IF(OR(L100="3.2.1.", L100="3.2.2."), VLOOKUP(L100, Работы!$A$3:$D$184, 4, 0), 0) -> 0 | Z100: =IF(OR(L100="3.4.1.", L100="3.4.2."), VLOOKUP(L100, Работы!$A$3:$D$184, 4, 0), 0) -> 0 | AA100: =P100*O100+Q100*T100+R100*T100+S100*T100+U100+V100+W100*Y100+X100*Y100+Z100 -> 3956 | AE100: =AC100*AD100 -> 0 | AF100: =C100*Работы!$D$180 -> 6188.15 | AG100: =AA100+AE100+AF100+AL100+AM100 -> 10144.15 | AJ100: =AG100-AA100*AI100 -> 10144.15 | AL100: =IF(OR(E100="да"), 4040, 0) -> 0 | AM100: =IF(OR(D100="доп."), AA100*0.1, 0) -> 0
A101: =ROW(A101)-10 -> 91 | B101: RO0494 | C101: =VLOOKUP(B101, Расстояния!B:J, 9, 0) -> 81 | D101: =VLOOKUP(B101, Расстояния!B:K, 10, 0) -> осн. | E101: =VLOOKUP(B101, Расстояния!B:F, 5, 0) -> нет | F101: WO06713622 | G101: 46097.706 | H101: 46097.806 | I101: 46097.84 | J101: Баженов | L101: 3.1.1. | M101: =VLOOKUP(L101, Работы!A:B, 2, 0) -> Стоимость аварийно-восстановительных работ, заявка по которым получена в течение рабочего времени | N101: Диагностика БС | P101: =IF(OR(L101="3.3.1.", L101="3.3.2.", L101="3.3.3.", L101="3.1.1.", L101="3.1.2.", L101="3.4.1.", L101="3.4.2."), 0, VLOOKUP(L101, Работы!$A$3:$D$184, 4, 0)) -> 0 | T101: =IF(OR(L101="3.3.1.", L101="3.3.2.", L101="3.3.3."), VLOOKUP(L101, Работы!$A$3:$D$184, 4, 0), 0) -> 0 | U101: =IF(OR(L101="3.1.1."), VLOOKUP(L101, Работы!$A$3:$D$184, 4, 0), 0) -> 3956 | V101: =IF(OR(L101="3.1.2."), VLOOKUP(L101, Работы!$A$3:$D$184, 4, 0), 0) -> 0 | Y101: =IF(OR(L101="3.2.1.", L101="3.2.2."), VLOOKUP(L101, Работы!$A$3:$D$184, 4, 0), 0) -> 0 | Z101: =IF(OR(L101="3.4.1.", L101="3.4.2."), VLOOKUP(L101, Работы!$A$3:$D$184, 4, 0), 0) -> 0 | AA101: =P101*O101+Q101*T101+R101*T101+S101*T101+U101+V101+W101*Y101+X101*Y101+Z101 -> 3956 | AE101: =AC101*AD101 -> 0 | AF101: =C101*Работы!$D$180 -> 4358.61 | AG101: =AA101+AE101+AF101+AL101+AM101 -> 8314.61 | AJ101: =AG101-AA101*AI101 -> 8314.61 | AL101: =IF(OR(E101="да"), 4040, 0) -> 0 | AM101: =IF(OR(D101="доп."), AA101*0.1, 0) -> 0
A102: =ROW(A102)-10 -> 92 | B102: RO0495 | C102: 0 | D102: =VLOOKUP(B102, Расстояния!B:K, 10, 0) -> осн. | E102: =VLOOKUP(B102, Расстояния!B:F, 5, 0) -> нет | F102: WO06713153 | G102: 46097.483 | H102: 46094.477 | I102: 46094.554 | J102: Баженов | L102: 10.3. | M102: =VLOOKUP(L102, Работы!A:B, 2, 0) -> Иные работы/услуги в отношении одного Объекта по одному обращению Заказчика в течение рабочего времени*****, независимо от количества представителей Подрядчика, участвующих в выполнении таких Работ на одном Объекте | N102: Монтаж проводов для АКБ*2 | O102: 1 | P102: =IF(OR(L102="3.3.1.", L102="3.3.2.", L102="3.3.3.", L102="3.1.1.", L102="3.1.2.", L102="3.4.1.", L102="3.4.2."), 0, VLOOKUP(L102, Работы!$A$3:$D$184, 4, 0)) -> 735 | T102: =IF(OR(L102="3.3.1.", L102="3.3.2.", L102="3.3.3."), VLOOKUP(L102, Работы!$A$3:$D$184, 4, 0), 0) -> 0 | U102: =IF(OR(L102="3.1.1."), VLOOKUP(L102, Работы!$A$3:$D$184, 4, 0), 0) -> 0 | V102: =IF(OR(L102="3.1.2."), VLOOKUP(L102, Работы!$A$3:$D$184, 4, 0), 0) -> 0 | Y102: =IF(OR(L102="3.2.1.", L102="3.2.2."), VLOOKUP(L102, Работы!$A$3:$D$184, 4, 0), 0) -> 0 | Z102: =IF(OR(L102="3.4.1.", L102="3.4.2."), VLOOKUP(L102, Работы!$A$3:$D$184, 4, 0), 0) -> 0 | AA102: =P102*O102+Q102*T102+R102*T102+S102*T102+U102+V102+W102*Y102+X102*Y102+Z102 -> 735 | AE102: =AC102*AD102 -> 0 | AF102: =C102*Работы!$D$180 -> 0 | AG102: =AA102+AE102+AF102+AL102+AM102 -> 735 | AJ102: =AG102-AA102*AI102 -> 735 | AL102: =IF(OR(E102="да"), 4040, 0) -> 0 | AM102: =IF(OR(D102="доп."), AA102*0.1, 0) -> 0
...

Sheet СИМ
K1: ПРИЛОЖЕНИЕ № 4 (Справка)
K2: к Договору на выполнение работ
F3: 8/2 | K3: № ТО-ЭСТ-РО-2025 от «01» сентября 2025 г.
A5: Справка об использовании оборудования (материалов) к Акту выполненных работ № от
A7: г.Ростов-на-Дону | H7: =КС2!Y23 -> 0
A8: Общество с ограниченной ответственностью «Т2-Мобайл» (Ростовский филиал) (сокращенное наименование ООО «Т2 Мобайл» Ростовский филиал), юридическое лицо, зарегистрированное по адресу: Российская Федерация, 108811, г. Москва, поселение Московский, Киевское шоссе 22-й километр, домовладение 6, строение 1, этаж 5, комната 33, в лице Руководителя Макрорегионального филиала "Юг" Общества с ограниченной ответственностью «Т2 Мобайл» Мотлях Константина Геннадьевича, действующего на основании доверенности №77/447-н/77-2024-3-169 от 15.02.2024 г., именуемое в дальнейшем «Заказчик», с одной стороны, и Общество с ограниченной ответственностью «Эффективные сервисные технологии», юридическое лицо, зарегистрированное по адресу: Российская Федерация, 350005, Краснодарский край, г. Краснодар, ул. им. Александра Покрышкина д. 25/А, корп.2, помещ. 21,22,23, в лице Директора Нестеренко Евгения Викторовича, действующего на основании Устава, именуемое в дальнейшем «Подрядчик», с другой стороны, совместно именуемые «Стороны», а по отдельности - «Сторона», составили Справку об использовании Оборудования (Материалов)
A9: к Акту выполненных работ № | C9: =КС2!P23 -> ОРЕХ 2612-2613 | D9: от | E9: =КС2!Y23 -> 0 | F9: к Договору на выполнение работ № ТО-ЭСТ-РО-2025
A10: от 01.09.2025 (далее – Договор), о нижеследующем:
A11: 1. Подрядчик при выполнении Работ использовал (смонтировал) Оборудование (Материалы), представленное Заказчиком, а именно:
A12: № п/п | B12: № Объекта | C12: Наименование Работ | D12: Наименование израсходованного Оборудования (Материалов) | E12: Ед. измерения | F12: Количество | G12: Примечание
A13: 1 | B13: RO0930 | C13: Замена джампера | D13: Джампер??? | E13: шт | F13: 1 | G13: новое
A14: 2 | B14: RO0326 | C14: Замена SFP | D14: SFP??? | E14: шт | F14: 1 | G14: новое
A15: 3 | B15: RO0175 | C15: Замена джампера | D15: Джампер??? | E15: шт | F15: 1 | G15: новое
A16: 4 | B16: RO0175 | C16: Замена SFP | D16: SFP??? | E16: шт | F16: 2 | G16: новое
A17: 6
A18: 7
A19: 2. Подрядчик при выполнении Работ использовал (смонтировал) Оборудование (Материалы), приобретенное Подрядчиком за счет Заказчика,
A20: а именно:
A21: № п/п | B21: № Объекта | C21: Наименование Работ | D21: Наименование израсходованного Оборудования (Материалов) | E21: Дата согласования стоимости с Заказчиком | F21: Стоимость, без НДС, руб. | G21: Сумма НДС, руб. | H21: Стоимость с НДС, руб. | I21: Ед. изм. | J21: Кол-во | K21: Примечание
A22: 1 | B22: -
A24: 3. Подрядчик при выполнении Работ демонтировал следующее оборудование Объекта и доставил его на склад Заказчика:
A26: № п/п | B26: № Объекта | C26: Наименование Работ | D26: Наименование Оборудования | E26: Заводской № | F26: Ед. измерения | G26: Количество | H26: Примечание
A27: 1
A28: 2
A29: 3
A30: 4
D32: ПОДПИСИ СТОРОН
B34: ПОДРЯДЧИК | F34: ЗАКАЗЧИК
B36: =ИНФ!C12 -> Директор ООО "ЭСТ" | F36: =ИНФ!C15 -> Директор макрорегионального филиала "Юг" ОOO "Т2 Мобайл"
B38: ________________ | C38: =ИНФ!C11 -> Нестеренко Е.В. | F38: _________________ | H38: =ИНФ!C14 -> Мотлях К.Г.
B40: МП | F40: МП
B69: Модуль SFP 1000BASE-SX iPasolink
B70: SFP GIGE BASE-T RJ45
B71: Коаксиальный кабель 8D-FB
B72: Разъем N-Type Connector (8D)
B73: Разъем TNC-Type Connector (8D)
B77: Джампер1/2 highflex 7/16m-7/16 90°m 5.0m
B78: Джампер1/2 highflex 7/16m-7/16 90°m2.0m
B79: Разъем Teracom 716 Famale(7/8)
B80: Разъем Teracom 716 Male(7/8)
B81: Разъем Teracom 716 Famale(1/2)
B82: Разъем Teracom 716 Male(1/2)
B83: Разъем N-Type Connector (8D)
... B91: Кабель коммутационный 2xRJ45

Sheet КС2
AG1: Унифицированная форма № КС - 2 Утверждена постановлением Госкомстата России от 11.11.99 № 100
AP2: Код
AG3: Форма по ОКУД | AP3: 0322001
A5: Инвестор | AK5: по ОКПО
R6: (организация, адрес, телефон, факс) | AP6: =ИНФ!C17 -> 17872715
A7: Заказчик (Генподрядчик): | K7: =ИНФ!C16 -> ООО "Т2 Мобайл", 108811, г. Москва, Киевское шоссе 22-й километр, домовладение 6, строение 1, этаж 5, комната 33 | AK7: по ОКПО
R8: (организация, адрес, телефон, факс) | AP8: =ИНФ!C13 -> 91130665
A9: Подрядчик (Субподрядчик): | K9: =ИНФ!C10 -> ООО "ЭСТ", 350005, Краснодарский край, г. Краснодар, ул. им. Александра Покрышкина д. 25/А, корп.2, помещ. 21,22,23 | AK9: по ОКПО
R10: (организация, адрес, телефон, факс)
A11: Стройка
M12: (наименование, адрес)
A13: Объект
M14: (наименование, адрес) | AC14: Вид деятельности по ОКДП
AC15: Договор подряда (контракт) | AK15: номер | AP15: =ИНФ!C2 -> ТО-ЭСТ-РО-2025
AK16: дата | AP16: =ИНФ!C3 -> 45901
AC17: Доп.Соглашение | AK17: номер | AP17: =ИНФ!C4 -> ОРЕХ 2612-2613
AK18: дата | AP18: =ИНФ!D2 -> 46111
AJ19: Вид операции
P21: Номер документа | Y21: Дата составления | AJ21: Отчетный период
AJ22: с | AN22: по
P23: =ИНФ!C4 -> ОРЕХ 2612-2613 | AJ23: =ИНФ!C6 -> 16.03.2026г | AN23: =ИНФ!C7 -> 29.03.2026г.
V25: АКТ
P26: О ПРИЕМКЕ ВЫПОЛНЕННЫХ РАБОТ
B28: Сметная (договорная) стоимость в соответствии с договором подряда (субподряда) | AH28: =AS39 -> 1397468.7 | AP28: руб.
A30: Номер по порядку | D30: Код затрат | G30: Наименование работ | AD30: Номер единичной расценки | AG30: Единица измерения | AJ30: Выполнено работ
AJ31: Количество | AN31: цена за единицу, рубль | AS31: стоимость, рубль
A32: 1 | D32: 2 | G32: 3 | AD32: 4 | AG32: 5 | AJ32: 6 | AN32: 7 | AS32: 8
A33: Выполненные работы:
A34: 1 | G34: ="Отчет по аварийно восстановительным работам "&ИНФ!C4&" " -> Отчет по аварийно восстановительным работам ОРЕХ 2612-2613 | AG34: шт. | AJ34: 1 | AN34: =Opex!AJ227 -> 1145466.1 | AS34: =AJ34*AN34 -> 1145466.1
A35: Материалы
AD37: Итого | AJ37: 1 | AN37: Х | AS37: =ROUND(AS34, 2) -> 1145466.1
AD38: Сумма НДС | AJ38: 1 | AN38: Х | AS38: =AS37*0.22 -> 252002.55
AB39: Всего с учетом НДС | AJ39: 1 | AN39: Х | AS39: =ROUND(AS37+AS38, 2) -> 1397468.7
H44: =ИНФ!C12 -> Директор ООО "ЭСТ"
A48: От исполнителя: | AI48: =ИНФ!C11 -> Нестеренко Е.В.
AB50: М.П.
H59: =ИНФ!C15 -> Директор макрорегионального филиала "Юг" ОOO "Т2 Мобайл"
A61: От заказчика: | AI61: =ИНФ!C14 -> Мотлях К.Г.
AB63: М.П.

Sheet КС3
G1: Унифицированная форма № КС-3
G2: Утверждена постановлением Госкомстата России
G3: от 11 ноября 1999г. № 100
F5: Код
E6: Форма по ОКУД | F6: 322001
A7: Инвестор | E7: по ОКПО
A9: Заказчик | B9: =ИНФ!C16 -> ООО "Т2 Мобайл", 108811, г. Москва, Киевское шоссе 22-й километр, домовладение 6, строение 1, этаж 5, комната 33 | E9: по ОКПО | F9: =ИНФ!C17 -> 17872715
A11: Подрядчик | B11: =ИНФ!C10 -> ООО "ЭСТ", 350005, Краснодарский край, г. Краснодар, ул. им. Александра Покрышкина д. 25/А, корп.2, помещ. 21,22,23 | E11: по ОКПО | F11: =ИНФ!C13 -> 91130665
A13: Стройка
A15: Объект | E15: Вид деятельности по ОКДП
D16: Договор подряда (контракт) | E16: номер | F16: =ИНФ!C2 -> ТО-ЭСТ-РО-2025
E17: дата | F17: =ИНФ!C3 -> 45901
E18: номер | F18: =ИНФ!C4 -> ОРЕХ 2612-2613
E19: дата | F19: =ИНФ!D2 -> 46111
E20: Вид операции
C22: Номер документа | D22: Дата составления | F22: Отчетный период
F23: с | G23: по
C24: =ИНФ!C4 -> ОРЕХ 2612-2613 | D24: =КС2!Y23 -> 0 | F24: =ИНФ!C6 -> 16.03.2026г | G24: =ИНФ!C7 -> 29.03.2026г.
B25: СПРАВКА
B26: О СТОИМОСТИ ВЫПОЛНЕННЫХ РАБОТ И ЗАТРАТ
A29: Номер по порядку | B29: Наименование пусковых комплексов, этапов, объектов видов выполненных работ, обрудования и затрат | C29: Код | E29: Стоимость выполненных работ и затрат, руб.
E30: с начала проведения работ | F30: с начала года | G30: в том числе за отчетный период
A31: 1 | B31: 2 | C31: 3 | E31: 4 | F31: 5 | G31: 6
B32: Всего работ и затрат, включаемых в стоимость работ | E32: =КС2!AS37 -> 1145466.1 | F32: =E32 -> 1145466.1 | G32: =F32 -> 1145466.1
B33: в том числе:
A34: 1 | B34: ="Отчет по аварийно восстановительным работам "&ИНФ!C4&" " -> Отчет по аварийно восстановительным работам ОРЕХ 2612-2613 | E34: =E32 -> 1145466.1 | F34: =E34 -> 1145466.1 | G34: =E34 -> 1145466.1
A35: 2 | B35: Стоимость материалов | E35: 0 | F35: =E35 -> 0 | G35: =E35 -> 0
F36: Итого | G36: =G32 -> 1145466.1
F37: Сумма НДС | G37: =КС2!AS38 -> 252002.55
F38: Всего с учетом НДС | G38: =G36+G37 -> 1397468.7
A42: Заказчик
B43: =ИНФ!C15 -> Директор макрорегионального филиала "Юг" ОOO "Т2 Мобайл" | E43: =ИНФ!C14 -> Мотлях К.Г.
D44: подпись
B45: М.П.
A49: Подрядчик
B50: =ИНФ!C12 -> Директор ООО "ЭСТ" | E50: =ИНФ!C11 -> Нестеренко Е.В.
D51: подпись
B52: М.П.
